Workbook

Sheet Setup
A1: La Cata – Control Total (LMF + DF + SJM)
A2: Concepto | B2: Valor | D2: Notas | G2: Ubicaciones
A3: Ubicación 1 | B3: La Cata LMF | D3: Color: Azul | G3: La Cata LMF
A4: Ubicación 2 | B4: La Cata DF | D4: Color: Verde | G4: La Cata DF
A5: Ubicación 3 | B5: La Cata SJM | D5: Color: Naranja | G5: La Cata SJM
A6: Fee Tarjeta | B6: 0.0345 | D6: 3.45% comisión bancaria | G6: AMBAS
A7: ITBIS % | B7: 0.18 | D7: Solo ventas gravadas (no alcohol)
A8: % Empresa | B8: 0.5 | D8: Distribución utilidades
A9: % Socio A | B9: 0.25 | D9: Distribución utilidades
A10: % Socio B | B10: 0.25 | D10: Distribución utilidades

Sheet Ventas Diarias
A1: FECHA | B1: UBICACION | C1: EFECTIVO | D1: TARJETA (BRUTA) | E1: FEE TARJETA (3.45%) | F1: TARJETA NETA | G1: TRANSFERENCIAS | H1: PEDIDOS YA | I1: NOTAS DE CREDITO (-) | J1: TOTAL COBRADO CON ITBS | K1: VENTAS GRABADAS (BASE SIN ITBS) | L1: ITBS COBRADO | M1: VENTAS SIN ITBIS (para utilidad) | N1: DEPOSITO EFECTIVO (SEMANAL) | O1: NOTAS
A2: 46023 | B2: La Cata LMF | C2: 561911.56 | D2: 191788.96 | E2: =D2*Setup!$B$6 | F2: =D2-E2 | G2: 0 | I2: 705 | J2: =C2+F2+G2-I2 | L2: =K2*Setup!$B$7 | M2: =J2-L2
A3: 46023 | B3: La Cata DF | C3: 16502.6 | D3: 15265 | E3: =D3*Setup!$B$6 | F3: =D3-E3 | G3: 0 | I3: 0 | J3: =C3+F3+G3-I3 | L3: =K3*Setup!$B$7 | M3: =J3-L3
A4: 46024 | B4: La Cata LMF | C4: 243603 | D4: 126392 | E4: =D4*Setup!$B$6 | F4: =D4-E4 | G4: 7890 | I4: 395 | J4: =C4+F4+G4-I4 | L4: =K4*Setup!$B$7 | M4: =J4-L4
A5: 46024 | B5: La Cata DF | C5: 3875 | D5: 2080 | E5: =D5*Setup!$B$6 | F5: =D5-E5 | G5: 0 | I5: 0 | J5: =C5+F5+G5-I5 | L5: =K5*Setup!$B$7 | M5: =J5-L5
A6: 46025 | B6: La Cata LMF | C6: 111795.61 | D6: 114720 | E6: =D6*Setup!$B$6 | F6: =D6-E6 | G6: 16502 | I6: 6219 | J6: =C6+F6+G6-I6 | L6: =K6*Setup!$B$7 | M6: =J6-L6
A7: 46025 | B7: La Cata DF | C7: 6495 | D7: 2695 | E7: =D7*Setup!$B$6 | F7: =D7-E7 | G7: 0 | I7: 0 | J7: =C7+F7+G7-I7 | L7: =K7*Setup!$B$7 | M7: =J7-L7
A8: 46026 | B8: La Cata LMF | C8: 150879 | D8: 94242 | E8: =D8*Setup!$B$6 | F8: =D8-E8 | G8: 2865 | I8: 0 | J8: =C8+F8+G8-I8 | L8: =K8*Setup!$B$7 | M8: =J8-L8
A9: 46026 | B9: La Cata DF | C9: 17995 | D9: 9272.6 | E9: =D9*Setup!$B$6 | F9: =D9-E9 | G9: 0 | I9: 0 | J9: =C9+F9+G9-I9 | L9: =K9*Setup!$B$7 | M9: =J9-L9
A10: 46027 | B10: La Cata LMF | C10: 54994 | D10: 22455 | E10: =D10*Setup!$B$6 | F10: =D10-E10 | G10: 645 | I10: 220 | J10: =C10+F10+G10-I10 | L10: =K10*Setup!$B$7 | M10: =J10-L10
A11: 46027 | B11: La Cata DF | C11: 6355 | D11: 650 | E11: =D11*Setup!$B$6 | F11: =D11-E11 | G11: 0 | I11: 0 | J11: =C11+F11+G11-I11 | L11: =K11*Setup!$B$7 | M11: =J11-L11
A12: 46028 | B12: La Cata LMF | C12: 45555 | D12: 13990 | E12: =D12*Setup!$B$6 | F12: =D12-E12 | G12: 1190 | I12: 0 | J12: =C12+F12+G12-I12 | L12: =K12*Setup!$B$7 | M12: =J12-L12 | N12: 511590
A13: 46028 | B13: La Cata DF | C13: 6055 | D13: 395 | E13: =D13*Setup!$B$6 | F13: =D13-E13 | G13: 0 | I13: 0 | J13: =C13+F13+G13-I13 | L13: =K13*Setup!$B$7 | M13: =J13-L13
A14: 46029 | B14: La Cata LMF | C14: 50380 | D14: 9300 | E14: =D14*Setup!$B$6 | F14: =D14-E14 | G14: 195 | I14: 0 | J14: =C14+F14+G14-I14 | L14: =K14*Setup!$B$7 | M14: =J14-L14
A15: 46029 | B15: La Cata DF | C15: 8160 | D15: 390 | E15: =D15*Setup!$B$6 | F15: =D15-E15 | G15: 0 | I15: 0 | J15: =C15+F15+G15-I15 | L15: =K15*Setup!$B$7 | M15: =J15-L15
A16: 46030 | B16: La Cata LMF | C16: 37165 | D16: 3720 | E16: =D16*Setup!$B$6 | F16: =D16-E16 | G16: 0 | I16: 0 | J16: =C16+F16+G16-I16 | L16: =K16*Setup!$B$7 | M16: =J16-L16
A17: 46030 | B17: La Cata DF | C17: 8080 | D17: 1485 | E17: =D17*Setup!$B$6 | F17: =D17-E17 | G17: 0 | I17: 0 | J17: =C17+F17+G17-I17 | L17: =K17*Setup!$B$7 | M17: =J17-L17
A18: 46031 | B18: La Cata LMF | C18: 34940 | D18: 34250 | E18: =D18*Setup!$B$6 | F18: =D18-E18 | G18: 1930 | I18: 0 | J18: =C18+F18+G18-I18 | L18: =K18*Setup!$B$7 | M18: =J18-L18
A19: 46031 | B19: La Cata DF | C19: 4805 | D19: 3050 | E19: =D19*Setup!$B$6 | F19: =D19-E19 | G19: 0 | I19: 0 | J19: =C19+F19+G19-I19 | L19: =K19*Setup!$B$7 | M19: =J19-L19
A20: 46032 | B20: La Cata LMF | C20: 78191 | D20: 28095 | E20: =D20*Setup!$B$6 | F20: =D20-E20 | G20: 0 | I20: 995 | J20: =C20+F20+G20-I20 | L20: =K20*Setup!$B$7 | M20: =J20-L20
A21: 46032 | B21: La Cata DF | C21: 16570 | D21: 11145 | E21: =D21*Setup!$B$6 | F21: =D21-E21 | G21: 0 | I21: 0 | J21: =C21+F21+G21-I21 | L21: =K21*Setup!$B$7 | M21: =J21-L21
A22: 46033 | B22: La Cata LMF | C22: 103865 | D22: 48035 | E22: =D22*Setup!$B$6 | F22: =D22-E22 | G22: 2325 | I22: 0 | J22: =C22+F22+G22-I22 | L22: =K22*Setup!$B$7 | M22: =J22-L22
A23: 46033 | B23: La Cata DF | C23: 9370 | D23: 4005 | E23: =D23*Setup!$B$6 | F23: =D23-E23 | G23: 0 | I23: 0 | J23: =C23+F23+G23-I23 | L23: =K23*Setup!$B$7 | M23: =J23-L23
A24: 46034 | B24: La Cata LMF | C24: 24400 | D24: 14880 | E24: =D24*Setup!$B$6 | F24: =D24-E24 | G24: 0 | I24: 870 | J24: =C24+F24+G24-I24 | L24: =K24*Setup!$B$7 | M24: =J24-L24 | N24: 408130
A25: 46034 | B25: La Cata DF | C25: 5010 | D25: 0 | E25: =D25*Setup!$B$6 | F25: =D25-E25 | G25: 0 | I25: 0 | J25: =C25+F25+G25-I25 | L25: =K25*Setup!$B$7 | M25: =J25-L25
A26: 46035 | B26: La Cata LMF | C26: 42075 | D26: 12823 | E26: =D26*Setup!$B$6 | F26: =D26-E26 | G26: 1350 | I26: 675 | J26: =C26+F26+G26-I26 | L26: =K26*Setup!$B$7 | M26: =J26-L26
A27: 46035 | B27: La Cata DF | C27: 0 | D27: 0 | E27: =D27*Setup!$B$6 | F27: =D27-E27 | G27: 0 | I27: 0 | J27: =C27+F27+G27-I27 | L27: =K27*Setup!$B$7 | M27: =J27-L27
A28: 46036 | B28: La Cata LMF | C28: 39490 | D28: 3100 | E28: =D28*Setup!$B$6 | F28: =D28-E28 | G28: 5125 | I28: 0 | J28: =C28+F28+G28-I28 | L28: =K28*Setup!$B$7 | M28: =J28-L28
A29: 46036 | B29: La Cata DF | C29: 8985 | D29: 990 | E29: =D29*Setup!$B$6 | F29: =D29-E29 | G29: 0 | I29: 0 | J29: =C29+F29+G29-I29 | L29: =K29*Setup!$B$7 | M29: =J29-L29
A30: 46037 | B30: La Cata LMF | C30: 27070 | D30: 30350 | E30: =D30*Setup!$B$6 | F30: =D30-E30 | G30: 0 | I30: 0 | J30: =C30+F30+G30-I30 | L30: =K30*Setup!$B$7 | M30: =J30-L30
A31: 46037 | B31: La Cata DF | C31: 5020 | D31: 2515 | E31: =D31*Setup!$B$6 | F31: =D31-E31 | G31: 0 | I31: 0 | J31: =C31+F31+G31-I31 | L31: =K31*Setup!$B$7 | M31: =J31-L31
A32: 46038 | B32: La Cata LMF | C32: 42968 | D32: 35085 | E32: =D32*Setup!$B$6 | F32: =D32-E32 | G32: 0 | I32: 0 | J32: =C32+F32+G32-I32 | L32: =K32*Setup!$B$7 | M32: =J32-L32
A33: 46038 | B33: La Cata DF | C33: 15315 | D33: 5585 | E33: =D33*Setup!$B$6 | F33: =D33-E33 | G33: 9000 | I33: 0 | J33: =C33+F33+G33-I33 | L33: =K33*Setup!$B$7 | M33: =J33-L33
A34: 46039 | B34: La Cata LMF | C34: 109222 | D34: 55501 | E34: =D34*Setup!$B$6 | F34: =D34-E34 | G34: 420 | I34: 820 | J34: =C34+F34+G34-I34 | L34: =K34*Setup!$B$7 | M34: =J34-L34
A35: 46039 | B35: La Cata DF | C35: 17110 | D35: 13045 | E35: =D35*Setup!$B$6 | F35: =D35-E35 | G35: 0 | I35: 0 | J35: =C35+F35+G35-I35 | L35: =K35*Setup!$B$7 | M35: =J35-L35
A36: 46040 | B36: La Cata LMF | C36: 102670 | D36: 29893 | E36: =D36*Setup!$B$6 | F36: =D36-E36 | G36: 900 | I36: 0 | J36: =C36+F36+G36-I36 | L36: =K36*Setup!$B$7 | M36: =J36-L36
A37: 46040 | B37: La Cata DF | C37: 26885 | D37: 15085 | E37: =D37*Setup!$B$6 | F37: =D37-E37 | G37: 735 | I37: 0 | J37: =C37+F37+G37-I37 | L37: =K37*Setup!$B$7 | M37: =J37-L37
A38: 46041 | B38: La Cata LMF | C38: 28194 | D38: 6985 | E38: =D38*Setup!$B$6 | F38: =D38-E38 | G38: 0 | I38: 0 | J38: =C38+F38+G38-I38 | L38: =K38*Setup!$B$7 | M38: =J38-L38 | N38: 387540
A39: 46041 | B39: La Cata DF | C39: 4480 | D39: 1465 | E39: =D39*Setup!$B$6 | F39: =D39-E39 | G39: 0 | I39: 0 | J39: =C39+F39+G39-I39 | L39: =K39*Setup!$B$7 | M39: =J39-L39
A40: 46042 | B40: La Cata LMF | C40: 39706 | D40: 20212 | E40: =D40*Setup!$B$6 | F40: =D40-E40 | G40: 1450 | I40: 0 | J40: =C40+F40+G40-I40 | L40: =K40*Setup!$B$7 | M40: =J40-L40
A41: 46042 | B41: La Cata DF | C41: 0 | D41: 0 | E41: =D41*Setup!$B$6 | F41: =D41-E41 | G41: 0 | I41: 0 | J41: =C41+F41+G41-I41 | L41: =K41*Setup!$B$7 | M41: =J41-L41
A42: 46043 | B42: La Cata LMF | C42: 192090 | D42: 56540 | E42: =D42*Setup!$B$6 | F42: =D42-E42 | G42: 14185 | I42: 0 | J42: =C42+F42+G42-I42 | L42: =K42*Setup!$B$7 | M42: =J42-L42
A43: 46043 | B43: La Cata DF | C43: 16530 | D43: 7590 | E43: =D43*Setup!$B$6 | F43: =D43-E43 | G43: 0 | I43: 0 | J43: =C43+F43+G43-I43 | L43: =K43*Setup!$B$7 | M43: =J43-L43
A44: 46044 | B44: La Cata LMF | C44: 37055 | D44: 10825 | E44: =D44*Setup!$B$6 | F44: =D44-E44 | G44: 0 | I44: 0 | J44: =C44+F44+G44-I44 | L44: =K44*Setup!$B$7 | M44: =J44-L44
A45: 46044 | B45: La Cata DF | C45: 6225 | D45: 1200 | E45: =D45*Setup!$B$6 | F45: =D45-E45 | G45: 0 | I45: 0 | J45: =C45+F45+G45-I45 | L45: =K45*Setup!$B$7 | M45: =J45-L45
A46: 46045 | B46: La Cata LMF | C46: 45155 | D46: 31475 | E46: =D46*Setup!$B$6 | F46: =D46-E46 | G46: 0 | I46: 1365 | J46: =C46+F46+G46-I46 | L46: =K46*Setup!$B$7 | M46: =J46-L46
A47: 46045 | B47: La Cata DF | C47: 12395 | D47: 6655 | E47: =D47*Setup!$B$6 | F47: =D47-E47 | G47: 0 | I47: 0 | J47: =C47+F47+G47-I47 | L47: =K47*Setup!$B$7 | M47: =J47-L47
A48: 46046 | B48: La Cata LMF | C48: 115685 | D48: 57585 | E48: =D48*Setup!$B$6 | F48: =D48-E48 | G48: 0 | I48: 0 | J48: =C48+F48+G48-I48 | L48: =K48*Setup!$B$7 | M48: =J48-L48
A49: 46046 | B49: La Cata DF | C49: 15180 | D49: 8170 | E49: =D49*Setup!$B$6 | F49: =D49-E49 | G49: 0 | I49: 0 | J49: =C49+F49+G49-I49 | L49: =K49*Setup!$B$7 | M49: =J49-L49
A50: 46047 | B50: La Cata LMF | C50: 164615 | D50: 70375 | E50: =D50*Setup!$B$6 | F50: =D50-E50 | G50: 80 | I50: 0 | J50: =C50+F50+G50-I50 | L50: =K50*Setup!$B$7 | M50: =J50-L50
... A53: 46048 | B53: La Cata DF | C53: 13870 | D53: 14715 | E53: =D53*Setup!$B$6 | F53: =D53-E53 | G53: 0 | I53: 0 | J53: =C53+F53+G53-I53 | L53: =K53*Setup!$B$7 | M53: =J53-L53
A54: 46049 | B54: La Cata LMF | C54: 48365 | D54: 21675 | E54: =D54*Setup!$B$6 | F54: =D54-E54 | G54: 1200 | I54: 0 | J54: =C54+F54+G54-I54 | L54: =K54*Setup!$B$7 | M54: =J54-L54 | N54: 624540
A55: 46049 | B55: La Cata DF | C55: 0 | D55: 0 | E55: =D55*Setup!$B$6 | F55: =D55-E55 | G55: 0 | I55: 0 | J55: =C55+F55+G55-I55 | L55: =K55*Setup!$B$7 | M55: =J55-L55
A56: 46050 | B56: La Cata LMF | C56: 41530 | D56: 10040 | E56: =D56*Setup!$B$6 | F56: =D56-E56 | G56: 0 | I56: 0 | J56: =C56+F56+G56-I56 | L56: =K56*Setup!$B$7 | M56: =J56-L56
A57: 46050 | B57: La Cata DF | C57: 5790 | D57: 230 | E57: =D57*Setup!$B$6 | F57: =D57-E57 | G57: 0 | I57: 0 | J57: =C57+F57+G57-I57 | L57: =K57*Setup!$B$7 | M57: =J57-L57
A58: 46051 | B58: La Cata LMF | C58: 45620 | D58: 14645 | E58: =D58*Setup!$B$6 | F58: =D58-E58 | G58: 1060 | I58: 0 | J58: =C58+F58+G58-I58 | L58: =K58*Setup!$B$7 | M58: =J58-L58
A59: 46051 | B59: La Cata DF | C59: 3940 | D59: 1720 | E59: =D59*Setup!$B$6 | F59: =D59-E59 | G59: 0 | I59: 0 | J59: =C59+F59+G59-I59 | L59: =K59*Setup!$B$7 | M59: =J59-L59
A60: 46052 | B60: La Cata LMF | C60: 80975 | D60: 12383 | E60: =D60*Setup!$B$6 | F60: =D60-E60 | G60: 628 | I60: 0 | J60: =C60+F60+G60-I60 | L60: =K60*Setup!$B$7 | M60: =J60-L60
A61: 46052 | B61: La Cata DF | C61: 20950 | D61: 18280 | E61: =D61*Setup!$B$6 | F61: =D61-E61 | G61: 870 | I61: 0 | J61: =C61+F61+G61-I61 | L61: =K61*Setup!$B$7 | M61: =J61-L61
A62: 46053 | B62: La Cata LMF | C62: 156755 | D62: 72317 | E62: =D62*Setup!$B$6 | F62: =D62-E62 | G62: 3065 | I62: 785 | J62: =C62+F62+G62-I62 | L62: =K62*Setup!$B$7 | M62: =J62-L62
A63: 46053 | B63: La Cata DF | C63: 24270 | D63: 13745 | E63: =D63*Setup!$B$6 | F63: =D63-E63 | G63: 0 | I63: 0 | J63: =C63+F63+G63-I63 | L63: =K63*Setup!$B$7 | M63: =J63-L63
A64: 46054 | B64: La Cata LMF | C64: 104285 | D64: 38550 | E64: =D64*Setup!$B$6 | F64: =D64-E64 | G64: 295 | I64: 0 | J64: =C64+F64+G64-I64 | L64: =K64*Setup!$B$7 | M64: =J64-L64
A65: 46054 | B65: La Cata DF | C65: 25805 | D65: 13850 | E65: =D65*Setup!$B$6 | F65: =D65-E65 | G65: 0 | I65: 0 | J65: =C65+F65+G65-I65 | L65: =K65*Setup!$B$7 | M65: =J65-L65
A66: 46055 | B66: La Cata LMF | C66: 30835 | D66: 3365 | E66: =D66*Setup!$B$6 | F66: =D66-E66 | G66: 330 | I66: 0 | J66: =C66+F66+G66-I66 | L66: =K66*Setup!$B$7 | M66: =J66-L66 | N66: 558930
A67: 46055 | B67: La Cata DF | C67: 5870 | D67: 1770 | E67: =D67*Setup!$B$6 | F67: =D67-E67 | G67: 860 | I67: 0 | J67: =C67+F67+G67-I67 | L67: =K67*Setup!$B$7 | M67: =J67-L67
A68: 46056 | B68: La Cata LMF | C68: 29290 | D68: 9465 | E68: =D68*Setup!$B$6 | F68: =D68-E68 | G68: 1770 | I68: 0 | J68: =C68+F68+G68-I68 | L68: =K68*Setup!$B$7 | M68: =J68-L68
A69: 46056 | B69: La Cata DF | C69: 0 | D69: 0 | E69: =D69*Setup!$B$6 | F69: =D69-E69 | G69: 0 | I69: 0 | J69: =C69+F69+G69-I69 | L69: =K69*Setup!$B$7 | M69: =J69-L69
A70: 46057 | B70: La Cata LMF | C70: 39235 | D70: 10805 | E70: =D70*Setup!$B$6 | F70: =D70-E70 | G70: 180081.34 | I70: 0 | J70: =C70+F70+G70-I70 | L70: =K70*Setup!$B$7 | M70: =J70-L70 | O70: $178,466.34 en Transferencia es el pago por visibilidad de UB.
A71: 46057 | B71: La Cata DF | C71: 8070 | D71: 3960 | E71: =D71*Setup!$B$6 | F71: =D71-E71 | G71: 0 | I71: 0 | J71: =C71+F71+G71-I71 | L71: =K71*Setup!$B$7 | M71: =J71-L71
A72: 46058 | B72: La Cata LMF | C72: 46625 | D72: 14135 | E72: =D72*Setup!$B$6 | F72: =D72-E72 | G72: 60 | I72: 0 | J72: =C72+F72+G72-I72 | L72: =K72*Setup!$B$7 | M72: =J72-L72
A73: 46058 | B73: La Cata DF | C73: 7025 | D73: 7145 | E73: =D73*Setup!$B$6 | F73: =D73-E73 | G73: 0 | I73: 0 | J73: =C73+F73+G73-I73 | L73: =K73*Setup!$B$7 | M73: =J73-L73
A74: 46059 | B74: La Cata LMF | C74: 78645 | D74: 14005 | E74: =D74*Setup!$B$6 | F74: =D74-E74 | G74: 240 | I74: 0 | J74: =C74+F74+G74-I74 | L74: =K74*Setup!$B$7 | M74: =J74-L74
A75: 46059 | B75: La Cata DF | C75: 16945 | D75: 7410 | E75: =D75*Setup!$B$6 | F75: =D75-E75 | G75: 0 | I75: 0 | J75: =C75+F75+G75-I75 | L75: =K75*Setup!$B$7 | M75: =J75-L75
A76: 46060 | B76: La Cata LMF | C76: 159986 | D76: 55915 | E76: =D76*Setup!$B$6 | F76: =D76-E76 | G76: 3940 | I76: 835 | J76: =C76+F76+G76-I76 | L76: =K76*Setup!$B$7 | M76: =J76-L76
A77: 46060 | B77: La Cata DF | C77: 15795 | D77: 4240 | E77: =D77*Setup!$B$6 | F77: =D77-E77 | G77: 0 | I77: 0 | J77: =C77+F77+G77-I77 | L77: =K77*Setup!$B$7 | M77: =J77-L77
A78: 46061 | B78: La Cata LMF | C78: 111155 | D78: 46793 | E78: =D78*Setup!$B$6 | F78: =D78-E78 | G78: 1650 | I78: 0 | J78: =C78+F78+G78-I78 | L78: =K78*Setup!$B$7 | M78: =J78-L78
A79: 46061 | B79: La Cata DF | C79: 19020 | D79: 6845 | E79: =D79*Setup!$B$6 | F79: =D79-E79 | G79: 0 | I79: 0 | J79: =C79+F79+G79-I79 | L79: =K79*Setup!$B$7 | M79: =J79-L79
A80: 46062 | B80: La Cata LMF | C80: 15085 | D80: 4425 | E80: =D80*Setup!$B$6 | F80: =D80-E80 | G80: 300 | I80: 0 | J80: =C80+F80+G80-I80 | L80: =K80*Setup!$B$7 | M80: =J80-L80 | N80: 501910
A81: 46062 | B81: La Cata DF | C81: 4510 | D81: 0 | E81: =D81*Setup!$B$6 | F81: =D81-E81 | G81: 0 | I81: 0 | J81: =C81+F81+G81-I81 | L81: =K81*Setup!$B$7 | M81: =J81-L81
A82: 46063 | B82: La Cata LMF | C82: 38700 | D82: 5875 | E82: =D82*Setup!$B$6 | F82: =D82-E82 | G82: 0 | I82: 0 | J82: =C82+F82+G82-I82 | L82: =K82*Setup!$B$7 | M82: =J82-L82
A83: 46063 | B83: La Cata DF | C83: 0 | D83: 0 | E83: =D83*Setup!$B$6 | F83: =D83-E83 | G83: 300 | I83: 0 | J83: =C83+F83+G83-I83 | L83: =K83*Setup!$B$7 | M83: =J83-L83
A84: 46064 | B84: La Cata LMF | C84: 39100 | D84: 11675 | E84: =D84*Setup!$B$6 | F84: =D84-E84 | G84: 1095 | I84: 0 | J84: =C84+F84+G84-I84 | L84: =K84*Setup!$B$7 | M84: =J84-L84
A85: 46064 | B85: La Cata DF | C85: 6360 | D85: 1190 | E85: =D85*Setup!$B$6 | F85: =D85-E85 | G85: 0 | I85: 0 | J85: =C85+F85+G85-I85 | L85: =K85*Setup!$B$7 | M85: =J85-L85
A86: 46065 | B86: La Cata LMF | C86: 32930 | D86: 8480 | E86: =D86*Setup!$B$6 | F86: =D86-E86 | G86: 0 | I86: 0 | J86: =C86+F86+G86-I86 | L86: =K86*Setup!$B$7 | M86: =J86-L86
A87: 46065 | B87: La Cata DF | C87: 10220 | D87: 3720 | E87: =D87*Setup!$B$6 | F87: =D87-E87 | G87: 0 | I87: 0 | J87: =C87+F87+G87-I87 | L87: =K87*Setup!$B$7 | M87: =J87-L87
A88: 46066 | B88: La Cata LMF | C88: 71695 | D88: 25825 | E88: =D88*Setup!$B$6 | F88: =D88-E88 | G88: 14205 | I88: 5400 | J88: =C88+F88+G88-I88 | L88: =K88*Setup!$B$7 | M88: =J88-L88
A89: 46066 | B89: La Cata DF | C89: 11240 | D89: 6385 | E89: =D89*Setup!$B$6 | F89: =D89-E89 | G89: 0 | I89: 0 | J89: =C89+F89+G89-I89 | L89: =K89*Setup!$B$7 | M89: =J89-L89
A90: 46067 | B90: La Cata LMF | C90: 208765 | D90: 60945 | E90: =D90*Setup!$B$6 | F90: =D90-E90 | G90: 1240 | I90: 0 | J90: =C90+F90+G90-I90 | L90: =K90*Setup!$B$7 | M90: =J90-L90
A91: 46067 | B91: La Cata DF | C91: 22574.12 | D91: 4085 | E91: =D91*Setup!$B$6 | F91: =D91-E91 | G91: 0 | I91: 0 | J91: =C91+F91+G91-I91 | L91: =K91*Setup!$B$7 | M91: =J91-L91
A92: 46068 | B92: La Cata LMF | C92: 121275 | D92: 37315 | E92: =D92*Setup!$B$6 | F92: =D92-E92 | G92: 18025 | I92: 7685 | J92: =C92+F92+G92-I92 | L92: =K92*Setup!$B$7 | M92: =J92-L92 | N92: 547155 | O92: Validar las transacciones de este dia
A93: 46068 | B93: La Cata DF | C93: 23795 | D93: 9440 | E93: =D93*Setup!$B$6 | F93: =D93-E93 | G93: 0 | I93: 0 | J93: =C93+F93+G93-I93 | L93: =K93*Setup!$B$7 | M93: =J93-L93
A94: 46069 | B94: La Cata LMF | C94: 25785 | D94: 3420 | E94: =D94*Setup!$B$6 | F94: =D94-E94 | G94: 13823 | I94: 0 | J94: =C94+F94+G94-I94 | L94: =K94*Setup!$B$7 | M94: =J94-L94
A95: 46069 | B95: La Cata DF | C95: 5690 | D95: 350 | E95: =D95*Setup!$B$6 | F95: =D95-E95 | G95: 0 | I95: 0 | J95: =C95+F95+G95-I95 | L95: =K95*Setup!$B$7 | M95: =J95-L95
A96: 46070 | B96: La Cata LMF | C96: 41845 | D96: 7775 | E96: =D96*Setup!$B$6 | F96: =D96-E96 | G96: 435 | I96: 0 | J96: =C96+F96+G96-I96 | L96: =K96*Setup!$B$7 | M96: =J96-L96
A97: 46070 | B97: La Cata DF | C97: 0 | D97: 0 | E97: =D97*Setup!$B$6 | F97: =D97-E97 | G97: 0 | I97: 0 | J97: =C97+F97+G97-I97 | L97: =K97*Setup!$B$7 | M97: =J97-L97
A98: 46071 | B98: La Cata LMF | C98: 34854 | D98: 7741 | E98: =D98*Setup!$B$6 | F98: =D98-E98 | G98: 0 | I98: 0 | J98: =C98+F98+G98-I98 | L98: =K98*Setup!$B$7 | M98: =J98-L98
A99: 46071 | B99: La Cata DF | C99: 12185 | D99: 850 | E99: =D99*Setup!$B$6 | F99: =D99-E99 | G99: 0 | I99: 0 | J99: =C99+F99+G99-I99 | L99: =K99*Setup!$B$7 | M99: =J99-L99
A100: 46072 | B100: La Cata LMF | C100: 27400 | D100: 7455 | E100: =D100*Setup!$B$6 | F100: =D100-E100 | G100: 165 | I100: 0 | J100: =C100+F100+G100-I100 | L100: =K100*Setup!$B$7 | M100: =J100-L100
A101: 46072 | B101: La Cata DF | C101: 6775 | D101: 3810 | E101: =D101*Setup!$B$6 | F101: =D101-E101 | G101: 0 | I101: 0 | J101: =C101+F101+G101-I101 | L101: =K101*Setup!$B$7 | M101: =J101-L101 | N101: 150000 | O101: Deposito 2-15 Febrero
A102: 46073 | B102: La Cata LMF | C102: 54655 | D102: 16205 | E102: =D102*Setup!$B$6 | F102: =D102-E102 | G102: 2380 | I102: 0 | J102: =C102+F102+G102-I102 | L102: =K102*Setup!$B$7 | M102: =J102-L102
...

Sheet Ventas Diarias Backup
A1: FECHA | B1: UBICACION | C1: EFECTIVO | D1: TARJETA (BRUTA) | E1: FEE TARJETA (3.45%) | F1: TARJETA NETA | G1: TRANSFERENCIAS | H1: PEDIDOS YA | I1: NOTAS DE CREDITO (-) | J1: TOTAL COBRADO CON ITBS | K1: VENTAS GRABADAS (BASE SIN ITBS) | L1: ITBS COBRADO | M1: VENTAS SIN ITBIS (para utilidad) | N1: DEPOSITO EFECTIVO (SEMANAL) | O1: NOTAS
A2: 46174 | B2: La Cata LMF | C2: 20725 | D2: 5905 | E2: =D2*Setup!$B$5 | F2: =D2-E2 | G2: 2365 | I2: 0 | J2: =C2+F2+G2-I2 | L2: =K2*Setup!$B$6 | M2: =J2-L2
A3: 46175 | B3: La Cata LMF | C3: 39077 | D3: 12420 | E3: =D3*Setup!$B$5 | F3: =D3-E3 | G3: 0 | I3: 0 | J3: =C3+F3+G3-I3 | L3: =K3*Setup!$B$6 | M3: =J3-L3
A4: 46176 | B4: La Cata LMF | C4: 54488 | D4: 13620 | E4: =D4*Setup!$B$5 | F4: =D4-E4 | G4: 1866 | I4: 0 | J4: =C4+F4+G4-I4 | L4: =K4*Setup!$B$6 | M4: =J4-L4
A5: 46177 | B5: La Cata LMF | C5: 104926 | D5: 46270 | E5: =D5*Setup!$B$5 | F5: =D5-E5 | G5: 3255 | I5: 0 | J5: =C5+F5+G5-I5 | L5: =K5*Setup!$B$6 | M5: =J5-L5
A6: 46178 | B6: La Cata LMF | C6: 0 | D6: 0 | E6: =D6*Setup!$B$5 | F6: =D6-E6 | G6: 0 | I6: 0 | J6: =C6+F6+G6-I6 | L6: =K6*Setup!$B$6 | M6: =J6-L6
A7: 46179 | B7: La Cata LMF | C7: 135910 | D7: 38305 | E7: =D7*Setup!$B$5 | F7: =D7-E7 | G7: 6875 | I7: 0 | J7: =C7+F7+G7-I7 | L7: =K7*Setup!$B$6 | M7: =J7-L7
A8: 46180 | B8: La Cata LMF | C8: 168335 | D8: 53835 | E8: =D8*Setup!$B$5 | F8: =D8-E8 | G8: 0 | I8: 0 | J8: =C8+F8+G8-I8 | L8: =K8*Setup!$B$6 | M8: =J8-L8
A9: 46181 | B9: La Cata LMF | C9: 20725 | D9: 5905 | E9: =D9*Setup!$B$5 | F9: =D9-E9 | G9: 2365 | I9: 0 | J9: =C9+F9+G9-I9 | L9: =K9*Setup!$B$6 | M9: =J9-L9 | N9: 623815
A10: 46182 | B10: La Cata LMF | C10: 33510 | D10: 11355 | E10: =D10*Setup!$B$5 | F10: =D10-E10 | G10: 0 | I10: 0 | J10: =C10+F10+G10-I10 | L10: =K10*Setup!$B$6 | M10: =J10-L10
A11: 46183 | B11: La Cata LMF | C11: 19035 | D11: 4460 | E11: =D11*Setup!$B$5 | F11: =D11-E11 | G11: 0 | I11: 0 | J11: =C11+F11+G11-I11 | L11: =K11*Setup!$B$6 | M11: =J11-L11
A12: 46184 | B12: La Cata LMF | C12: 14400 | D12: 9505 | E12: =D12*Setup!$B$5 | F12: =D12-E12 | G12: 0 | I12: 0 | J12: =C12+F12+G12-I12 | L12: =K12*Setup!$B$6 | M12: =J12-L12
A13: 46185 | B13: La Cata LMF | C13: 47335 | D13: 14035 | E13: =D13*Setup!$B$5 | F13: =D13-E13 | G13: 1290 | I13: 160 | J13: =C13+F13+G13-I13 | L13: =K13*Setup!$B$6 | M13: =J13-L13
A14: 46186 | B14: La Cata LMF | C14: 114934 | D14: 40440 | E14: =D14*Setup!$B$5 | F14: =D14-E14 | G14: 16775 | I14: 0 | J14: =C14+F14+G14-I14 | L14: =K14*Setup!$B$6 | M14: =J14-L14
A15: 46187 | B15: La Cata LMF | C15: 183535 | D15: 53845 | E15: =D15*Setup!$B$5 | F15: =D15-E15 | G15: 1740 | I15: 0 | J15: =C15+F15+G15-I15 | L15: =K15*Setup!$B$6 | M15: =J15-L15
A16: 46188 | B16: La Cata LMF | C16: 29567 | D16: 9435 | E16: =D16*Setup!$B$5 | F16: =D16-E16 | G16: 2765 | I16: 0 | J16: =C16+F16+G16-I16 | L16: =K16*Setup!$B$6 | M16: =J16-L16 | N16: 434840
A17: 46189 | B17: La Cata LMF | C17: 30559 | D17: 10346 | E17: =D17*Setup!$B$5 | F17: =D17-E17 | G17: 0 | I17: 0 | J17: =C17+F17+G17-I17 | L17: =K17*Setup!$B$6 | M17: =J17-L17
A18: 46190 | B18: La Cata LMF | C18: 37857 | D18: 27615 | E18: =D18*Setup!$B$5 | F18: =D18-E18 | G18: 0 | I18: 0 | J18: =C18+F18+G18-I18 | L18: =K18*Setup!$B$6 | M18: =J18-L18
A19: 46191 | B19: La Cata LMF | C19: 29700 | D19: 24095 | E19: =D19*Setup!$B$5 | F19: =D19-E19 | G19: 0 | I19: 0 | J19: =C19+F19+G19-I19 | L19: =K19*Setup!$B$6 | M19: =J19-L19
A20: 46192 | B20: La Cata LMF | C20: 65320 | D20: 37590 | E20: =D20*Setup!$B$5 | F20: =D20-E20 | G20: 420 | I20: 0 | J20: =C20+F20+G20-I20 | L20: =K20*Setup!$B$6 | M20: =J20-L20
A21: 46193 | B21: La Cata LMF | C21: 137440 | D21: 80635 | E21: =D21*Setup!$B$5 | F21: =D21-E21 | G21: 760 | I21: 0 | J21: =C21+F21+G21-I21 | L21: =K21*Setup!$B$6 | M21: =J21-L21
A22: 46194 | B22: La Cata LMF | C22: 151265 | D22: 65345 | E22: =D22*Setup!$B$5 | F22: =D22-E22 | G22: 3155 | I22: 0 | J22: =C22+F22+G22-I22 | L22: =K22*Setup!$B$6 | M22: =J22-L22
A23: 46195 | B23: La Cata LMF | C23: 24815 | D23: 16840 | E23: =D23*Setup!$B$5 | F23: =D23-E23 | G23: 600 | I23: 0 | J23: =C23+F23+G23-I23 | L23: =K23*Setup!$B$6 | M23: =J23-L23
A24: 46196 | B24: La Cata LMF | C24: 55010 | D24: 15505 | E24: =D24*Setup!$B$5 | F24: =D24-E24 | G24: 2660 | I24: 0 | J24: =C24+F24+G24-I24 | L24: =K24*Setup!$B$6 | M24: =J24-L24
A25: 46197 | B25: La Cata LMF | C25: 59190 | D25: 25428 | E25: =D25*Setup!$B$5 | F25: =D25-E25 | G25: 80 | I25: 0 | J25: =C25+F25+G25-I25 | L25: =K25*Setup!$B$6 | M25: =J25-L25
A26: 46198 | B26: La Cata LMF | C26: 54185 | D26: 25635 | E26: =D26*Setup!$B$5 | F26: =D26-E26 | G26: 1925 | I26: 0 | J26: =C26+F26+G26-I26 | L26: =K26*Setup!$B$6 | M26: =J26-L26
A27: 46199 | B27: La Cata LMF | C27: 46815 | D27: 32320 | E27: =D27*Setup!$B$5 | F27: =D27-E27 | G27: 375 | I27: 0 | J27: =C27+F27+G27-I27 | L27: =K27*Setup!$B$6 | M27: =J27-L27
A28: 46200 | B28: La Cata LMF | C28: 160930 | D28: 69930 | E28: =D28*Setup!$B$5 | F28: =D28-E28 | G28: 3160 | I28: 4585 | J28: =C28+F28+G28-I28 | L28: =K28*Setup!$B$6 | M28: =J28-L28
... A32: 46174 | B32: La Cata DF | C32: 4460 | D32: 3305 | E32: =D32*Setup!$B$5 | F32: =D32-E32 | G32: 0 | I32: 0 | J32: =C32+F32+G32-I32 | L32: =K32*Setup!$B$6 | M32: =J32-L32
A33: 46175 | B33: La Cata DF | E33: =D33*Setup!$B$5 | F33: =D33-E33 | G33: 0 | I33: 0 | J33: =C33+F33+G33-I33 | L33: =K33*Setup!$B$6 | M33: =J33-L33
A34: 46176 | B34: La Cata DF | E34: =D34*Setup!$B$5 | F34: =D34-E34 | G34: 0 | I34: 0 | J34: =C34+F34+G34-I34 | L34: =K34*Setup!$B$6 | M34: =J34-L34
A35: 46177 | B35: La Cata DF | E35: =D35*Setup!$B$5 | F35: =D35-E35 | G35: 0 | I35: 0 | J35: =C35+F35+G35-I35 | L35: =K35*Setup!$B$6 | M35: =J35-L35
A36: 46178 | B36: La Cata DF | E36: =D36*Setup!$B$5 | F36: =D36-E36 | G36: 0 | I36: 0 | J36: =C36+F36+G36-I36 | L36: =K36*Setup!$B$6 | M36: =J36-L36
A37: 46179 | B37: La Cata DF | E37: =D37*Setup!$B$5 | F37: =D37-E37 | G37: 0 | I37: 0 | J37: =C37+F37+G37-I37 | L37: =K37*Setup!$B$6 | M37: =J37-L37
A38: 46180 | B38: La Cata DF | E38: =D38*Setup!$B$5 | F38: =D38-E38 | G38: 0 | I38: 0 | J38: =C38+F38+G38-I38 | L38: =K38*Setup!$B$6 | M38: =J38-L38
A39: 46181 | B39: La Cata DF | E39: =D39*Setup!$B$5 | F39: =D39-E39 | G39: 0 | I39: 0 | J39: =C39+F39+G39-I39 | L39: =K39*Setup!$B$6 | M39: =J39-L39
A40: 46182 | B40: La Cata DF | E40: =D40*Setup!$B$5 | F40: =D40-E40 | G40: 0 | I40: 0 | J40: =C40+F40+G40-I40 | L40: =K40*Setup!$B$6 | M40: =J40-L40 | N40: 181328
A41: 46183 | B41: La Cata DF | E41: =D41*Setup!$B$5 | F41: =D41-E41 | G41: 0 | I41: 0 | J41: =C41+F41+G41-I41 | L41: =K41*Setup!$B$6 | M41: =J41-L41
A42: 46184 | B42: La Cata DF | E42: =D42*Setup!$B$5 | F42: =D42-E42 | G42: 0 | I42: 0 | J42: =C42+F42+G42-I42 | L42: =K42*Setup!$B$6 | M42: =J42-L42
A43: 46185 | B43: La Cata DF | E43: =D43*Setup!$B$5 | F43: =D43-E43 | G43: 0 | I43: 0 | J43: =C43+F43+G43-I43 | L43: =K43*Setup!$B$6 | M43: =J43-L43
A44: 46186 | B44: La Cata DF | E44: =D44*Setup!$B$5 | F44: =D44-E44 | G44: 0 | I44: 0 | J44: =C44+F44+G44-I44 | L44: =K44*Setup!$B$6 | M44: =J44-L44
A45: 46187 | B45: La Cata DF | E45: =D45*Setup!$B$5 | F45: =D45-E45 | G45: 0 | I45: 0 | J45: =C45+F45+G45-I45 | L45: =K45*Setup!$B$6 | M45: =J45-L45
A46: 46188 | B46: La Cata DF | E46: =D46*Setup!$B$5 | F46: =D46-E46 | G46: 0 | I46: 0 | J46: =C46+F46+G46-I46 | L46: =K46*Setup!$B$6 | M46: =J46-L46
A47: 46189 | B47: La Cata DF | E47: =D47*Setup!$B$5 | F47: =D47-E47 | G47: 0 | I47: 0 | J47: =C47+F47+G47-I47 | L47: =K47*Setup!$B$6 | M47: =J47-L47
A48: 46190 | B48: La Cata DF | E48: =D48*Setup!$B$5 | F48: =D48-E48 | G48: 0 | I48: 0 | J48: =C48+F48+G48-I48 | L48: =K48*Setup!$B$6 | M48: =J48-L48
A49: 46191 | B49: La Cata DF | E49: =D49*Setup!$B$5 | F49: =D49-E49 | G49: 0 | I49: 0 | J49: =C49+F49+G49-I49 | L49: =K49*Setup!$B$6 | M49: =J49-L49
A50: 46192 | B50: La Cata DF | E50: =D50*Setup!$B$5 | F50: =D50-E50 | G50: 0 | I50: 0 | J50: =C50+F50+G50-I50 | L50: =K50*Setup!$B$6 | M50: =J50-L50
A51: 46193 | B51: La Cata DF | E51: =D51*Setup!$B$5 | F51: =D51-E51 | G51: 0 | I51: 0 | J51: =C51+F51+G51-I51 | L51: =K51*Setup!$B$6 | M51: =J51-L51
A52: 46194 | B52: La Cata DF | E52: =D52*Setup!$B$5 | F52: =D52-E52 | G52: 0 | I52: 0 | J52: =C52+F52+G52-I52 | L52: =K52*Setup!$B$6 | M52: =J52-L52
... A61: 46203 | B61: La Cata DF | E61: =D61*Setup!$B$5 | F61: =D61-E61 | G61: 0 | I61: 0 | J61: =C61+F61+G61-I61 | L61: =K61*Setup!$B$6 | M61: =J61-L61
A63: 46143 | B63: La Cata LMF | C63: 78835 | D63: 13840 | E63: =D63*Setup!$B$5 | F63: =D63-E63 | G63: 320 | I63: 0 | J63: =C63+F63+G63-I63 | L63: =K63*Setup!$B$6 | M63: =J63-L63
A64: 46144 | B64: La Cata LMF | C64: 169855 | D64: 73995 | E64: =D64*Setup!$B$5 | F64: =D64-E64 | G64: 4420 | I64: 0 | J64: =C64+F64+G64-I64 | L64: =K64*Setup!$B$6 | M64: =J64-L64
A65: 46145 | B65: La Cata LMF | C65: 214184 | D65: 103654 | E65: =D65*Setup!$B$5 | F65: =D65-E65 | G65: 10870 | I65: 0 | J65: =C65+F65+G65-I65 | L65: =K65*Setup!$B$6 | M65: =J65-L65
A66: 46146 | B66: La Cata LMF | C66: 87074 | D66: 43820 | E66: =D66*Setup!$B$5 | F66: =D66-E66 | G66: 0 | I66: 0 | J66: =C66+F66+G66-I66 | L66: =K66*Setup!$B$6 | M66: =J66-L66 | N66: 511600
A67: 46147 | B67: La Cata LMF | C67: 28710 | D67: 5825 | E67: =D67*Setup!$B$5 | F67: =D67-E67 | G67: 705 | I67: 0 | J67: =C67+F67+G67-I67 | L67: =K67*Setup!$B$6 | M67: =J67-L67
A68: 46148 | B68: La Cata LMF | C68: 30240 | D68: 13490 | E68: =D68*Setup!$B$5 | F68: =D68-E68 | G68: 0 | I68: 0 | J68: =C68+F68+G68-I68 | L68: =K68*Setup!$B$6 | M68: =J68-L68
A69: 46149 | B69: La Cata LMF | C69: 31975 | D69: 15745 | E69: =D69*Setup!$B$5 | F69: =D69-E69 | G69: 0 | I69: 0 | J69: =C69+F69+G69-I69 | L69: =K69*Setup!$B$6 | M69: =J69-L69
A70: 46150 | B70: La Cata LMF | C70: 70085 | D70: 19935 | E70: =D70*Setup!$B$5 | F70: =D70-E70 | G70: 4050 | I70: 0 | J70: =C70+F70+G70-I70 | L70: =K70*Setup!$B$6 | M70: =J70-L70
A71: 46151 | B71: La Cata LMF | C71: 89085 | D71: 63415 | E71: =D71*Setup!$B$5 | F71: =D71-E71 | G71: 100 | I71: 0 | J71: =C71+F71+G71-I71 | L71: =K71*Setup!$B$6 | M71: =J71-L71
A72: 46152 | B72: La Cata LMF | C72: 148285 | D72: 54435 | E72: =D72*Setup!$B$5 | F72: =D72-E72 | G72: 5490 | I72: 0 | J72: =C72+F72+G72-I72 | L72: =K72*Setup!$B$6 | M72: =J72-L72
A73: 46153 | B73: La Cata LMF | C73: 25440 | D73: 2290 | E73: =D73*Setup!$B$5 | F73: =D73-E73 | G73: 0 | I73: 0 | J73: =C73+F73+G73-I73 | L73: =K73*Setup!$B$6 | M73: =J73-L73 | N73: 563100
A74: 46154 | B74: La Cata LMF | C74: 21960 | D74: 16180 | E74: =D74*Setup!$B$5 | F74: =D74-E74 | G74: 0 | I74: 0 | J74: =C74+F74+G74-I74 | L74: =K74*Setup!$B$6 | M74: =J74-L74
A75: 46155 | B75: La Cata LMF | C75: 36225 | D75: 7880 | E75: =D75*Setup!$B$5 | F75: =D75-E75 | G75: 3095 | I75: 0 | J75: =C75+F75+G75-I75 | L75: =K75*Setup!$B$6 | M75: =J75-L75
A76: 46156 | B76: La Cata LMF | C76: 23200 | D76: 6950 | E76: =D76*Setup!$B$5 | F76: =D76-E76 | G76: 0 | I76: 0 | J76: =C76+F76+G76-I76 | L76: =K76*Setup!$B$6 | M76: =J76-L76
A77: 46157 | B77: La Cata LMF | C77: 47765 | D77: 7255 | E77: =D77*Setup!$B$5 | F77: =D77-E77 | G77: 12820 | I77: 0 | J77: =C77+F77+G77-I77 | L77: =K77*Setup!$B$6 | M77: =J77-L77
A78: 46158 | B78: La Cata LMF | C78: 144732 | D78: 80333 | E78: =D78*Setup!$B$5 | F78: =D78-E78 | G78: 5885 | I78: 330 | J78: =C78+F78+G78-I78 | L78: =K78*Setup!$B$6 | M78: =J78-L78
A79: 46159 | B79: La Cata LMF | C79: 176873 | D79: 59965 | E79: =D79*Setup!$B$5 | F79: =D79-E79 | G79: 2980 | I79: 435 | J79: =C79+F79+G79-I79 | L79: =K79*Setup!$B$6 | M79: =J79-L79
A80: 46160 | B80: La Cata LMF | C80: 26545 | D80: 12780 | E80: =D80*Setup!$B$5 | F80: =D80-E80 | G80: 0 | I80: 0 | J80: =C80+F80+G80-I80 | L80: =K80*Setup!$B$6 | M80: =J80-L80 | N80: 478610
A81: 46161 | B81: La Cata LMF | C81: 27905 | D81: 6260 | E81: =D81*Setup!$B$5 | F81: =D81-E81 | G81: 600 | I81: 0 | J81: =C81+F81+G81-I81 | L81: =K81*Setup!$B$6 | M81: =J81-L81
A82: 46162 | B82: La Cata LMF | C82: 38255 | D82: 36870 | E82: =D82*Setup!$B$5 | F82: =D82-E82 | G82: 0 | I82: 0 | J82: =C82+F82+G82-I82 | L82: =K82*Setup!$B$6 | M82: =J82-L82
A83: 46163 | B83: La Cata LMF | C83: 34940 | D83: 15880 | E83: =D83*Setup!$B$5 | F83: =D83-E83 | G83: 2820 | I83: 0 | J83: =C83+F83+G83-I83 | L83: =K83*Setup!$B$6 | M83: =J83-L83
A84: 46164 | B84: La Cata LMF | C84: 70590 | D84: 37595 | E84: =D84*Setup!$B$5 | F84: =D84-E84 | G84: 1390 | I84: 0 | J84: =C84+F84+G84-I84 | L84: =K84*Setup!$B$6 | M84: =J84-L84
A85: 46165 | B85: La Cata LMF | C85: 112970 | D85: 53170 | E85: =D85*Setup!$B$5 | F85: =D85-E85 | G85: 0 | I85: 0 | J85: =C85+F85+G85-I85 | L85: =K85*Setup!$B$6 | M85: =J85-L85
A86: 46166 | B86: La Cata LMF | C86: 146790 | D86: 37750 | E86: =D86*Setup!$B$5 | F86: =D86-E86 | G86: 3810 | I86: 0 | J86: =C86+F86+G86-I86 | L86: =K86*Setup!$B$6 | M86: =J86-L86
A87: 46167 | B87: La Cata LMF | C87: 31965 | D87: 15365 | E87: =D87*Setup!$B$5 | F87: =D87-E87 | G87: 0 | I87: 0 | J87: =C87+F87+G87-I87 | L87: =K87*Setup!$B$6 | M87: =J87-L87 | N87: 461001
A88: 46168 | B88: La Cata LMF | C88: 30080 | D88: 16760 | E88: =D88*Setup!$B$5 | F88: =D88-E88 | G88: 0 | I88: 0 | J88: =C88+F88+G88-I88 | L88: =K88*Setup!$B$6 | M88: =J88-L88
A89: 46169 | B89: La Cata LMF | C89: 45115 | D89: 3325 | E89: =D89*Setup!$B$5 | F89: =D89-E89 | G89: 9840 | I89: 0 | J89: =C89+F89+G89-I89 | L89: =K89*Setup!$B$6 | M89: =J89-L89
A90: 46170 | B90: La Cata LMF | C90: 38977 | D90: 21462 | E90: =D90*Setup!$B$5 | F90: =D90-E90 | G90: 3155 | I90: 0 | J90: =C90+F90+G90-I90 | L90: =K90*Setup!$B$6 | M90: =J90-L90
A91: 46171 | B91: La Cata LMF | C91: 78460 | D91: 35475 | E91: =D91*Setup!$B$5 | F91: =D91-E91 | G91: 4750 | I91: 0 | J91: =C91+F91+G91-I91 | L91: =K91*Setup!$B$6 | M91: =J91-L91
A92: 46172 | B92: La Cata LMF | C92: 168585 | D92: 107360 | E92: =D92*Setup!$B$5 | F92: =D92-E92 | G92: 3010 | I92: 0 | J92: =C92+F92+G92-I92 | L92: =K92*Setup!$B$6 | M92: =J92-L92
A93: 46173 | B93: La Cata LMF | C93: 345921 | D93: 100290 | E93: =D93*Setup!$B$5 | F93: =D93-E93 | G93: 8335 | I93: 0 | J93: =C93+F93+G93-I93 | L93: =K93*Setup!$B$6 | M93: =J93-L93
A95: 46143 | B95: La Cata DF | C95: 19450 | D95: 4475 | E95: =D95*Setup!$B$5 | F95: =D95-E95 | G95: 0 | H95: 8145 | I95: 0 | J95: =C95+F95+G95-I95 | L95: =K95*Setup!$B$6 | M95: =J95-L95
A96: 46144 | B96: La Cata DF | C96: 20050 | D96: 14660 | E96: =D96*Setup!$B$5 | F96: =D96-E96 | G96: 0 | H96: 5033.75 | I96: 0 | J96: =C96+F96+G96-I96 | L96: =K96*Setup!$B$6 | M96: =J96-L96
A97: 46145 | B97: La Cata DF | C97: 14465 | D97: 4265 | E97: =D97*Setup!$B$5 | F97: =D97-E97 | G97: 0 | H97: 6060 | I97: 0 | J97: =C97+F97+G97-I97 | L97: =K97*Setup!$B$6 | M97: =J97-L97 | N97: 75670
A98: 46146 | B98: La Cata DF | C98: 11835 | D98: 11880 | E98: =D98*Setup!$B$5 | F98: =D98-E98 | G98: 0 | H98: 5185 | I98: 0 | J98: =C98+F98+G98-I98 | L98: =K98*Setup!$B$6 | M98: =J98-L98
A99: 46147 | B99: La Cata DF | C99: 3290 | D99: 2195 | E99: =D99*Setup!$B$5 | F99: =D99-E99 | G99: 0 | H99: 2795 | I99: 0 | J99: =C99+F99+G99-I99 | L99: =K99*Setup!$B$6 | M99: =J99-L99
A100: 46148 | B100: La Cata DF | C100: 3820 | D100: 3385 | E100: =D100*Setup!$B$5 | F100: =D100-E100 | G100: 1015 | H100: 590 | I100: 0 | J100: =C100+F100+G100-I100 | L100: =K100*Setup!$B$6 | M100: =J100-L100
A101: 46149 | B101: La Cata DF | C101: 8785 | D101: 1895 | E101: =D101*Setup!$B$5 | F101: 825 | G101: 0 | I101: 0 | J101: =C101+F101+G101-I101 | L101: =K101*Setup!$B$6 | M101: =J101-L101
A102: 46150 | B102: La Cata DF | C102: 21495 | D102: 5090 | E102: =D102*Setup!$B$5 | F102: =D102-E102 | G102: 2465 | I102: 0 | J102: =C102+F102+G102-I102 | L102: =K102*Setup!$B$6 | M102: =J102-L102
A103: 46151 | B103: La Cata DF | C103: 25390 | D103: 21460 | E103: =D103*Setup!$B$5 | F103: =D103-E103 | G103: 0 | H103: 7780 | I103: 0 | J103: =C103+F103+G103-I103 | L103: =K103*Setup!$B$6 | M103: =J103-L103
A104: 46152 | B104: La Cata DF | C104: 23405 | D104: 6490 | E104: =D104*Setup!$B$5 | F104: =D104-E104 | G104: 0 | H104: 5532.75 | I104: 0 | J104: =C104+F104+G104-I104 | L104: =K104*Setup!$B$6 | M104: =J104-L104
A105: 46153 | B105: La Cata DF | C105: 2045 | D105: 1515 | E105: =D105*Setup!$B$5 | F105: =D105-E105 | G105: 0 | H105: 1475 | I105: 0 | J105: =C105+F105+G105-I105 | L105: =K105*Setup!$B$6 | M105: =J105-L105
A106: 46154 | B106: La Cata DF | C106: 2885 | D106: 0 | E106: =D106*Setup!$B$5 | F106: 645 | G106: 0 | H106: 785 | I106: 0 | J106: =C106+F106+G106-I106 | L106: =K106*Setup!$B$6 | M106: =J106-L106 | N106: 97380
A107: 46155 | B107: La Cata DF | C107: 4225 | D107: 2065 | E107: =D107*Setup!$B$5 | F107: =D107-E107 | G107: 0 | H107: 6535 | I107: 0 | J107: =C107+F107+G107-I107 | L107: =K107*Setup!$B$6 | M107: =J107-L107
A108: 46156 | B108: La Cata DF | C108: 6545 | D108: 4915 | E108: =D108*Setup!$B$5 | F108: =D108-E108 | G108: 0 | H108: 4910 | I108: 0 | J108: =C108+F108+G108-I108 | L108: =K108*Setup!$B$6 | M108: =J108-L108
A109: 46157 | B109: La Cata DF | C109: 25150 | D109: 13270 | E109: =D109*Setup!$B$5 | F109: =D109-E109 | G109: 570 | H109: 7891 | I109: 0 | J109: =C109+F109+G109-I109 | L109: =K109*Setup!$B$6 | M109: =J109-L109
A110: 46158 | B110: La Cata DF | C110: 23455 | D110: 6725 | E110: =D110*Setup!$B$5 | F110: =D110-E110 | G110: 0 | H110: 2850.5 | I110: 0 | J110: =C110+F110+G110-I110 | L110: =K110*Setup!$B$6 | M110: =J110-L110
A111: 46159 | B111: La Cata DF | C111: 22195 | D111: 11150 | E111: =D111*Setup!$B$5 | F111: =D111-E111 | G111: 3350 | H111: 2560 | I111: 0 | J111: =C111+F111+G111-I111 | L111: =K111*Setup!$B$6 | M111: =J111-L111
A112: 46160 | B112: La Cata DF | C112: 9105 | D112: 600 | E112: =D112*Setup!$B$5 | F112: =D112-E112 | G112: 0 | H112: 155 | I112: 0 | J112: =C112+F112+G112-I112 | L112: =K112*Setup!$B$6 | M112: =J112-L112
A113: 46161 | B113: La Cata DF | C113: 1040 | D113: 0 | E113: =D113*Setup!$B$5 | F113: =D113-E113 | G113: 0 | H113: 310 | I113: 0 | J113: =C113+F113+G113-I113 | L113: =K113*Setup!$B$6 | M113: =J113-L113
...

Sheet Gastos
A1: FECHA | B1: UBICACION | C1: CATEGORIA | D1: SUBCATEGORIA | E1: MONTO | F1: METODO PAGO | G1: ESTADO | H1: NOTAS
A2: 46028 | B2: La Cata LMF | C2: Gastos Fijos | D2: Internet | E2: 9000 | F2: Transferencia | G2: Pago | H2: Pago Ignacio
A3: 46029 | B3: La Cata LMF | C3: Operación | D3: Caja chica | E3: 5000 | F3: Transferencia | G3: Pago
A4: 46031 | B4: La Cata DF | C4: Operación | D4: Trabajo | E4: 2500 | F4: Transferencia | G4: Pago | H4: Instalacion Camara
A5: 46034 | B5: La Cata LMF | C5: Operación | D5: Caja chica | E5: 5000 | F5: Transferencia | G5: Pago
A6: 46036 | B6: La Cata LMF | C6: Operación | D6: Electricidad | E6: 49776.58 | F6: Transferencia | G6: Pago | H6: Ambas Sucursales
A7: 46036 | B7: La Cata LMF | C7: Operación | D7: Nomina | E7: 56500 | F7: Transferencia | G7: Pago | H7: Ambas Sucursales
A8: 46037 | B8: La Cata LMF | C8: Operación | D8: Nomina | E8: 5000 | F8: Transferencia | G8: Pago | H8: Pago Contable LMF
A9: 46042 | B9: La Cata DF | C9: Operación | D9: Trabajo | E9: 900 | F9: Transferencia | G9: Pago | H9: Trabajo electrico: Henry Troncoso
A10: 46042 | B10: La Cata DF | C10: Administrativos | D10: Motor DF | E10: 50000 | F10: Transferencia | G10: Pago | H10: Pago a Chobelo
A11: 46050 | B11: La Cata DF | C11: Gastos Fijos | D11: Renta | E11: 29000 | F11: Transferencia | G11: Pago | H11: Local Defillo
A12: 46051 | B12: La Cata DF | C12: Operación | D12: Trabajo | E12: 3400 | F12: Transferencia | G12: Pago | H12: Trabajo electrico: Henry Troncoso
A13: 46052 | B13: La Cata LMF | C13: Gastos Fijos | D13: Nomina | E13: 66250 | F13: Transferencia | G13: Pago | H13: Ambas Sucursales
A14: 46052 | B14: La Cata LMF | C14: Gastos Fijos | D14: Renta | E14: 40000 | F14: Transferencia | G14: Pago
A15: 46060 | B15: La Cata LMF | C15: Gastos Fijos | D15: TSS | E15: 10289.91 | F15: Transferencia | G15: Pago | H15: Seguro TSS
A16: 46060 | B16: La Cata LMF | C16: Gastos Fijos | D16: Infotep | E16: 545 | F16: Transferencia | G16: Pago
A17: 46064 | B17: La Cata LMF | C17: Operación | D17: Electricidad | E17: 25404.22 | F17: Transferencia | G17: Pendiente | H17: edesur
A18: 46067 | B18: La Cata DF | C18: Gastos Fijos | D18: Nomina | E18: 19750 | F18: Transferencia | G18: Pago | H18: Nomina
A19: 46067 | B19: La Cata LMF | C19: Gastos Fijos | D19: Nomina | E19: 39250 | F19: Transferencia | G19: Pago | H19: Nomina
A20: 46070 | B20: La Cata LMF | C20: Gastos Fijos | D20: Nomina | E20: 10000 | F20: Transferencia | G20: Pago | H20: Pago Contable LMF Enero y Febrero, pagada hasta mayo
A21: 46072 | B21: La Cata DF | C21: Operación | D21: Electricidad | E21: 25645.96 | F21: Transferencia | G21: Pago | H21: Mes de Enero 26, Edesur.
A22: 46072 | B22: La Cata DF | C22: Operación | D22: PedidosYa | E22: 8000 | F22: Transferencia | G22: Pago | H22: Pago Enlace a Pedidos Ya
A23: 46080 | B23: La Cata DF | C23: Gastos Fijos | D23: Nomina | E23: 19750 | F23: Transferencia | G23: Pago | H23: Nomina
A24: 46080 | B24: La Cata LMF | C24: Gastos Fijos | D24: Nomina | E24: 39250 | F24: Transferencia | G24: Pago | H24: Nomina
A25: 46080 | B25: La Cata LMF | C25: Gastos Fijos | D25: Renta | E25: 40000 | F25: Transferencia | G25: Pago
A26: 46080 | B26: La Cata LMF | C26: Gastos Fijos | D26: TSS | E26: 10833.15 | F26: Transferencia | G26: Pago | H26: Seguro TSS
A27: 46080 | B27: La Cata LMF | C27: Gastos Fijos | D27: Infotep | E27: 395 | F27: Transferencia | G27: Pago
A28: 46083 | B28: La Cata DF | C28: Gastos Fijos | D28: Renta | E28: 36000 | F28: Transferencia | G28: Pago | H28: Local Defillo
A29: 46106 | B29: La Cata DF | C29: Gastos Fijos | D29: Internet | E29: 5201.6 | F29: Transferencia | G29: Pago | H29: Local Defillo
A30: 46106 | B30: La Cata DF | C30: Gastos Fijos | D30: Electricidad | E30: 26236.88 | F30: Transferencia | G30: Pago | H30: Local Defillo
A31: 46112 | B31: La Cata DF | C31: Gastos Fijos | D31: Renta | E31: 36000 | F31: Transferencia | G31: Pago | H31: Local Defillo
A32: 46112 | B32: AMBAS | C32: Gastos Fijos | D32: Internet | E32: 9000 | F32: Transferencia | G32: Pago | H32: Pago Ignacio
A33: 46112 | B33: La Cata LMF | C33: Gastos Fijos | D33: Renta | E33: 40000 | F33: Transferencia | G33: Pago
A34: 46112 | B34: La Cata LMF | C34: Gastos Fijos | D34: TSS | E34: 7222.1 | F34: Transferencia | G34: Pago | H34: Seguro TSS
A35: 46112 | B35: La Cata LMF | C35: Operación | D35: Electricidad | E35: 23456.87 | F35: Transferencia | G35: Pago | H35: edesur
A36: 46129 | B36: La Cata DF | C36: Gastos Fijos | D36: Agua | E36: 950 | F36: Transferencia | G36: Pago | H36: Agua Defillo
A37: 46132 | B37: La Cata DF | C37: Operación | D37: Caja chica | E37: 3000 | F37: Transferencia | G37: Pago
A38: 46139 | B38: La Cata DF | C38: Gastos Fijos | D38: Renta | E38: 36000 | F38: Transferencia | G38: Pago | H38: Local Defillo
A39: 46139 | B39: La Cata LMF | C39: Gastos Fijos | D39: Renta | E39: 40000 | F39: Transferencia | G39: Pago | H39: LMF
A40: 46139 | B40: La Cata DF | C40: Operación | D40: Electricidad | E40: 36295.95 | F40: Transferencia | G40: Pago
A41: 46139 | B41: La Cata LMF | C41: Operación | D41: Electricidad | E41: 22933.1 | F41: Transferencia | G41: Pago
A42: 46139 | B42: La Cata DF | C42: Operación | D42: Telefono | E42: 1692.58 | F42: Transferencia | G42: Pago
A43: 46139 | B43: La Cata LMF | C43: Operación | D43: Telefono | E43: 1238.01 | F43: Transferencia | G43: Pago
A44: 46139 | B44: La Cata LMF | C44: Gastos Fijos | D44: TSS | E44: 3611.05 | F44: Transferencia | G44: Pago
A45: 46141 | B45: AMBAS | C45: Gastos Fijos | D45: Nomina | E45: 86650 | F45: Transferencia | G45: Pago
A46: 46157 | B46: AMBAS | C46: Gastos Fijos | D46: Nomina | E46: 59684 | F46: Transferencia | G46: Pago
A47: 46172 | B47: AMBAS | C47: Gastos Fijos | D47: Nomina | E47: 79850 | F47: Transferencia | G47: Pago
A48: 46170 | B48: La Cata DF | C48: Gastos Fijos | D48: Renta | E48: RD$ 36,000.00 | F48: Transferencia | G48: Pago | H48: Local Defillo
A49: 46170 | B49: La Cata LMF | C49: Gastos Fijos | D49: Renta | E49: 40000 | F49: Transferencia | G49: Pago | H49: Local Defillo
A50: 46170 | B50: La Cata LMF | C50: Gastos Fijos | D50: TSS | E50: 3611.05 | F50: Transferencia | G50: Pago
A51: 46170 | B51: La Cata LMF | C51: Gastos Fijos | D51: Infotep | E51: 545 | F51: Transferencia | G51: Pago
A52: 46183 | B52: La Cata DF | C52: Operación | D52: Telefono | E52: 1599 | F52: Transferencia | G52: Pago
A53: 46183 | B53: LA CATA SJ | C53: Operación | D53: Telefono | E53: 7964.74 | F53: Transferencia | G53: Pago
A54: 46183 | B54: La Cata DF | C54: Operación | D54: Electricidad | E54: 29594.38 | F54: Transferencia | G54: Pago
A55: 46183 | B55: LA CATA SJ | C55: Operación | D55: Electricidad | E55: 24544 | F55: Transferencia | G55: Pago
A56: 46183 | B56: La Cata LMF | C56: Operación | D56: Telefono | E56: 500 | F56: Transferencia | G56: Pago
A57: 46192 | B57: AMBAS | C57: Operación | D57: Caja chica | E57: 20000 | F57: Transferencia | G57: PAGO | H57: CAJA CHICA LMF Y SAN JUAN
A58: 46196 | B58: LA CATA SJ | C58: Operación | D58: Caja chica | E58: 5000 | F58: Transferencia | G58: PAGO

Sheet CXP
A1: Semana (Lunes) | B1: UBICACION | C1: PROVEEDOR | D1: FACTURA | E1: FECHA FACTURA | F1: FECHA VENCIMIENTO | G1: TIPO (CREDITO/CONTADO) | H1: MONTO | I1: PAGO 1 | J1: FECHA PAGO 1 | K1: PAGO 2 | L1: FECHA PAGO 2 | M1: TOTAL PAGADO | N1: PAGADO (SI/NO) | O1: FECHA PAGO | P1: METODO PAGO | Q1: MONTO PENDIENTE | R1: DIAS A VENCER | S1: ALERTA | T1: Registrado por | U1: Validado | V1: Validado por | W1: Fecha validación | X1: NOTA
B2: La Cata DF | C2: UNITED BRANDS | D2: 16426 | E2: 46373 | F2: 46038 | G2: Crédito | H2: 58087.07 | M2: =SUM(I2,K2) | N2: Sí | Q2: =IF(N2="Sí",0,H2-I2-K2) | R2: =F2-TODAY() | S2: =IF(N2="Sí","🟢 Pagado",IF(R2<0,"🔴 Vencido",IF(R2<=7,"🟡 Por vencer","")))
B3: La Cata DF | C3: UNITED BRANDS | D3: 16439 | E3: 46011 | F3: 46041 | G3: Crédito | H3: 17050.19 | M3: =SUM(I3,K3) | N3: Sí | Q3: =IF(N3="Sí",0,H3-I3-K3) | R3: =F3-TODAY() | S3: =IF(N3="Sí","🟢 Pagado",IF(R3<0,"🔴 Vencido",IF(R3<=7,"🟡 Por vencer","")))
B4: La Cata DF | C4: UNITED BRANDS | D4: 16441 | E4: 46011 | F4: 46041 | G4: Crédito | H4: 15904.22 | M4: =SUM(I4,K4) | N4: Sí | Q4: =IF(N4="Sí",0,H4-I4-K4) | R4: =F4-TODAY() | S4: =IF(N4="Sí","🟢 Pagado",IF(R4<0,"🔴 Vencido",IF(R4<=7,"🟡 Por vencer","")))
B5: AMBAS | C5: JUAN BEATO | D5: TC QIK | E5: 46011 | F5: 46042 | G5: Crédito | H5: 359960 | I5: 347060.01 | K5: 12899.99 | L5: 46112 | M5: =SUM(I5,K5) | N5: Sí | Q5: =IF(N5="Sí",0,H5-I5-K5) | R5: =F5-TODAY() | S5: =IF(N5="Sí","🟢 Pagado",IF(R5<0,"🔴 Vencido",IF(R5<=7,"🟡 Por vencer","")))
B6: AMBAS | C6: JUAN BEATO | D6: TC 2564 Banesco | E6: 46012 | F6: 46054 | G6: Crédito | H6: 262167 | M6: =SUM(I6,K6) | N6: Sí | Q6: =IF(N6="Sí",0,H6-I6-K6) | R6: =F6-TODAY() | S6: =IF(N6="Sí","🟢 Pagado",IF(R6<0,"🔴 Vencido",IF(R6<=7,"🟡 Por vencer","")))
B7: La Cata DF | C7: JUAN BEATO | D7: GASTOS VARIOS | E7: 45940 | F7: 46096 | G7: Contado | H7: 7974.8 | I7: 7974.8 | M7: =SUM(I7,K7) | N7: Sí | O7: 46097 | Q7: =IF(N7="Sí",0,H7-I7-K7) | R7: =F7-TODAY() | S7: =IF(N7="Sí","🟢 Pagado",IF(R7<0,"🔴 Vencido",IF(R7<=7,"🟡 Por vencer","")))
B8: AMBAS | C8: JOSE IGNACIO ROA | D8: GASTOS VARIOS | E8: 45940 | F8: 46050 | G8: Contado | H8: 68200 | I8: 27290 | M8: =SUM(I8,K8) | N8: Sí | Q8: =IF(N8="Sí",0,H8-I8-K8) | R8: =F8-TODAY() | S8: =IF(N8="Sí","🟢 Pagado",IF(R8<0,"🔴 Vencido",IF(R8<=7,"🟡 Por vencer",""))) | X8: Extraido del archivo de Juan Beato, menos RD$50,000 motor
B9: La Cata LMF | C9: UNITED BRANDS | D9: 1645632 | E9: 46017 | F9: 46047 | G9: Crédito | H9: 81021.67 | I9: 630 | M9: =SUM(I9,K9) | N9: Sí | Q9: =IF(N9="Sí",0,H9-I9-K9) | R9: =F9-TODAY() | S9: =IF(N9="Sí","🟢 Pagado",IF(R9<0,"🔴 Vencido",IF(R9<=7,"🟡 Por vencer",""))) | X9: pendiente pagar a Juan Beato
B10: La Cata DF | C10: OXBAR | D10: 10144 | E10: 46041 | F10: 46059 | G10: Crédito | H10: 11984.45 | I10: 5992 | K10: 5992.45 | L10: 46072 | M10: =SUM(I10,K10) | N10: Sí | Q10: =IF(N10="Sí",0,H10-I10-K10) | R10: =F10-TODAY() | S10: =IF(N10="Sí","🟢 Pagado",IF(R10<0,"🔴 Vencido",IF(R10<=7,"🟡 Por vencer","")))
B11: La Cata DF | C11: JUAN BEATO | D11: TC | E11: 46040 | F11: 46075 | G11: Crédito | H11: 41344.99 | M11: =SUM(I11,K11) | N11: Sí | Q11: =IF(N11="Sí",0,H11-I11-K11) | R11: =F11-TODAY() | S11: =IF(N11="Sí","🟢 Pagado",IF(R11<0,"🔴 Vencido",IF(R11<=7,"🟡 Por vencer","")))
B12: La Cata LMF | C12: UNITED BRANDS | D12: 1646194 | E12: 46018 | F12: 46079 | G12: Crédito | H12: 100309.44 | I12: 100309.44 | M12: =SUM(I12,K12) | N12: Sí | Q12: =IF(N12="Sí",0,H12-I12-K12) | R12: =F12-TODAY() | S12: =IF(N12="Sí","🟢 Pagado",IF(R12<0,"🔴 Vencido",IF(R12<=7,"🟡 Por vencer",""))) | X12: pendiente pagar a Juan Beato
B13: La Cata LMF | C13: CND LMF | D13: TRANSFERENCIA | E13: 46043 | F13: 46051 | G13: Crédito | H13: 160521.84 | I13: 160521.84 | M13: =SUM(I13,K13) | N13: Sí | P13: Transferencia | Q13: =IF(N13="Sí",0,H13-I13-K13) | R13: =F13-TODAY() | S13: =IF(N13="Sí","🟢 Pagado",IF(R13<0,"🔴 Vencido",IF(R13<=7,"🟡 Por vencer","")))
B14: La Cata LMF | C14: LOCAL LMF | D14: TRANSFERENCIA | E14: 46021 | F14: 46051 | G14: Crédito | H14: 40000 | I14: 40000 | M14: =SUM(I14,K14) | N14: Sí | O14: 46053 | P14: Transferencia | Q14: =IF(N14="Sí",0,H14-I14-K14) | R14: =F14-TODAY() | S14: =IF(N14="Sí","🟢 Pagado",IF(R14<0,"🔴 Vencido",IF(R14<=7,"🟡 Por vencer","")))
B15: La Cata DF | C15: EDESUR DEFILLO | D15: NIC 44327 | E15: 46043 | F15: 46072 | G15: Crédito | H15: 25645.96 | I15: 25645.96 | J15: 46072 | M15: =SUM(I15,K15) | N15: Sí | O15: 46072 | Q15: =IF(N15="Sí",0,H15-I15-K15) | R15: =F15-TODAY() | S15: =IF(N15="Sí","🟢 Pagado",IF(R15<0,"🔴 Vencido",IF(R15<=7,"🟡 Por vencer","")))
B16: La Cata LMF | C16: UNITED BRANDS | D16: 1647227 | E16: 46021 | F16: 46052 | G16: Crédito | H16: 191510.11 | I16: 191510.11 | M16: =SUM(I16,K16) | N16: Sí | Q16: =IF(N16="Sí",0,H16-I16-K16) | R16: =F16-TODAY() | S16: =IF(N16="Sí","🟢 Pagado",IF(R16<0,"🔴 Vencido",IF(R16<=7,"🟡 Por vencer","")))
B17: La Cata DF | C17: FRANCELIS SANCHEZ | D17: TC | E17: 46043 | F17: 46081 | G17: Crédito | H17: 820 | I17: 820 | J17: 46084 | M17: =SUM(I17,K17) | N17: Sí | O17: 46084 | Q17: =IF(N17="Sí",0,H17-I17-K17) | R17: =F17-TODAY() | S17: =IF(N17="Sí","🟢 Pagado",IF(R17<0,"🔴 Vencido",IF(R17<=7,"🟡 Por vencer","")))
B18: La Cata DF | C18: JUAN BEATO | D18: TC | E18: 46012 | F18: 46081 | G18: Crédito | H18: 13110 | I18: 13110 | J18: 46084 | M18: =SUM(I18,K18) | N18: Sí | O18: 46084 | Q18: =IF(N18="Sí",0,H18-I18-K18) | R18: =F18-TODAY() | S18: =IF(N18="Sí","🟢 Pagado",IF(R18<0,"🔴 Vencido",IF(R18<=7,"🟡 Por vencer","")))
B19: La Cata LMF | C19: SUPERNOVA /TULIPAN/DELVIS | D19: 3104 | E19: 46038 | F19: 46052 | G19: Crédito | H19: 87905 | I19: 73844.99 | M19: =SUM(I19,K19) | N19: Sí | O19: 46057 | Q19: =IF(N19="Sí",0,H19-I19-K19) | R19: =F19-TODAY() | S19: =IF(N19="Sí","🟢 Pagado",IF(R19<0,"🔴 Vencido",IF(R19<=7,"🟡 Por vencer","")))
B20: La Cata LMF | C20: JOSE IGNACIO ROA | D20: TRANSFERENCIA | E20: 46035 | F20: 46052 | G20: Contado | H20: 1750 | I20: 1750 | M20: =SUM(I20,K20) | N20: Sí | Q20: =IF(N20="Sí",0,H20-I20-K20) | R20: =F20-TODAY() | S20: =IF(N20="Sí","🟢 Pagado",IF(R20<0,"🔴 Vencido",IF(R20<=7,"🟡 Por vencer",""))) | X20: HIELO LMF
B21: La Cata LMF | C21: JOSE IGNACIO ROA | D21: TRANSFERENCIA | E21: 46040 | F21: 46052 | G21: Contado | H21: 1350 | I21: 1350 | M21: =SUM(I21,K21) | N21: Sí | Q21: =IF(N21="Sí",0,H21-I21-K21) | R21: =F21-TODAY() | S21: =IF(N21="Sí","🟢 Pagado",IF(R21<0,"🔴 Vencido",IF(R21<=7,"🟡 Por vencer",""))) | X21: CENA LMF DEGUSTACION
B22: La Cata LMF | C22: JOSE IGNACIO ROA | D22: TRANSFERENCIA | E22: 46041 | F22: 46052 | G22: Contado | H22: 2000 | I22: 2000 | M22: =SUM(I22,K22) | N22: Sí | Q22: =IF(N22="Sí",0,H22-I22-K22) | R22: =F22-TODAY() | S22: =IF(N22="Sí","🟢 Pagado",IF(R22<0,"🔴 Vencido",IF(R22<=7,"🟡 Por vencer",""))) | X22: MULTA SOLTERO
B23: La Cata LMF | C23: SUPERNOVA /TULIPAN/DELVIS | D23: 3134 | E23: 46045 | F23: 46059 | G23: Crédito | H23: 158515 | I23: 1000 | M23: =SUM(I23,K23) | N23: Sí | O23: 46057 | Q23: =IF(N23="Sí",0,H23-I23-K23) | R23: =F23-TODAY() | S23: =IF(N23="Sí","🟢 Pagado",IF(R23<0,"🔴 Vencido",IF(R23<=7,"🟡 Por vencer","")))
B24: La Cata DF | C24: JUAN BEATO | D24: TC | E24: 46049 | F24: 46069 | G24: Crédito | H24: 10222.49 | I24: 1400 | M24: =SUM(I24,K24) | N24: Sí | Q24: =IF(N24="Sí",0,H24-I24-K24) | R24: =F24-TODAY() | S24: =IF(N24="Sí","🟢 Pagado",IF(R24<0,"🔴 Vencido",IF(R24<=7,"🟡 Por vencer","")))
B25: La Cata LMF | C25: SUPERNOVA /TULIPAN/DELVIS | D25: 3146 | E25: 46043 | F25: 46059 | G25: Crédito | H25: 11680 | I25: 1000 | M25: =SUM(I25,K25) | N25: Sí | O25: 46057 | Q25: =IF(N25="Sí",0,H25-I25-K25) | R25: =F25-TODAY() | S25: =IF(N25="Sí","🟢 Pagado",IF(R25<0,"🔴 Vencido",IF(R25<=7,"🟡 Por vencer","")))
B26: AMBAS | C26: JUAN BEATO | D26: TC | E26: 46050 | F26: 46091 | G26: Crédito | H26: 181331.11 | I26: 181331.11 | M26: =SUM(I26,K26) | N26: Sí | O26: 46091 | Q26: =IF(N26="Sí",0,H26-I26-K26) | R26: =F26-TODAY() | S26: =IF(N26="Sí","🟢 Pagado",IF(R26<0,"🔴 Vencido",IF(R26<=7,"🟡 Por vencer",""))) | X26: Pagos facturas United Brands el 28 Enero por TC
B27: La Cata LMF | C27: JOSE IGNACIO ROA | D27: TRANSFERENCIA | E27: 46050 | G27: Contado | H27: 1000 | I27: 1000 | M27: =SUM(I27,K27) | N27: Sí | Q27: =IF(N27="Sí",0,H27-I27-K27) | R27: =F27-TODAY() | S27: =IF(N27="Sí","🟢 Pagado",IF(R27<0,"🔴 Vencido",IF(R27<=7,"🟡 Por vencer",""))) | X27: PAGO A SOTERO
B28: La Cata LMF | C28: JOSE IGNACIO ROA | D28: TRANSFERENCIA | E28: 46051 | G28: Contado | H28: 1400 | I28: 1400 | M28: =SUM(I28,K28) | N28: Sí | Q28: =IF(N28="Sí",0,H28-I28-K28) | R28: =F28-TODAY() | S28: =IF(N28="Sí","🟢 Pagado",IF(R28<0,"🔴 Vencido",IF(R28<=7,"🟡 Por vencer",""))) | X28: AGUA SUBLIME
B29: La Cata LMF | C29: SUPERNOVA /TULIPAN/DELVIS | D29: 3163 | E29: 46051 | F29: 46055 | G29: Crédito | H29: 193848.03 | I29: 193848.03 | M29: =SUM(I29,K29) | N29: Sí | O29: 46062 | Q29: =IF(N29="Sí",0,H29-I29-K29) | R29: =F29-TODAY() | S29: =IF(N29="Sí","🟢 Pagado",IF(R29<0,"🔴 Vencido",IF(R29<=7,"🟡 Por vencer","")))
B30: AMBAS | C30: TUBEBIDA.NET( Hollandia) | D30: 2120 | E30: 46053 | F30: 46081 | G30: Crédito | H30: 43999.99 | I30: 43999.99 | J30: 46076 | M30: =SUM(I30,K30) | N30: Sí | O30: 46076 | Q30: =IF(N30="Sí",0,H30-I30-K30) | R30: =F30-TODAY() | S30: =IF(N30="Sí","🟢 Pagado",IF(R30<0,"🔴 Vencido",IF(R30<=7,"🟡 Por vencer",""))) | X30: CERVEZAS HOLLANDIA
B31: La Cata LMF | C31: JOSE IGNACIO ROA | D31: TRANSFERENCIA | E31: 46053 | G31: Contado | H31: 1000 | I31: 1000 | M31: =SUM(I31,K31) | N31: Sí | Q31: =IF(N31="Sí",0,H31-I31-K31) | R31: =F31-TODAY() | S31: =IF(N31="Sí","🟢 Pagado",IF(R31<0,"🔴 Vencido",IF(R31<=7,"🟡 Por vencer",""))) | X31: PAGO A ORLANDITO
B32: La Cata DF | C32: JUAN BEATO | D32: TC | E32: 46053 | F32: 46092 | G32: Crédito | H32: 27290 | I32: 27290 | M32: =SUM(I32,K32) | N32: Sí | O32: 46097 | Q32: =IF(N32="Sí",0,H32-I32-K32) | R32: =F32-TODAY() | S32: =IF(N32="Sí","🟢 Pagado",IF(R32<0,"🔴 Vencido",IF(R32<=7,"🟡 Por vencer","")))
B33: La Cata DF | C33: JUAN BEATO | D33: TC | E33: 46053 | F33: 46092 | G33: Crédito | H33: 630 | I33: 630 | M33: =SUM(I33,K33) | N33: Sí | O33: 46097 | Q33: =IF(N33="Sí",0,H33-I33-K33) | R33: =F33-TODAY() | S33: =IF(N33="Sí","🟢 Pagado",IF(R33<0,"🔴 Vencido",IF(R33<=7,"🟡 Por vencer",""))) | X33: Material gastable
B34: La Cata LMF | C34: SUPERNOVA /TULIPAN/DELVIS | D34: 3184 | E34: 46058 | F34: 46070 | G34: Crédito | H34: =192310-6420 | I34: 185890 | J34: 46069 | M34: =SUM(I34,K34) | N34: Sí | O34: 46069 | Q34: =IF(N34="Sí",0,H34-I34-K34) | R34: =F34-TODAY() | S34: =IF(N34="Sí","🟢 Pagado",IF(R34<0,"🔴 Vencido",IF(R34<=7,"🟡 Por vencer",""))) | X34: Restamos RON MACORIX RD$6,420.00, MONTO ORIGINAL RD$192,310.00
B35: La Cata LMF | C35: JUAN BEATO | D35: TC | E35: 46059 | F35: 46086 | G35: Crédito | H35: 73844.99 | I35: 73844.99 | J35: 46084 | M35: =SUM(I35,K35) | N35: Sí | O35: 46084 | Q35: =IF(N35="Sí",0,H35-I35-K35) | R35: =F35-TODAY() | S35: =IF(N35="Sí","🟢 Pagado",IF(R35<0,"🔴 Vencido",IF(R35<=7,"🟡 Por vencer","")))
B36: La Cata LMF | C36: JUAN BEATO | D36: UB a Beato | E36: 46061 | F36: 46109 | G36: Crédito | H36: 282551.59 | I36: 282551.59 | J36: 46112 | M36: =SUM(I36,K36) | N36: Sí | Q36: =IF(N36="Sí",0,H36-I36-K36) | R36: =F36-TODAY() | S36: =IF(N36="Sí","🟢 Pagado",IF(R36<0,"🔴 Vencido",IF(R36<=7,"🟡 Por vencer","")))
B37: La Cata LMF | C37: SUPERNOVA /TULIPAN/DELVIS | D37: 3211 | E37: 46065 | F37: 46077 | G37: Crédito | H37: 247915 | I37: 247915 | J37: 46077 | M37: =SUM(I37,K37) | N37: Sí | O37: 46077 | Q37: =IF(N37="Sí",0,H37-I37-K37) | R37: =F37-TODAY() | S37: =IF(N37="Sí","🟢 Pagado",IF(R37<0,"🔴 Vencido",IF(R37<=7,"🟡 Por vencer","")))
B38: La Cata DF | C38: JUAN BEATO | D38: TC 5309 | E38: 46066 | F38: 46108 | G38: Crédito | H38: 23688.64 | I38: 23688.64 | J38: 46112 | M38: =SUM(I38,K38) | N38: Sí | Q38: =IF(N38="Sí",0,H38-I38-K38) | R38: =F38-TODAY() | S38: =IF(N38="Sí","🟢 Pagado",IF(R38<0,"🔴 Vencido",IF(R38<=7,"🟡 Por vencer",""))) | X38: PEDIDO ALMACENES HATUEY SRL 148476
B39: La Cata DF | C39: JUAN BEATO | D39: 1 | E39: 46066 | F39: 46071 | G39: Crédito | H39: 925 | M39: =SUM(I39,K39) | N39: Sí | Q39: =IF(N39="Sí",0,H39-I39-K39) | R39: =F39-TODAY() | S39: =IF(N39="Sí","🟢 Pagado",IF(R39<0,"🔴 Vencido",IF(R39<=7,"🟡 Por vencer",""))) | X39: Material gastable
B40: La Cata DF | C40: JUAN BEATO | D40: 2 | E40: 46067 | F40: 46069 | G40: Crédito | H40: 264 | M40: =SUM(I40,K40) | N40: Sí | Q40: =IF(N40="Sí",0,H40-I40-K40) | R40: =F40-TODAY() | S40: =IF(N40="Sí","🟢 Pagado",IF(R40<0,"🔴 Vencido",IF(R40<=7,"🟡 Por vencer",""))) | X40: Impresion oferta 6x5
B41: La Cata LMF | C41: UNITED BRANDS | D41: UB-1648468 | E41: 46029 | F41: 46059 | G41: Crédito | H41: 103132 | I41: 103132 | J41: 46076 | M41: =SUM(I41,K41) | N41: Sí | O41: 46076 | Q41: =IF(N41="Sí",0,H41-I41-K41) | R41: =F41-TODAY() | S41: =IF(N41="Sí","🟢 Pagado",IF(R41<0,"🔴 Vencido",IF(R41<=7,"🟡 Por vencer","")))
B42: La Cata DF | C42: UNITED BRANDS | D42: UB-1649008 | E42: 46031 | F42: 46061 | G42: Crédito | H42: 31611.77 | I42: 44223.91 | M42: =SUM(I42,K42) | N42: Sí | Q42: =IF(N42="Sí",0,H42-I42-K42) | R42: =F42-TODAY() | S42: =IF(N42="Sí","🟢 Pagado",IF(R42<0,"🔴 Vencido",IF(R42<=7,"🟡 Por vencer",""))) | X42: Pago mediante transferencia el dia 16/2/2026
B43: La Cata DF | C43: UNITED BRANDS | D43: UB-1649609 | E43: 46034 | F43: 46064 | G43: Crédito | H43: 24940.83 | I43: 140417.76 | M43: =SUM(I43,K43) | N43: Sí | Q43: =IF(N43="Sí",0,H43-I43-K43) | R43: =F43-TODAY() | S43: =IF(N43="Sí","🟢 Pagado",IF(R43<0,"🔴 Vencido",IF(R43<=7,"🟡 Por vencer","")))
B44: La Cata DF | C44: UNITED BRANDS | D44: UB-1649762 | E44: 46034 | F44: 46064 | G44: Crédito | H44: 15259.81 | I44: 7629.9 | M44: =SUM(I44,K44) | N44: Sí | Q44: =IF(N44="Sí",0,H44-I44-K44) | R44: =F44-TODAY() | S44: =IF(N44="Sí","🟢 Pagado",IF(R44<0,"🔴 Vencido",IF(R44<=7,"🟡 Por vencer","")))
B45: La Cata LMF | C45: UNITED BRANDS | D45: UB-1650560 | E45: 46036 | F45: 46066 | G45: Crédito | H45: 44223.91 | I45: 2106.06 | J45: 46076 | M45: =SUM(I45,K45) | N45: Sí | O45: 46076 | Q45: =IF(N45="Sí",0,H45-I45-K45) | R45: =F45-TODAY() | S45: =IF(N45="Sí","🟢 Pagado",IF(R45<0,"🔴 Vencido",IF(R45<=7,"🟡 Por vencer","")))
B46: La Cata LMF | C46: UNITED BRANDS | D46: UB-1650567 | E46: 46036 | F46: 46066 | G46: Crédito | H46: 140417.76 | I46: 5963.37 | J46: 46076 | M46: =SUM(I46,K46) | N46: Sí | O46: 46076 | Q46: =IF(N46="Sí",0,H46-I46-K46) | R46: =F46-TODAY() | S46: =IF(N46="Sí","🟢 Pagado",IF(R46<0,"🔴 Vencido",IF(R46<=7,"🟡 Por vencer","")))
B47: La Cata LMF | C47: UNITED BRANDS | D47: UB-1650576 | E47: 46036 | F47: 46066 | G47: Crédito | H47: 7629.9 | I47: 2733.3 | J47: 46076 | M47: =SUM(I47,K47) | N47: Sí | O47: 46076 | Q47: =IF(N47="Sí",0,H47-I47-K47) | R47: =F47-TODAY() | S47: =IF(N47="Sí","🟢 Pagado",IF(R47<0,"🔴 Vencido",IF(R47<=7,"🟡 Por vencer","")))
B48: La Cata LMF | C48: UNITED BRANDS | D48: UB-1650590 | E48: 46036 | F48: 46066 | G48: Crédito | H48: 2106.06 | I48: 17689.67 | J48: 46076 | M48: =SUM(I48,K48) | N48: Sí | O48: 46076 | Q48: =IF(N48="Sí",0,H48-I48-K48) | R48: =F48-TODAY() | S48: =IF(N48="Sí","🟢 Pagado",IF(R48<0,"🔴 Vencido",IF(R48<=7,"🟡 Por vencer","")))
B49: La Cata DF | C49: UNITED BRANDS | D49: UB-1651344 | E49: 46039 | F49: 46069 | G49: Crédito | H49: 264553.68 | I49: 264553.68 | J49: 46084 | M49: =SUM(I49,K49) | N49: Sí | O49: 46084 | Q49: =IF(N49="Sí",0,H49-I49-K49) | R49: =F49-TODAY() | S49: =IF(N49="Sí","🟢 Pagado",IF(R49<0,"🔴 Vencido",IF(R49<=7,"🟡 Por vencer","")))
B50: La Cata DF | C50: UNITED BRANDS | D50: UB-1651896 | E50: 46042 | F50: 46072 | G50: Crédito | H50: 44223.91 | I50: 44223.91 | J50: 46084 | M50: =SUM(I50,K50) | N50: Sí | O50: 46084 | Q50: =IF(N50="Sí",0,H50-I50-K50) | R50: =F50-TODAY() | S50: =IF(N50="Sí","🟢 Pagado",IF(R50<0,"🔴 Vencido",IF(R50<=7,"🟡 Por vencer","")))
B51: La Cata LMF | C51: UNITED BRANDS | D51: UB-1654041 | E51: 46050 | F51: 46080 | G51: Crédito | H51: 124701.89 | I51: 124701.89 | M51: =SUM(I51,K51) | N51: Sí | O51: 46097 | Q51: =IF(N51="Sí",0,H51-I51-K51) | R51: =F51-TODAY() | S51: =IF(N51="Sí","🟢 Pagado",IF(R51<0,"🔴 Vencido",IF(R51<=7,"🟡 Por vencer",""))) | X51: Pagado por Beato en Marzo 16 2026 a traves de link
B52: La Cata LMF | C52: UNITED BRANDS | D52: UB-1655843 | E52: 46057 | F52: 46087 | G52: Crédito | H52: 142735.26 | I52: 142735.26 | M52: =SUM(I52,K52) | N52: Sí | O52: 46097 | Q52: =IF(N52="Sí",0,H52-I52-K52) | R52: =F52-TODAY() | S52: =IF(N52="Sí","🟢 Pagado",IF(R52<0,"🔴 Vencido",IF(R52<=7,"🟡 Por vencer",""))) | X52: Pagado por Beato en Marzo 16 2026 a traves de link
B53: La Cata LMF | C53: UNITED BRANDS | D53: UB-1656134 | E53: 46058 | F53: 46088 | G53: Crédito | H53: 30477.26 | I53: 30477.26 | M53: =SUM(I53,K53) | N53: Sí | O53: 46097 | Q53: =IF(N53="Sí",0,H53-I53-K53) | R53: =F53-TODAY() | S53: =IF(N53="Sí","🟢 Pagado",IF(R53<0,"🔴 Vencido",IF(R53<=7,"🟡 Por vencer",""))) | X53: Pagado por Beato en Marzo 16 2026 a traves de link
B54: La Cata DF | C54: UNITED BRANDS | D54: UB-1656132 | E54: 46058 | F54: 46088 | G54: Crédito | H54: 45944.24 | I54: 45944.24 | M54: =SUM(I54,K54) | N54: Sí | O54: 46097 | Q54: =IF(N54="Sí",0,H54-I54-K54) | R54: =F54-TODAY() | S54: =IF(N54="Sí","🟢 Pagado",IF(R54<0,"🔴 Vencido",IF(R54<=7,"🟡 Por vencer",""))) | X54: Pagado por Beato en Marzo 16 2026 a traves de link
B55: La Cata DF | C55: UNITED BRANDS | D55: UB-1656529 | E55: 46059 | F55: 46089 | G55: Crédito | H55: 48462.56 | I55: 48462.56 | M55: =SUM(I55,K55) | N55: Sí | O55: 46097 | Q55: =IF(N55="Sí",0,H55-I55-K55) | R55: =F55-TODAY() | S55: =IF(N55="Sí","🟢 Pagado",IF(R55<0,"🔴 Vencido",IF(R55<=7,"🟡 Por vencer",""))) | X55: Pagado por Beato en Marzo 16 2026 a traves de link
B56: La Cata LMF | C56: UNITED BRANDS | D56: UB-1658082 | E56: 46064 | F56: 46094 | G56: Crédito | H56: 11355.57 | I56: 11355.57 | M56: =SUM(I56,K56) | N56: Sí | O56: 46097 | Q56: =IF(N56="Sí",0,H56-I56-K56) | R56: =F56-TODAY() | S56: =IF(N56="Sí","🟢 Pagado",IF(R56<0,"🔴 Vencido",IF(R56<=7,"🟡 Por vencer",""))) | X56: Pagado por Beato en Marzo 16 2026 a traves de link
B57: La Cata LMF | C57: BEERS & CO | D57: BEERS-0063311 | E57: 46029 | F57: 46059 | G57: Crédito | H57: 5963.37 | I57: 5963.37 | J57: 46076 | M57: =SUM(I57,K57) | N57: Sí | O57: 46076 | Q57: =IF(N57="Sí",0,H57-I57-K57) | R57: =F57-TODAY() | S57: =IF(N57="Sí","🟢 Pagado",IF(R57<0,"🔴 Vencido",IF(R57<=7,"🟡 Por vencer","")))
B58: La Cata LMF | C58: BEERS & CO | D58: BEERS-0063725 | E58: 46036 | F58: 46066 | G58: Crédito | H58: 2733.3 | I58: 2733.3 | J58: 46076 | M58: =SUM(I58,K58) | N58: Sí | O58: 46076 | Q58: =IF(N58="Sí",0,H58-I58-K58) | R58: =F58-TODAY() | S58: =IF(N58="Sí","🟢 Pagado",IF(R58<0,"🔴 Vencido",IF(R58<=7,"🟡 Por vencer","")))
B59: La Cata LMF | C59: BEERS & CO | D59: BEERS-0064013 | E59: 46042 | F59: 46072 | G59: Crédito | H59: 17689.67 | I59: 17689.67 | J59: 46076 | M59: =SUM(I59,K59) | N59: Sí | O59: 46076 | Q59: =IF(N59="Sí",0,H59-I59-K59) | R59: =F59-TODAY() | S59: =IF(N59="Sí","🟢 Pagado",IF(R59<0,"🔴 Vencido",IF(R59<=7,"🟡 Por vencer","")))
B60: La Cata DF | C60: BEERS & CO | D60: BEERS-0064446 | E60: 46050 | F60: 46080 | G60: Crédito | H60: 14632.58 | I60: 14632.58 | M60: =SUM(I60,K60) | N60: Sí | O60: 46097 | Q60: =IF(N60="Sí",0,H60-I60-K60) | R60: =F60-TODAY() | S60: =IF(N60="Sí","🟢 Pagado",IF(R60<0,"🔴 Vencido",IF(R60<=7,"🟡 Por vencer","")))
B61: La Cata LMF | C61: DISTRIBUCIONES CALDERON MOLINA SRL | D61: 960904 | E61: 46055 | F61: 46055 | G61: Contado | H61: 3284 | M61: =SUM(I61,K61) | N61: Sí | Q61: =IF(N61="Sí",0,H61-I61-K61) | R61: =F61-TODAY() | S61: =IF(N61="Sí","🟢 Pagado",IF(R61<0,"🔴 Vencido",IF(R61<=7,"🟡 Por vencer",""))) | X61: 89599
B62: La Cata LMF | C62: STARLINK | D62: 8891353 | E62: 46056 | F62: 46056 | G62: Contado | H62: 9250 | M62: =SUM(I62,K62) | N62: Sí | Q62: =IF(N62="Sí",0,H62-I62-K62) | R62: =F62-TODAY() | S62: =IF(N62="Sí","🟢 Pagado",IF(R62<0,"🔴 Vencido",IF(R62<=7,"🟡 Por vencer","")))
B63: La Cata LMF | C63: LA TABACALERA SA | D63: 332-1195 | E63: 46057 | F63: 46085 | G63: Crédito | H63: 3665 | I63: 3665 | J63: 46084 | M63: =SUM(I63,K63) | N63: Sí | O63: 46084 | Q63: =IF(N63="Sí",0,H63-I63-K63) | R63: =F63-TODAY() | S63: =IF(N63="Sí","🟢 Pagado",IF(R63<0,"🔴 Vencido",IF(R63<=7,"🟡 Por vencer","")))
B64: La Cata LMF | C64: DISTRIBUCIONES CALDERON MOLINA SRL | D64: 798627 | E64: 46057 | F64: 46057 | G64: Contado | H64: 2979 | M64: =SUM(I64,K64) | N64: Sí | Q64: =IF(N64="Sí",0,H64-I64-K64) | R64: =F64-TODAY() | S64: =IF(N64="Sí","🟢 Pagado",IF(R64<0,"🔴 Vencido",IF(R64<=7,"🟡 Por vencer","")))
B65: La Cata DF | C65: CERVECERIA NACIONAL DOMINICANA SA | D65: C00691858 | E65: 46057 | F65: 46057 | G65: Contado | H65: 38657.81 | I65: 38657.81 | M65: =SUM(I65,K65) | N65: Sí | Q65: =IF(N65="Sí",0,H65-I65-K65) | R65: =F65-TODAY() | S65: =IF(N65="Sí","🟢 Pagado",IF(R65<0,"🔴 Vencido",IF(R65<=7,"🟡 Por vencer","")))
B66: La Cata DF | C66: CABEZA LIQUORS STORE | D66: 200534333 | E66: 46033 | F66: 46057 | G66: Crédito | H66: 29532.85 | M66: =SUM(I66,K66) | N66: Sí | Q66: =IF(N66="Sí",0,H66-I66-K66) | R66: =F66-TODAY() | S66: =IF(N66="Sí","🟢 Pagado",IF(R66<0,"🔴 Vencido",IF(R66<=7,"🟡 Por vencer","")))
B67: La Cata DF | C67: CABEZA LIQUORS STORE | D67: 425 | E67: 46052 | F67: 46057 | G67: Crédito | H67: 20899.99 | M67: =SUM(I67,K67) | N67: Sí | Q67: =IF(N67="Sí",0,H67-I67-K67) | R67: =F67-TODAY() | S67: =IF(N67="Sí","🟢 Pagado",IF(R67<0,"🔴 Vencido",IF(R67<=7,"🟡 Por vencer","")))
B68: La Cata LMF | C68: ALTA COPA | D68: 109246 | E68: 46058 | F68: 46058 | G68: Contado | H68: 6160.17 | M68: =SUM(I68,K68) | N68: Sí | Q68: =IF(N68="Sí",0,H68-I68-K68) | R68: =F68-TODAY() | S68: =IF(N68="Sí","🟢 Pagado",IF(R68<0,"🔴 Vencido",IF(R68<=7,"🟡 Por vencer","")))
B69: La Cata DF | C69: AQUASED | D69: 1137 | E69: 46058 | F69: 46058 | G69: Contado | H69: 720 | M69: =SUM(I69,K69) | N69: Sí | Q69: =IF(N69="Sí",0,H69-I69-K69) | R69: =F69-TODAY() | S69: =IF(N69="Sí","🟢 Pagado",IF(R69<0,"🔴 Vencido",IF(R69<=7,"🟡 Por vencer","")))
B70: La Cata LMF | C70: FRITO LAY DOMINICANA S A | D70: 1 | E70: 46058 | F70: 46058 | G70: Contado | H70: 12398.3 | M70: =SUM(I70,K70) | N70: Sí | Q70: =IF(N70="Sí",0,H70-I70-K70) | R70: =F70-TODAY() | S70: =IF(N70="Sí","🟢 Pagado",IF(R70<0,"🔴 Vencido",IF(R70<=7,"🟡 Por vencer","")))
B71: La Cata LMF | C71: CERVECERIA NACIONAL DOMINICANA SA | D71: C11461180 | E71: 46058 | F71: 46058 | G71: Contado | H71: 123197.2 | I71: 123197.2 | M71: =SUM(I71,K71) | N71: Sí | Q71: =IF(N71="Sí",0,H71-I71-K71) | R71: =F71-TODAY() | S71: =IF(N71="Sí","🟢 Pagado",IF(R71<0,"🔴 Vencido",IF(R71<=7,"🟡 Por vencer","")))
B72: La Cata LMF | C72: DISTRBUIDORA DE BEBIDAS CARLIS | D72: 61393 | E72: 46060 | F72: 46060 | G72: Contado | H72: 17100 | M72: =SUM(I72,K72) | N72: Sí | Q72: =IF(N72="Sí",0,H72-I72-K72) | R72: =F72-TODAY() | S72: =IF(N72="Sí","🟢 Pagado",IF(R72<0,"🔴 Vencido",IF(R72<=7,"🟡 Por vencer","")))
B73: AMBAS | C73: TSS | D73: 1 | E73: 46060 | F73: 46060 | G73: Contado | H73: 10289.91 | M73: =SUM(I73,K73) | N73: Sí | Q73: =IF(N73="Sí",0,H73-I73-K73) | R73: =F73-TODAY() | S73: =IF(N73="Sí","🟢 Pagado",IF(R73<0,"🔴 Vencido",IF(R73<=7,"🟡 Por vencer","")))
B74: AMBAS | C74: INFOTEP | D74: 1 | E74: 46060 | F74: 46060 | G74: Contado | H74: 545 | M74: =SUM(I74,K74) | N74: Sí | Q74: =IF(N74="Sí",0,H74-I74-K74) | R74: =F74-TODAY() | S74: =IF(N74="Sí","🟢 Pagado",IF(R74<0,"🔴 Vencido",IF(R74<=7,"🟡 Por vencer","")))
B75: La Cata DF | C75: FRITO LAY DOMINICANA S A | D75: 1 | E75: 46062 | F75: 46062 | G75: Contado | H75: 6127 | M75: =SUM(I75,K75) | N75: Sí | Q75: =IF(N75="Sí",0,H75-I75-K75) | R75: =F75-TODAY() | S75: =IF(N75="Sí","🟢 Pagado",IF(R75<0,"🔴 Vencido",IF(R75<=7,"🟡 Por vencer","")))
B76: La Cata DF | C76: WILLY MEDRANO | D76: 1 | E76: 46063 | F76: 46063 | G76: Contado | H76: 1953 | M76: =SUM(I76,K76) | N76: Sí | Q76: =IF(N76="Sí",0,H76-I76-K76) | R76: =F76-TODAY() | S76: =IF(N76="Sí","🟢 Pagado",IF(R76<0,"🔴 Vencido",IF(R76<=7,"🟡 Por vencer",""))) | X76: Inventario Defillo
B77: La Cata DF | C77: ITZEL | D77: 1 | E77: 46063 | F77: 46063 | G77: Contado | H77: 2000 | M77: =SUM(I77,K77) | N77: Sí | Q77: =IF(N77="Sí",0,H77-I77-K77) | R77: =F77-TODAY() | S77: =IF(N77="Sí","🟢 Pagado",IF(R77<0,"🔴 Vencido",IF(R77<=7,"🟡 Por vencer",""))) | X77: Inventario Defillo
B78: La Cata LMF | C78: EDESUR | E78: 46064 | F78: 46064 | G78: Crédito | H78: 25404.22 | M78: =SUM(I78,K78) | N78: Sí | Q78: =IF(N78="Sí",0,H78-I78-K78) | R78: =F78-TODAY() | S78: =IF(N78="Sí","🟢 Pagado",IF(R78<0,"🔴 Vencido",IF(R78<=7,"🟡 Por vencer","")))
B79: La Cata LMF | C79: DISTRIBUIDORA DE CERVEZAS ALCANTARA | E79: 46064 | F79: 46064 | G79: Contado | H79: 6600 | M79: =SUM(I79,K79) | N79: Sí | Q79: =IF(N79="Sí",0,H79-I79-K79) | R79: =F79-TODAY() | S79: =IF(N79="Sí","🟢 Pagado",IF(R79<0,"🔴 Vencido",IF(R79<=7,"🟡 Por vencer","")))
B80: La Cata DF | C80: HENRY TRONCOSO | D80: 1 | E80: 46064 | F80: 46064 | G80: Contado | H80: 8150 | M80: =SUM(I80,K80) | N80: Sí | Q80: =IF(N80="Sí",0,H80-I80-K80) | R80: =F80-TODAY() | S80: =IF(N80="Sí","🟢 Pagado",IF(R80<0,"🔴 Vencido",IF(R80<=7,"🟡 Por vencer",""))) | X80: TRABAJOS ALMACEN DEFILLO
B81: La Cata LMF | C81: CERVECERIA NACIONAL DOMINICANA SA | D81: C11612143 | E81: 46065 | F81: 46065 | G81: Contado | H81: 141095.05 | I81: 141095.05 | M81: =SUM(I81,K81) | N81: Sí | Q81: =IF(N81="Sí",0,H81-I81-K81) | R81: =F81-TODAY() | S81: =IF(N81="Sí","🟢 Pagado",IF(R81<0,"🔴 Vencido",IF(R81<=7,"🟡 Por vencer","")))
B82: La Cata LMF | C82: KATHERIN | D82: 1 | E82: 46065 | F82: 46065 | G82: Contado | H82: 5000 | M82: =SUM(I82,K82) | N82: Sí | Q82: =IF(N82="Sí",0,H82-I82-K82) | R82: =F82-TODAY() | S82: =IF(N82="Sí","🟢 Pagado",IF(R82<0,"🔴 Vencido",IF(R82<=7,"🟡 Por vencer",""))) | X82: DECORACION SAN VALENTIN
B83: La Cata DF | C83: PROVISIONES JM | D83: 1 | E83: 46065 | F83: 46065 | G83: Contado | H83: 6150 | M83: =SUM(I83,K83) | N83: Sí | Q83: =IF(N83="Sí",0,H83-I83-K83) | R83: =F83-TODAY() | S83: =IF(N83="Sí","🟢 Pagado",IF(R83<0,"🔴 Vencido",IF(R83<=7,"🟡 Por vencer","")))
B84: La Cata LMF | C84: DISTRIBUCIONES CALDERON MOLINA SRL | D84: 802578 | E84: 46065 | F84: 46065 | G84: Contado | H84: 4092 | M84: =SUM(I84,K84) | N84: Sí | Q84: =IF(N84="Sí",0,H84-I84-K84) | R84: =F84-TODAY() | S84: =IF(N84="Sí","🟢 Pagado",IF(R84<0,"🔴 Vencido",IF(R84<=7,"🟡 Por vencer","")))
B85: La Cata LMF | C85: GRUPO EVEREST | D85: 1356 | E85: 46066 | F85: 46066 | G85: Contado | H85: 1375 | M85: =SUM(I85,K85) | N85: Sí | Q85: =IF(N85="Sí",0,H85-I85-K85) | R85: =F85-TODAY() | S85: =IF(N85="Sí","🟢 Pagado",IF(R85<0,"🔴 Vencido",IF(R85<=7,"🟡 Por vencer","")))
B86: La Cata DF | C86: CERVECERIA NACIONAL DOMINICANA SA | D86: C02461511 | E86: 46067 | F86: 46067 | G86: Contado | H86: 46448.48 | I86: 46448.48 | M86: =SUM(I86,K86) | N86: Sí | Q86: =IF(N86="Sí",0,H86-I86-K86) | R86: =F86-TODAY() | S86: =IF(N86="Sí","🟢 Pagado",IF(R86<0,"🔴 Vencido",IF(R86<=7,"🟡 Por vencer",""))) | X86: PAGO DUPLICADO, CREDITO PENDIENTE
B87: La Cata LMF | C87: JOSE IGNACIO ROA | D87: 1 | E87: 46068 | F87: 46068 | G87: Crédito | H87: 630 | I87: 630 | J87: 46084 | M87: =SUM(I87,K87) | N87: Sí | O87: 46084 | Q87: =IF(N87="Sí",0,H87-I87-K87) | R87: =F87-TODAY() | S87: =IF(N87="Sí","🟢 Pagado",IF(R87<0,"🔴 Vencido",IF(R87<=7,"🟡 Por vencer",""))) | X87: DEVOLUCION PAGO TC NICOLE GARCIA
B88: La Cata LMF | C88: JOSE IGNACIO ROA | D88: 1 | E88: 46068 | F88: 46068 | G88: Crédito | H88: 800 | I88: 800 | J88: 46084 | M88: =SUM(I88,K88) | N88: Sí | O88: 46084 | Q88: =IF(N88="Sí",0,H88-I88-K88) | R88: =F88-TODAY() | S88: =IF(N88="Sí","🟢 Pagado",IF(R88<0,"🔴 Vencido",IF(R88<=7,"🟡 Por vencer",""))) | X88: CENA EQUIPO LMF
B89: La Cata DF | C89: HENRY TRONCOSO | D89: 1 | E89: 46066 | F89: 46066 | G89: Contado | H89: 1100 | I89: 247600 | J89: 46074 | M89: =SUM(I89,K89) | N89: Sí | O89: 46074 | Q89: =IF(N89="Sí",0,H89-I89-K89) | R89: =F89-TODAY() | S89: =IF(N89="Sí","🟢 Pagado",IF(R89<0,"🔴 Vencido",IF(R89<=7,"🟡 Por vencer",""))) | X89: REPARACION BOMBA DE AGUA La Cata DF
B90: La Cata DF | C90: OXBAR | D90: 10062 | E90: 46036 | F90: 46067 | G90: Crédito | H90: 13124.65 | I90: 2500 | K90: 6562.15 | L90: 46072 | M90: =SUM(I90,K90) | N90: Sí | Q90: =IF(N90="Sí",0,H90-I90-K90) | R90: =F90-TODAY() | S90: =IF(N90="Sí","🟢 Pagado",IF(R90<0,"🔴 Vencido",IF(R90<=7,"🟡 Por vencer","")))
B91: La Cata DF | C91: JUAN BEATO | D91: 1 | E91: 46071 | F91: 46118 | G91: Crédito | H91: 40209.7 | I91: 40209.7 | J91: 46119 | M91: =SUM(I91,K91) | N91: Sí | Q91: =IF(N91="Sí",0,H91-I91-K91) | R91: =F91-TODAY() | S91: =IF(N91="Sí","🟢 Pagado",IF(R91<0,"🔴 Vencido",IF(R91<=7,"🟡 Por vencer",""))) | X91: Factura Almacenes Hatuey Defillo
B92: La Cata DF | C92: OXBAR | D92: 9740 | E92: 46004 | F92: 46035 | G92: Crédito | H92: 6000.03 | I92: 6000.03 | M92: =SUM(I92,K92) | N92: Sí | Q92: =IF(N92="Sí",0,H92-I92-K92) | R92: =F92-TODAY() | S92: =IF(N92="Sí","🟢 Pagado",IF(R92<0,"🔴 Vencido",IF(R92<=7,"🟡 Por vencer","")))
B93: La Cata LMF | C93: OXBAR | D93: 9196 | E93: 45960 | F93: 45991 | G93: Crédito | H93: 18099.15 | I93: 9000 | J93: 46044 | K93: 9099.15 | L93: 46072 | M93: =SUM(I93,K93) | N93: Sí | O93: 46044 | Q93: =IF(N93="Sí",0,H93-I93-K93) | R93: =F93-TODAY() | S93: =IF(N93="Sí","🟢 Pagado",IF(R93<0,"🔴 Vencido",IF(R93<=7,"🟡 Por vencer","")))
B94: La Cata LMF | C94: CERVECERIA NACIONAL DOMINICANA SA | D94: E310000949521 | E94: 46072 | F94: 46072 | G94: Contado | H94: 130243.41 | I94: 130243.41 | J94: 46072 | M94: =SUM(I94,K94) | N94: Sí | O94: 46072 | Q94: =IF(N94="Sí",0,H94-I94-K94) | R94: =F94-TODAY() | S94: =IF(N94="Sí","🟢 Pagado",IF(R94<0,"🔴 Vencido",IF(R94<=7,"🟡 Por vencer","")))
B95: La Cata LMF | C95: UNITED BRANDS | D95: UB-1659869 | E95: 46072 | F95: 46100 | G95: Crédito | H95: 103132 | M95: =SUM(I95,K95) | Q95: =IF(N95="Sí",0,H95-I95-K95) | R95: =F95-TODAY() | S95: =IF(N95="Sí","🟢 Pagado",IF(R95<0,"🔴 Vencido",IF(R95<=7,"🟡 Por vencer","")))
B96: La Cata DF | C96: Pedidos YA | D96: 0 | E96: 46072 | F96: 46072 | G96: Contado | H96: 8000 | I96: 8000 | J96: 46072 | M96: =SUM(I96,K96) | N96: Sí | O96: 46072 | Q96: =IF(N96="Sí",0,H96-I96-K96) | R96: =F96-TODAY() | S96: =IF(N96="Sí","🟢 Pagado",IF(R96<0,"🔴 Vencido",IF(R96<=7,"🟡 Por vencer","")))
B97: La Cata LMF | C97: SUPERNOVA /TULIPAN/DELVIS | D97: 3231 | E97: 46072 | F97: 46087 | G97: Crédito | H97: 247600 | I97: 247600 | J97: 46084 | M97: =SUM(I97,K97) | N97: Sí | O97: 46084 | Q97: =IF(N97="Sí",0,H97-I97-K97) | R97: =F97-TODAY() | S97: =IF(N97="Sí","🟢 Pagado",IF(R97<0,"🔴 Vencido",IF(R97<=7,"🟡 Por vencer","")))
B98: La Cata LMF | C98: JOSE IGNACIO ROA | D98: 0 | E98: 46073 | F98: 46081 | G98: Crédito | H98: 2500 | I98: 2500 | J98: 46084 | M98: =SUM(I98,K98) | N98: Sí | O98: 46084 | Q98: =IF(N98="Sí",0,H98-I98-K98) | R98: =F98-TODAY() | S98: =IF(N98="Sí","🟢 Pagado",IF(R98<0,"🔴 Vencido",IF(R98<=7,"🟡 Por vencer",""))) | X98: Transporte mercancia LMF
B99: La Cata DF | C99: AQUASED | D99: 1287 | E99: 46073 | F99: 46073 | G99: Contado | H99: 960 | I99: 960 | J99: 46073 | M99: =SUM(I99,K99) | N99: Sí | O99: 46073 | Q99: =IF(N99="Sí",0,H99-I99-K99) | R99: =F99-TODAY() | S99: =IF(N99="Sí","🟢 Pagado",IF(R99<0,"🔴 Vencido",IF(R99<=7,"🟡 Por vencer",""))) | X99: HIELO DEFILLO
B100: La Cata LMF | C100: DISTRIBUCIONES CALDERON MOLINA SRL | D100: 806769 | E100: 46074 | F100: 46074 | G100: Contado | H100: 9967 | I100: 9967 | J100: 46074 | M100: =SUM(I100,K100) | N100: Sí | O100: 46074 | Q100: =IF(N100="Sí",0,H100-I100-K100) | R100: =F100-TODAY() | S100: =IF(N100="Sí","🟢 Pagado",IF(R100<0,"🔴 Vencido",IF(R100<=7,"🟡 Por vencer","")))
...

Sheet Cata SJM
A1: Presupuesto Total | B1: 800000 | D1: Inversion Ignacio | E1: =SUMIFS(I:I,B:B,"Ignacio",G:G,"Pagado")
A2: Total Invertido | B2: =SUMIFS(I:I,G:G,"Pagado") | D2: Inversion Beato | E2: =SUMIFS(I:I,B:B,"Beato",G:G,"Pagado")
A3: Total Pendiente | B3: =SUMIFS(I:I,G:G,"Pendiente") | D3: Inversion La Cata | E3: =SUMIFS(I:I,B:B,"La Cata",G:G,"Pagado")
A4: Disponible Presupuesto | B4: =B1-(B2+B3) | D4: Total Capital Invertido | E4: =SUM(E1:E3)
A7: Fecha | B7: Pagado por | C7: Categoría | D7: Descripción | E7: Proveedor | F7: Método de pago | G7: Pagado a Suplidor | H7: Pago Inversionista | I7: Monto | J7: Fecha de pago Inversionista | K7: Notas
A8: 46105 | B8: Ignacio | C8: Renta | D8: Depositos de Alquiler | F8: Transferencia | G8: Pagado | H8: Pendiente | I8: 135000 | K8: 2+1 depositos de alquiler
A9: 46105 | B9: Ignacio | C9: Seguridad | D9: Camaras | F9: Transferencia | G9: Pagado | H9: Pendiente | I9: 162911 | K9: 13 Camaras + 1 router +cables red
A10: 46107 | B10: Ignacio | C10: Sonido | D10: Bocina | F10: Transferencia | G10: Pagado | H10: Pendiente | I10: 5400 | K10: 2 Bocinas
A11: 46112 | B11: Ignacio | C11: Pintura | D11: Pintura fuera del local | F11: Transferencia | G11: Pagado | H11: Pendiente | I11: 23500 | K11: 6 galones de pintura, tiner y mano de obra
A12: 46114 | B12: Beato | C12: Seguridad | D12: Cables Camara | F12: Tarjeta | G12: Pagado | H12: Pendiente | I12: 3400 | K12: Agregar metodo de pago Tarjeta de Credito
A13: 46121 | B13: Ignacio | C13: Techo | D13: Mano de Obra Techo y Division | E13: Maestro Bonvi | F13: Efectivo | G13: Pagado | H13: Pendiente | I13: 50000 | K13: Adelante de la mano de obra
A14: 46120 | B14: La Cata | C14: Techo | D14: Aluzinc y Materiales | E14: Ferreteria Prisma | F14: Transferencia | G14: Pagado | H14: Pendiente | I14: 55000
A15: 46120 | B15: La Cata | C15: Techo | D15: Perfiles y tornillos | E15: Ferreteria Prisma | F15: Transferencia | G15: Pagado | H15: Pendiente | I15: 15000
A16: 46120 | B16: La Cata | C16: Techo | D16: Madera y Clavos | E16: Ferreteria Prisma | F16: Transferencia | G16: Pagado | H16: Pendiente | I16: 4475
A17: 46121 | B17: Ignacio | C17: Techo PVC | D17: Adelanto y tumbado de Techo | E17: Maestro Melvin | F17: Transferencia | G17: Pagado | H17: Pendiente | I17: 20000
A18: 46118 | B18: La Cata | C18: Letrero | D18: Pago 50% Letrero | E18: Dexter Graphics | F18: Transferencia | G18: Pagado | H18: Pendiente | I18: 60000 | K18: Adelanto por el 50% del trabajo del letrero
A19: 46121 | B19: Ignacio | C19: Vidrios y Puertas | D19: Abono | E19: Maestro Ayendi | F19: Transferencia | G19: Pagado | H19: Pendiente | I19: 50000
A20: 46122 | B20: Ignacio | C20: Materiales | D20: Materiales para contruccion de meseta y banos | E20: Ferreteria Humberto | F20: Transferencia | G20: Pagado | H20: Pendiente | I20: 45440 | K20: Materiales para la pared, division, banos etc.
A21: 46122 | B21: Beato | C21: Materiales Techo PVC | D21: Materiales Techo PVC | E21: Max Ferreteria | F21: Tarjeta | G21: Pagado | H21: Pendiente | I21: 29458.04
A22: 46122 | B22: Beato | C22: Materiales Techo PVC | D22: Materiales Techo PVC | E22: Cielos Acusticos | F22: Tarjeta | G22: Pagado | H22: Pendiente | I22: 64779.17
A23: 38817 | B23: Ignacio | C23: Transporte | D23: Materiales Techo PVC | E23: Sotero | F23: Transferencia | G23: Pagado | H23: Pendiente | I23: 6000
A24: 46123 | B24: Ignacio | C24: Electricidad | D24: Materiales | E24: Maestro Pachi | F24: Transferencia | G24: Pagado | H24: Pendiente | I24: 3500 | K24: Materialies para extension alto voltaje
A25: 46125 | B25: Ignacio | C25: Techo | D25: Materiales | E25: Ferreteria Prisma | F25: Transferencia | G25: Pagado | H25: Pendiente | I25: 15700
A26: 46125 | B26: Ignacio | C26: Cable Bocinas | D26: Bocinas | E26: Amazon | F26: Tarjeta | G26: Pagado | H26: Pendiente | I26: 3900 | K26: 200 pies de cable audio 14amp
A27: 46130 | B27: Ignacio | C27: Letrero | D27: Pago 50% Letrero | E27: Dexter Graphics | F27: Transferencia | G27: Pagado | H27: Pendiente | I27: 60000
A28: 46134 | B28: Ignacio | C28: Muebles | D28: Abono Muebles y mesas alta | E28: Tio Nelson | F28: Transferencia | G28: Pagado | H28: Pendiente | I28: 40000 | K28: Restan 18mil, y la tapiceria del mueble.
A29: 46134 | B29: Ignacio | C29: Ceramica | D29: Ceramica Meseta | E29: Ramizaba Terminaciones | F29: Transferencia | G29: Pagado | H29: Pendiente | I29: 4896
A30: 46134 | B30: Ignacio | C30: Materiales | D30: 6 fundas de pegatin y barillas | E30: Tio Moreno | F30: Transferencia | G30: Pagado | H30: Pendiente | I30: 4000
A31: 46134 | B31: Ignacio | C31: Materiales | D31: Plomeria bano | E31: Ferreteria Prisma | F31: Transferencia | G31: Pagado | H31: Pendiente | I31: 1101
A32: 46135 | B32: Ignacio | C32: Ceramica | D32: Cermica piso bano etc. | E32: Ramizaba Terminaciones | F32: Transferencia | G32: Pagado | H32: Pendiente | I32: 6288
A33: 46135 | B33: Ignacio | C33: Ceramica | D33: Cermica piso bano etc. | E33: Ramizaba Terminaciones | F33: Transferencia | G33: Pagado | H33: Pendiente | I33: 2100
A34: 46136 | B34: Ignacio | C34: Materiales | D34: Materiales faltantes | E34: Ferreteria Prisma | F34: Transferencia | G34: Pagado | H34: Pendiente | I34: 4697
A35: 46132 | B35: Ignacio | C35: Sueldo | D35: Pago sueldo | E35: Valdez | F35: Transferencia | G35: Pagado | H35: Pendiente | I35: 5000 | K35: Valdez es quien abre y cierra el local y nos esta asistiendo con las compras y asugrando que nadie va a poner mano alla.
A36: 46136 | B36: Ignacio | C36: Construcion | D36: Adelanto Mano de obra | E36: Maestro Bonvi | F36: Transferencia | G36: Pagado | H36: Pendiente | I36: 30000
A37: 46137 | B37: Ignacio | C37: Construcion | D37: Materiales faltantes | E37: Ferreteria Prisma | F37: Transferencia | G37: Pagado | H37: Pendiente | I37: 1220
A38: 46137 | B38: Ignacio | C38: Construcion | D38: Materiales faltantes | E38: Ferreteria Prisma | F38: Transferencia | G38: Pagado | H38: Pendiente | I38: 1535
A39: 46140 | B39: Ignacio | C39: Construcion | D39: Materiales faltantes | E39: Ferreteria Luz | F39: Transferencia | G39: Pagado | H39: Pendiente | I39: 1170
A40: 46141 | B40: Ignacio | C40: Techo | D40: Materiales faltantes | E40: Ferreteria Prisma | F40: Transferencia | G40: Pagado | H40: Pendiente | I40: 13215
A41: 46141 | B41: Ignacio | C41: Construcion | D41: Cermica piso bano etc. | E41: Ramizaba Terminaciones | F41: Transferencia | G41: Pagado | H41: Pendiente | I41: 612
A42: 46141 | B42: Beato | C42: Abanicos | D42: 4 Abanicos | E42: Innovacentro | F42: Tarjeta | G42: Pagado | H42: Pendiente | I42: 15539.99
A43: 46143 | B43: Ignacio | C43: Electricidad | D43: Cables Electricos | E43: Ferreteria Prisma | F43: Transferencia | G43: Pagado | H43: Pendiente | I43: 11600
A44: 46144 | B44: Ignacio | C44: Sueldo | D44: Pago sueldo | E44: Valdez | F44: Transferencia | G44: Pagado | H44: Pendiente | I44: 5000 | K44: Valdez es quien abre y cierra el local y nos esta asistiendo con las compras y asugrando que nadie va a poner mano alla.
A45: 46144 | B45: Ignacio | C45: Electricidad | D45: Cables Electricos | E45: Ferreteria Prisma | F45: Transferencia | G45: Pagado | H45: Pendiente | I45: 12506
A46: 46144 | B46: Ignacio | C46: Electricidad | D46: Tornillos abanicos | E46: Ferreteria Prisma | F46: Transferencia | G46: Pagado | H46: Pendiente | I46: 688
A47: 46144 | B47: Ignacio | C47: Electricidad | D47: Pago abono trabajo electricidad | E47: Maestro Pachi | F47: Transferencia | G47: Pagado | H47: Pendiente | I47: 10000
A48: 46147 | B48: Ignacio | C48: Construcion | D48: Espuma | E48: Ferreteria Prisma | F48: Transferencia | G48: Pagado | H48: Pendiente | I48: 1200
A49: 46147 | B49: La Cata | C49: Electricidad | D49: Cables Electricos | E49: Ferreteria Luz | F49: Transferencia | G49: Pagado | H49: Pagado | I49: 25600
A50: 46144 | B50: Ignacio | C50: Electricidad | D50: Materiales faltantes | E50: Ferreteria Luz | F50: Transferencia | G50: Pagado | H50: Pendiente | I50: 850
A51: 46149 | B51: Ignacio | C51: Electricidad | D51: Pago abono trabajo electricidad | E51: Maestro Pachi | F51: Transferencia | G51: Pagado | H51: Pendiente | I51: 5000
A52: 46150 | B52: Ignacio | C52: Construcion | D52: Adelanto Mano de obra | E52: Maestro Bonvi | F52: Transferencia | G52: Pagado | H52: Pendiente | I52: 10000
A53: 46150 | B53: Ignacio | C53: Electricidad | D53: Materiales faltantes | E53: Ferreteria Luz | F53: Transferencia | G53: Pagado | H53: Pendiente | I53: 7491.96
A54: 46153 | B54: Ignacio | C54: Electricidad | D54: Materiales | E54: Ferreteria Prisma | F54: Transferencia | G54: Pagado | H54: Pendiente | I54: 2645
A55: 46153 | B55: Ignacio | C55: Electricidad | D55: Materiales | E55: Ferreteria Corcino | F55: Transferencia | G55: Pagado | H55: Pendiente | I55: 1390
A56: 46153 | B56: Ignacio | C56: Electricidad | D56: Materiales Electricos | E56: Ferreteria Prisma | F56: Transferencia | G56: Pagado | H56: Pendiente | I56: 10854
... A63: 46157 | B63: Beato | C63: Aires | D63: Aires acondicionados | E63: Plaza Lama | F63: Transferencia | G63: Pagado | H63: Pendiente | I63: 101990
A64: 46157 | B64: Ignacio | C64: Soldador | D64: Cerrar puerta de atras y agregar candados a las demas puertas | E64: Tio Moreno | F64: Transferencia | G64: Pagado | H64: Pendiente | I64: 3000 | K64: Cerrar puerta de atras y agregar candados a las demas puertas
A65: 46157 | B65: Ignacio | C65: Pintura | D65: Pintura y masilla | E65: Ferreteria Prisma | F65: Transferencia | G65: Pagado | H65: Pendiente | I65: 2000
A66: 46157 | B66: Ignacio | C66: Pintura | D66: Pintura y masilla | E66: Ferreteria Prisma | F66: Transferencia | G66: Pagado | H66: Pendiente | I66: 1500
A67: 46157 | B67: Ignacio | C67: Pintura | D67: Mano de Obra Pintura | E67: Maestro Ronny | F67: Transferencia | G67: Pagado | H67: Pendiente | I67: 18000
A68: 46157 | B68: Ignacio | C68: Plomeria | D68: Tinaco y Inversor | E68: Ferreteria Prisma | F68: Transferencia | G68: Pagado | H68: Pendiente | I68: 3989
A69: 46157 | B69: Ignacio | C69: Plomeria | D69: Tinaco y Inversor | E69: Ferreteria Prisma | F69: Transferencia | G69: Pagado | H69: Pendiente | I69: 403
A70: 46157 | B70: Ignacio | C70: Sueldo | D70: Pago sueldo | E70: Valdez | F70: Transferencia | G70: Pagado | H70: Pendiente | I70: 5000
A71: 46157 | B71: Ignacio | C71: Pintor Arte | D71: 50% Trabajo | E71: Moca Pintor | F71: Transferencia | G71: Pagado | H71: Pendiente | I71: 20000
A72: 46158 | B72: Ignacio | C72: Aires | D72: Palometas | E72: Ferreteria Luz | F72: Transferencia | G72: Pagado | H72: Pendiente | I72: 1015
A73: 46158 | B73: Ignacio | C73: Techo PVC | D73: PAGO FINAL MANO DE OBRA | E73: Maestro Melvin | F73: Transferencia | G73: Pagado | H73: Pendiente | I73: 75000
A74: 46158 | B74: Beato | C74: Luces faltantes | E74: Max Ferreteria | F74: Transferencia | G74: Pagado | H74: Pendiente | I74: 5850.03
A75: 46158 | B75: Beato | C75: Inversor | E75: Beato | F75: Transferencia | G75: Pagado | H75: Pendiente | I75: 29725
A76: 46158 | B76: Beato | C76: Inversor | E76: Beato | F76: Transferencia | G76: Pagado | H76: Pendiente | I76: 29725
A77: 46159 | B77: Ignacio | C77: Aires | D77: Aires acondicionados | E77: Ferreteria Luz | F77: Transferencia | G77: Pagado | H77: Pendiente | I77: 4292
A78: 46159 | B78: Beato | C78: Aires | D78: Cortinas de aire | F78: Transferencia | G78: Pagado | H78: Pendiente | I78: 12106.57
A79: 46160 | B79: Ignacio | C79: Aires | D79: Tuberias Aire | E79: Ferreteria Luz | F79: Transferencia | G79: Pagado | H79: Pendiente | I79: 1800
A80: 46160 | B80: Ignacio | C80: Aires | E80: Ferreteria Luz | F80: Transferencia | G80: Pagado | H80: Pendiente | I80: 1200
A81: 46160 | B81: Ignacio | C81: Aires | E81: Ferreteria Luz | F81: Transferencia | G81: Pagado | H81: Pendiente | I81: 1787
A82: 46161 | B82: La Cata | C82: Construcion | D82: PAGO FINAL MANO DE OBRA | E82: Maestro Bonvi | F82: Transferencia | G82: Pagado | H82: Pagado | I82: 115000
A83: 46161 | B83: Ignacio | C83: Caja fuerte | D83: Amazon | F83: Transferencia | G83: Pagado | H83: Pendiente | I83: 7200
A84: 46161 | B84: Ignacio | C84: Computadora | D84: Amazon | F84: Transferencia | G84: Pagado | H84: Pendiente | I84: 12300
A85: 46161 | B85: Beato | C85: Sillas | D85: Sillas Altas y bajitas | E85: Max Ferreteria | F85: Tarjeta | G85: Pagado | H85: Pendiente | I85: 45439.74
A86: 46162 | B86: Ignacio | C86: Telefonos | D86: Amazon | F86: Transferencia | G86: Pagado | H86: Pendiente | I86: 3364
A87: 46163 | B87: Beato | C87: Computadora | D87: Caja registradora | E87: DH DULCE HOGAR | F87: Tarjeta | G87: Pagado | H87: Pendiente | I87: 3085
A88: 46163 | B88: Beato | C88: Computadora | D88: Disco duro, pistotla y printer | E88: Omega Tech SA | F88: Tarjeta | G88: Pagado | H88: Pendiente | I88: 36520
A89: 46163 | B89: Beato | C89: Electricidad | D89: Baterias Inversor | E89: Decohaven srl | F89: Tarjeta | G89: Pagado | H89: Pendiente | I89: 43890
A90: 46165 | B90: Beato | C90: Materiales | D90: Estantes tramerias | E90: Comercial Wan Xin | F90: Transferencia | G90: Pagado | H90: Pendiente | I90: 28000
A91: 46164 | B91: La Cata | C91: Materiales | D91: Materiales Mueble | F91: Transferencia | G91: Pagado | H91: Pagado | I91: 29600
A92: 46164 | B92: Ignacio | C92: Materiales | D92: Materiales Cristales | F92: Transferencia | G92: Pagado | H92: Pendiente | I92: 35000
A93: 46163 | B93: Ignacio | C93: Electricidad | D93: Fianza Edesur SJM | F93: Transferencia | G93: Pagado | H93: Pendiente | I93: 5477
A94: 46164 | B94: La Cata | C94: Materiales | D94: Banco inversor | F94: Transferencia | G94: Pagado | H94: Pagado | I94: 3000
A95: 46165 | B95: Ignacio | C95: Materiales Inversor | D95: Cables | E95: Ferreteria Luz | F95: Transferencia | G95: Pagado | H95: Pendiente | I95: 3848
A96: 46165 | B96: Beato | C96: Trameria | D96: Trameria La Cata | F96: Transferencia | G96: Pagado | H96: Pendiente | I96: 28000
A97: 46165 | B97: La Cata | C97: Mano de Obra electrica | D97: PAGO FINAL MANO DE OBRA | E97: Maestro Pachi | F97: Transferencia | G97: Pagado | H97: Pagado | I97: 40000
A98: 46167 | B98: Beato | C98: Tv's | E98: Plaza Lama | F98: Transferencia | G98: Pagado | H98: Pendiente | I98: 46990
A99: 46167 | B99: Beato | C99: Base TV's | E99: Plaza Lama | F99: Transferencia | G99: Pagado | H99: Pendiente | I99: 3990
A100: 46168 | B100: La Cata | C100: Vidrios y Puertas | D100: Abono | E100: Maestro Ayendi | F100: Transferencia | G100: Pagado | H100: Pagado | I100: 20000
A101: 46168 | B101: Beato | C101: Trameria | D101: Trameria La Cata | F101: Transferencia | G101: Pagado | H101: Pendiente | I101: 415
A102: 46172 | B102: La Cata | C102: Cable Internet | E102: ICM Technology | F102: Transferencia | G102: Pagado | H102: Pagado | I102: 4495
A103: 46172 | B103: Ignacio | C103: Sueldo | D103: Pago sueldo | E103: Valdez | F103: Transferencia | G103: Pagado | H103: Pendiente | I103: 5000
A104: 46172 | B104: Ignacio | C104: Electricidad | D104: Mano de Obra | E104: Maestro Pachi | F104: Transferencia | G104: Pagado | H104: Pagado | I104: 4000
A105: 46178 | B105: Beato | C105: Materiales | D105: Trameria trasera La Cata | E105: Solares SA | F105: Tarjeta | G105: Pagado | H105: Pendiente | I105: 8448.42
A106: 46178 | B106: Beato | C106: Materiales | D106: Maouse, Teclado, Monitor y regleta | E106: Omega Tech SA | F106: Tarjeta | G106: Pagado | H106: Pendiente | I106: 9165
A107: 46181 | B107: Beato | C107: Materiales | D107: Vitrina acrilico | E107: ROTULPACK | F107: Tarjeta | G107: Pagado | H107: Pendiente | I107: 7291.89
A108: 46181 | B108: Beato | C108: Materiales | D108: Corte acrilico Vitrina | E108: ROTULPACK | F108: Tarjeta | G108: Pagado | H108: Pendiente | I108: 800
...

Sheet Análisis CXP
B2: 📊 ANÁLISIS DE CUENTAS POR PAGAR (CXP) - LA CATA
B3: =CONCATENATE("Análisis generado: ",TEXT(TODAY(),"d")," de ",TEXT(TODAY(),"mmmm")," de ",TEXT(TODAY(),"yyyy"))
B5: 📋 TOTAL REGISTROS | C5: 💰 MONTO TOTAL | D5: ⏳ PENDIENTE | E5: ✅ TASA PAGO | F5: 🏢 PROVEEDORES
B6: =COUNTA(CXP!B:B)-1 | C6: =SUM(CXP!H:H) | D6: =SUM(CXP!Q:Q) | E6: =IF(C6=0,0,1-(D6/C6)) | F6: {=ROWS(_xlfn.UNIQUE(_xlfn._xlws.FILTER(CXP!C2:C5000,CXP!C2:C5000<>"")))-1+1}
B8: 🚦 ESTADO DE PAGOS | F8: 🏢 MONTO POR UBICACIÓN
B9: Estado | C9: Cantidad | D9: Porcentaje | F9: Ubicación | G9: Monto Total | H9: Pendiente
B10: 🟢 Pagado | C10: =COUNTIFS(CXP!S:S,"*Pagado*",CXP!B:B,"<>") | D10: =IF($B$6=0,0,C10/$B$6) | F10: La Cata LMF | G10: =SUMIF(CXP!B:B,F10,CXP!H:H) | H10: =SUMIF(CXP!B:B,F10,CXP!Q:Q)
B11: 🔴 Vencido | C11: =COUNTIFS(CXP!S:S,"*Vencido*",CXP!B:B,"<>") | D11: =IF($B$6=0,0,C11/$B$6) | F11: AMBAS | G11: =SUMIF(CXP!B:B,F11,CXP!H:H) | H11: =SUMIF(CXP!B:B,F11,CXP!Q:Q)
B12: 🟡 Por vencer | C12: =COUNTIFS(CXP!S:S,"*Por vencer*",CXP!B:B,"<>") | D12: =IF($B$6=0,0,C12/$B$6) | F12: La Cata DF | G12: =SUMIF(CXP!B:B,F12,CXP!H:H) | H12: =SUMIF(CXP!B:B,F12,CXP!Q:Q)
B13: Sin estado | C13: =B6-C10-C11-C12 | D13: =IF($B$6=0,0,C13/$B$6) | F13: La Cata SJM | G13: =SUMIF(CXP!B:B,F13,CXP!H:H) | H13: =SUMIF(CXP!B:B,F13,CXP!Q:Q)
B15: 🏆 TOP 10 PROVEEDORES POR MONTO | F15: ⚠️ MAYOR PENDIENTE POR PAGAR
B16: Proveedor | C16: Monto Total | F16: Proveedor | G16: Pendiente
B17: {=_xlfn.LET(_xlpm.provs,_xlfn.UNIQUE(_xlfn._xlws.FILTER(CXP!C:C,CXP!C:C<>"")),_xlpm.montos,SUMIF(CXP!C:C,_xlpm.provs,CXP!H:H),_xlpm.sorted,_xlfn.SORTBY(_xlfn.HSTACK(_xlpm.provs,_xlpm.montos),_xlpm.montos,-1),_xlfn.TAKE(_xlpm.sorted,10))} | C17: 7567616.6 | F17: {=_xlfn.LET(_xlpm.provs,_xlfn.UNIQUE(_xlfn._xlws.FILTER(CXP!C:C,CXP!C:C<>"")),_xlpm.pends,SUMIF(CXP!C:C,_xlpm.provs,CXP!Q:Q),_xlpm.filtered,_xlfn._xlws.FILTER(_xlfn.HSTACK(_xlpm.provs,_xlpm.pends),_xlpm.pends>0),_xlpm.sorted,_xlfn.SORTBY(_xlpm.filtered,INDEX(_xlpm.filtered,,2),-1),_xlfn.TAKE(_xlpm.sorted,8))} | G17: 1953090.8
B18: SUPERNOVA /TULIPAN/DELVIS | C18: 7245995.7 | F18: JOSE IGNACIO ROA | G18: 1151431
B19: CERVECERIA NACIONAL DOMINICANA SA | C19: 4652231.1 | F19: SUPERNOVA /TULIPAN/DELVIS | G19: 1113173
B20: UNITED BRANDS | C20: 2397420.9 | F20: UNITED BRANDS | G20: 676726.69
B21: JOSE IGNACIO ROA | C21: 1682084.2 | F21: UTENA GROUP | G21: 64142.95
B22: TUBEBIDA.NET( Hollandia) | C22: 238640.18 | F22: CABEZA LIQUORS | G22: 37799.99
B23: CABEZA LIQUORS STORE | C23: 211656.28 | F23: BEERS & CO | G23: 6807.52
B24: CND LMF | C24: 160521.84
B25: FRITO LAY DOMINICANA S A | C25: 140830.7
B26: DGI | C26: 116242.76
B28: =_xlfn.CONCAT("📅 PAGOS DE LA SEMANA: ",TEXT(TODAY()+MOD(9-WEEKDAY(TODAY()),7),"DD/MM/YYYY")," - ",TEXT(TODAY()+MOD(9-WEEKDAY(TODAY()),7)+6,"DD/MM/YYYY")) | I28: Semana: | J28: =TODAY()+MOD(9-WEEKDAY(TODAY()),7) | K28: =J28+6
B30: 💰 Total a Pagar: | C30: =SUMIFS(CXP!$Q:$Q,CXP!$F:$F,">="&$J$28,CXP!$F:$F,"<="&$K$28,CXP!$N:$N,"No",CXP!$Q:$Q,">0") | D30: 📋 Facturas: | E30: =COUNTIFS(CXP!$F:$F,">="&$J$28,CXP!$F:$F,"<="&$K$28,CXP!$N:$N,"No",CXP!$Q:$Q,">0") | F30: 🏢 Proveedores: | G30: {=IFERROR(ROWS(_xlfn.UNIQUE(_xlfn._xlws.FILTER(CXP!$C$2:$C$5000,(CXP!$F$2:$F$5000>=$J$28)*(CXP!$F$2:$F$5000<=$K$28)*(CXP!$N$2:$N$5000="No")*(CXP!$Q$2:$Q$5000>0)))),0)}
B32: =_xlfn.CONCAT("⚠️ VENCIDAS (antes de ",TEXT($J$28,"DD/MM"),"):") | D32: =SUMIFS(CXP!$Q:$Q,CXP!$F:$F,"<"&$J$28,CXP!$N:$N,"No",CXP!$Q:$Q,">0") | F32: =_xlfn.CONCAT("(",COUNTIFS(CXP!$F:$F,"<"&$J$28,CXP!$N:$N,"No",CXP!$Q:$Q,">0")," facturas)")
B34: 📆 Por Día | C34: Fecha | D34: Facturas | E34: Monto
B35: Lunes | C35: =$J$28+0 | D35: =COUNTIFS(CXP!$F:$F,$J$28+0,CXP!$N:$N,"No",CXP!$Q:$Q,">0") | E35: =SUMIFS(CXP!$Q:$Q,CXP!$F:$F,$J$28+0,CXP!$N:$N,"No",CXP!$Q:$Q,">0")
B36: Martes | C36: =$J$28+1 | D36: =COUNTIFS(CXP!$F:$F,$J$28+1,CXP!$N:$N,"No",CXP!$Q:$Q,">0") | E36: =SUMIFS(CXP!$Q:$Q,CXP!$F:$F,$J$28+1,CXP!$N:$N,"No",CXP!$Q:$Q,">0")
B37: Miércoles | C37: =$J$28+2 | D37: =COUNTIFS(CXP!$F:$F,$J$28+2,CXP!$N:$N,"No",CXP!$Q:$Q,">0") | E37: =SUMIFS(CXP!$Q:$Q,CXP!$F:$F,$J$28+2,CXP!$N:$N,"No",CXP!$Q:$Q,">0")
B38: Jueves | C38: =$J$28+3 | D38: =COUNTIFS(CXP!$F:$F,$J$28+3,CXP!$N:$N,"No",CXP!$Q:$Q,">0") | E38: =SUMIFS(CXP!$Q:$Q,CXP!$F:$F,$J$28+3,CXP!$N:$N,"No",CXP!$Q:$Q,">0")
B39: Viernes | C39: =$J$28+4 | D39: =COUNTIFS(CXP!$F:$F,$J$28+4,CXP!$N:$N,"No",CXP!$Q:$Q,">0") | E39: =SUMIFS(CXP!$Q:$Q,CXP!$F:$F,$J$28+4,CXP!$N:$N,"No",CXP!$Q:$Q,">0")
B40: Sábado | C40: =$J$28+5 | D40: =COUNTIFS(CXP!$F:$F,$J$28+5,CXP!$N:$N,"No",CXP!$Q:$Q,">0") | E40: =SUMIFS(CXP!$Q:$Q,CXP!$F:$F,$J$28+5,CXP!$N:$N,"No",CXP!$Q:$Q,">0")
B41: Domingo | C41: =$J$28+6 | D41: =COUNTIFS(CXP!$F:$F,$J$28+6,CXP!$N:$N,"No",CXP!$Q:$Q,">0") | E41: =SUMIFS(CXP!$Q:$Q,CXP!$F:$F,$J$28+6,CXP!$N:$N,"No",CXP!$Q:$Q,">0")
B42: TOTAL SEMANA | D42: =SUM(D35:D41) | E42: =SUM(E35:E41)
B44: 🧾 DETALLE PENDIENTE POR PROVEEDOR (Semana + Vencidas)
B45: Proveedor | C45: Pendiente Semana | D45: Vencido | E45: TOTAL PENDIENTE | F45: Facturas | G45: Prioridad
B46: {=IFERROR(_xlfn._xlws.SORT(_xlfn.UNIQUE(_xlfn._xlws.FILTER(CXP!$C$2:$C$5000,(CXP!$Q$2:$Q$5000>0)*(CXP!$N$2:$N$5000="No")))),"Sin pendientes")} | C46: {=IFERROR(_xlfn.MAP(_xlfn.ANCHORARRAY(B46),_xlfn.LAMBDA(_xlpm.prov,SUMIFS(CXP!$Q$2:$Q$5000,CXP!$C$2:$C$5000,_xlpm.prov,CXP!$F$2:$F$5000,">="&$J$28,CXP!$F$2:$F$5000,"<="&$K$28,CXP!$N$2:$N$5000,"No"))),0)} | D46: {=IFERROR(_xlfn.MAP(_xlfn.ANCHORARRAY(B46),_xlfn.LAMBDA(_xlpm.prov,SUMIFS(CXP!$Q$2:$Q$5000,CXP!$C$2:$C$5000,_xlpm.prov,CXP!$F$2:$F$5000,"<"&$J$28,CXP!$N$2:$N$5000,"No"))),0)} | E46: {=_xlfn.ANCHORARRAY(C46)+_xlfn.ANCHORARRAY(D46)} | F46: {=IFERROR(_xlfn.MAP(_xlfn.ANCHORARRAY(B46),_xlfn.LAMBDA(_xlpm.prov,COUNTIFS(CXP!$C$2:$C$5000,_xlpm.prov,CXP!$Q$2:$Q$5000,">0",CXP!$N$2:$N$5000,"No"))),0)} | G46: {=IFERROR(_xlfn.MAP(_xlfn.ANCHORARRAY(D46),_xlfn.LAMBDA(_xlpm.venc,IF(_xlpm.venc>0,"🔴 URGENTE",IF(C46>0,"🟡 ESTA SEMANA","🟢 OK")))),"")}
B47: 📊 TOTAL PENDIENTE | C47: =SUM(_xlfn.ANCHORARRAY(C46)) | D47: =SUM(_xlfn.ANCHORARRAY(D46)) | E47: =SUM(_xlfn.ANCHORARRAY(E46)) | F47: =SUM(_xlfn.ANCHORARRAY(F46))
B49: ⚠️ FACTURAS VENCIDAS (Requieren Atención Inmediata)
B50: Proveedor | C50: Factura | D50: Fecha Venc. | E50: Días Vencida | F50: Monto Pendiente | G50: Ubicación
B51: {=IFERROR(_xlfn._xlws.SORT(_xlfn._xlws.FILTER(CHOOSE({1,2,3,4,5,6},CXP!$C$2:$C$5000,CXP!$D$2:$D$5000,CXP!$F$2:$F$5000,TODAY()-CXP!$F$2:$F$5000,CXP!$Q$2:$Q$5000,CXP!$B$2:$B$5000),(CXP!$F$2:$F$5000<$J$28)*(CXP!$N$2:$N$5000="No")*(CXP!$Q$2:$Q$5000>0)),4,-1),"✅ No hay facturas vencidas")}
B54: 📌 INSIGHTS CLAVE
B55: • Tasa de pago del 80.3% - Buen comportamiento general de pagos
B56: • RD$ 5.0M pendiente de pago (19.7% del total facturado)
B57: • JUAN BEATO lidera tanto en monto total (RD$ 7.6M) como en pendiente (RD$ 1.95M)
B58: • La Cata SJM tiene el mayor porcentaje de saldo pendiente (61% de sus facturas)
B59: • 23 facturas vencidas (🔴) requieren atención inmediata
B60: • La Cata LMF concentra el 55% de las compras totales (RD$ 14M)
B61: • Los 3 principales proveedores representan el 77% del monto total

Sheet Comparativo
A1: 📊 DASHBOARD COMPARATIVO - LA CATA | N1: Fecha Referencia: | O1: =TODAY()
A3: 📅 VENTAS SEMANA ACTUAL
A4: Día | B4: Fecha | C4: La Cata LMF | D4: La Cata DF | E4: La Cata SJM | F4: TOTAL DÍA | G4: % vs Promedio
A5: Lunes | B5: =$O$1-WEEKDAY($O$1,2)+1 | C5: =SUMIFS('Ventas Diarias'!$J:$J,'Ventas Diarias'!$A:$A,B5,'Ventas Diarias'!$B:$B,"La Cata LMF") | D5: =SUMIFS('Ventas Diarias'!$J:$J,'Ventas Diarias'!$A:$A,B5,'Ventas Diarias'!$B:$B,"La Cata DF") | E5: =SUMIFS('Ventas Diarias'!$J:$J,'Ventas Diarias'!$A:$A,B5,'Ventas Diarias'!$B:$B,"La Cata SJM") | F5: =C5+D5+E5 | G5: =IFERROR(F5/AVERAGE('Ventas Diarias'!$J:$J)-1,0)
A6: Martes | B6: =$O$1-WEEKDAY($O$1,2)+2 | C6: =SUMIFS('Ventas Diarias'!$J:$J,'Ventas Diarias'!$A:$A,B6,'Ventas Diarias'!$B:$B,"La Cata LMF") | D6: =SUMIFS('Ventas Diarias'!$J:$J,'Ventas Diarias'!$A:$A,B6,'Ventas Diarias'!$B:$B,"La Cata DF") | E6: =SUMIFS('Ventas Diarias'!$J:$J,'Ventas Diarias'!$A:$A,B6,'Ventas Diarias'!$B:$B,"La Cata SJM") | F6: =C6+D6+E6 | G6: =IFERROR(F6/AVERAGE('Ventas Diarias'!$J:$J)-1,0)
A7: Miércoles | B7: =$O$1-WEEKDAY($O$1,2)+3 | C7: =SUMIFS('Ventas Diarias'!$J:$J,'Ventas Diarias'!$A:$A,B7,'Ventas Diarias'!$B:$B,"La Cata LMF") | D7: =SUMIFS('Ventas Diarias'!$J:$J,'Ventas Diarias'!$A:$A,B7,'Ventas Diarias'!$B:$B,"La Cata DF") | E7: =SUMIFS('Ventas Diarias'!$J:$J,'Ventas Diarias'!$A:$A,B7,'Ventas Diarias'!$B:$B,"La Cata SJM") | F7: =C7+D7+E7 | G7: =IFERROR(F7/AVERAGE('Ventas Diarias'!$J:$J)-1,0)
A8: Jueves | B8: =$O$1-WEEKDAY($O$1,2)+4 | C8: =SUMIFS('Ventas Diarias'!$J:$J,'Ventas Diarias'!$A:$A,B8,'Ventas Diarias'!$B:$B,"La Cata LMF") | D8: =SUMIFS('Ventas Diarias'!$J:$J,'Ventas Diarias'!$A:$A,B8,'Ventas Diarias'!$B:$B,"La Cata DF") | E8: =SUMIFS('Ventas Diarias'!$J:$J,'Ventas Diarias'!$A:$A,B8,'Ventas Diarias'!$B:$B,"La Cata SJM") | F8: =C8+D8+E8 | G8: =IFERROR(F8/AVERAGE('Ventas Diarias'!$J:$J)-1,0)
A9: Viernes | B9: =$O$1-WEEKDAY($O$1,2)+5 | C9: =SUMIFS('Ventas Diarias'!$J:$J,'Ventas Diarias'!$A:$A,B9,'Ventas Diarias'!$B:$B,"La Cata LMF") | D9: =SUMIFS('Ventas Diarias'!$J:$J,'Ventas Diarias'!$A:$A,B9,'Ventas Diarias'!$B:$B,"La Cata DF") | E9: =SUMIFS('Ventas Diarias'!$J:$J,'Ventas Diarias'!$A:$A,B9,'Ventas Diarias'!$B:$B,"La Cata SJM") | F9: =C9+D9+E9 | G9: =IFERROR(F9/AVERAGE('Ventas Diarias'!$J:$J)-1,0)
A10: Sábado | B10: =$O$1-WEEKDAY($O$1,2)+6 | C10: =SUMIFS('Ventas Diarias'!$J:$J,'Ventas Diarias'!$A:$A,B10,'Ventas Diarias'!$B:$B,"La Cata LMF") | D10: =SUMIFS('Ventas Diarias'!$J:$J,'Ventas Diarias'!$A:$A,B10,'Ventas Diarias'!$B:$B,"La Cata DF") | E10: =SUMIFS('Ventas Diarias'!$J:$J,'Ventas Diarias'!$A:$A,B10,'Ventas Diarias'!$B:$B,"La Cata SJM") | F10: =C10+D10+E10 | G10: =IFERROR(F10/AVERAGE('Ventas Diarias'!$J:$J)-1,0)
A11: Domingo | B11: =$O$1-WEEKDAY($O$1,2)+7 | C11: =SUMIFS('Ventas Diarias'!$J:$J,'Ventas Diarias'!$A:$A,B11,'Ventas Diarias'!$B:$B,"La Cata LMF") | D11: =SUMIFS('Ventas Diarias'!$J:$J,'Ventas Diarias'!$A:$A,B11,'Ventas Diarias'!$B:$B,"La Cata DF") | E11: =SUMIFS('Ventas Diarias'!$J:$J,'Ventas Diarias'!$A:$A,B11,'Ventas Diarias'!$B:$B,"La Cata SJM") | F11: =C11+D11+E11 | G11: =IFERROR(F11/AVERAGE('Ventas Diarias'!$J:$J)-1,0)
A12: TOTAL SEMANA | C12: =SUM(C5:C11) | D12: =SUM(D5:D11) | E12: =SUM(E5:E11) | F12: =SUM(F5:F11) | G12: =IFERROR(F12/(AVERAGE('Ventas Diarias'!$J:$J)*7)-1,0)
A14: 📆 VENTAS MENSUALES POR TIENDA | Q14: Distribución Total 2026
A15: Mes | B15: La Cata LMF | C15: La Cata DF | D15: La Cata SJM | E15: TOTAL | F15: % LMF | G15: % DF | H15: % SJM | Q15: Tienda | R15: Total
A16: Enero 2026 | B16: =SUMIFS('Ventas Diarias'!$J:$J,'Ventas Diarias'!$A:$A,">="&46023,'Ventas Diarias'!$A:$A,"<="&46053,'Ventas Diarias'!$B:$B,"La Cata LMF") | C16: =SUMIFS('Ventas Diarias'!$J:$J,'Ventas Diarias'!$A:$A,">="&46023,'Ventas Diarias'!$A:$A,"<="&46053,'Ventas Diarias'!$B:$B,"La Cata DF") | D16: =SUMIFS('Ventas Diarias'!$J:$J,'Ventas Diarias'!$A:$A,">="&46023,'Ventas Diarias'!$A:$A,"<="&46053,'Ventas Diarias'!$B:$B,"La Cata SJM") | E16: =B16+C16+D16 | F16: =IFERROR(B16/E16,0) | G16: =IFERROR(C16/E16,0) | H16: =IFERROR(D16/E16,0) | Q16: La Cata LMF | R16: =B28
A17: Febrero 2026 | B17: =SUMIFS('Ventas Diarias'!$J:$J,'Ventas Diarias'!$A:$A,">="&46054,'Ventas Diarias'!$A:$A,"<="&46081,'Ventas Diarias'!$B:$B,"La Cata LMF") | C17: =SUMIFS('Ventas Diarias'!$J:$J,'Ventas Diarias'!$A:$A,">="&46054,'Ventas Diarias'!$A:$A,"<="&46081,'Ventas Diarias'!$B:$B,"La Cata DF") | D17: =SUMIFS('Ventas Diarias'!$J:$J,'Ventas Diarias'!$A:$A,">="&46054,'Ventas Diarias'!$A:$A,"<="&46081,'Ventas Diarias'!$B:$B,"La Cata SJM") | E17: =B17+C17+D17 | F17: =IFERROR(B17/E17,0) | G17: =IFERROR(C17/E17,0) | H17: =IFERROR(D17/E17,0) | Q17: La Cata DF | R17: =C28
A18: Marzo 2026 | B18: =SUMIFS('Ventas Diarias'!$J:$J,'Ventas Diarias'!$A:$A,">="&46082,'Ventas Diarias'!$A:$A,"<="&46112,'Ventas Diarias'!$B:$B,"La Cata LMF") | C18: =SUMIFS('Ventas Diarias'!$J:$J,'Ventas Diarias'!$A:$A,">="&46082,'Ventas Diarias'!$A:$A,"<="&46112,'Ventas Diarias'!$B:$B,"La Cata DF") | D18: =SUMIFS('Ventas Diarias'!$J:$J,'Ventas Diarias'!$A:$A,">="&46082,'Ventas Diarias'!$A:$A,"<="&46112,'Ventas Diarias'!$B:$B,"La Cata SJM") | E18: =B18+C18+D18 | F18: =IFERROR(B18/E18,0) | G18: =IFERROR(C18/E18,0) | H18: =IFERROR(D18/E18,0) | Q18: La Cata SJM | R18: =D28
A19: Abril 2026 | B19: =SUMIFS('Ventas Diarias'!$J:$J,'Ventas Diarias'!$A:$A,">="&46113,'Ventas Diarias'!$A:$A,"<="&46142,'Ventas Diarias'!$B:$B,"La Cata LMF") | C19: =SUMIFS('Ventas Diarias'!$J:$J,'Ventas Diarias'!$A:$A,">="&46113,'Ventas Diarias'!$A:$A,"<="&46142,'Ventas Diarias'!$B:$B,"La Cata DF") | D19: =SUMIFS('Ventas Diarias'!$J:$J,'Ventas Diarias'!$A:$A,">="&46113,'Ventas Diarias'!$A:$A,"<="&46142,'Ventas Diarias'!$B:$B,"La Cata SJM") | E19: =B19+C19+D19 | F19: =IFERROR(B19/E19,0) | G19: =IFERROR(C19/E19,0) | H19: =IFERROR(D19/E19,0)
A20: Mayo 2026 | B20: =SUMIFS('Ventas Diarias'!$J:$J,'Ventas Diarias'!$A:$A,">="&46143,'Ventas Diarias'!$A:$A,"<="&46173,'Ventas Diarias'!$B:$B,"La Cata LMF") | C20: =SUMIFS('Ventas Diarias'!$J:$J,'Ventas Diarias'!$A:$A,">="&46143,'Ventas Diarias'!$A:$A,"<="&46173,'Ventas Diarias'!$B:$B,"La Cata DF") | D20: =SUMIFS('Ventas Diarias'!$J:$J,'Ventas Diarias'!$A:$A,">="&46143,'Ventas Diarias'!$A:$A,"<="&46173,'Ventas Diarias'!$B:$B,"La Cata SJM") | E20: =B20+C20+D20 | F20: =IFERROR(B20/E20,0) | G20: =IFERROR(C20/E20,0) | H20: =IFERROR(D20/E20,0) | Q20: Métodos de Pago
A21: Junio 2026 | B21: =SUMIFS('Ventas Diarias'!$J:$J,'Ventas Diarias'!$A:$A,">="&46174,'Ventas Diarias'!$A:$A,"<="&46203,'Ventas Diarias'!$B:$B,"La Cata LMF") | C21: =SUMIFS('Ventas Diarias'!$J:$J,'Ventas Diarias'!$A:$A,">="&46174,'Ventas Diarias'!$A:$A,"<="&46203,'Ventas Diarias'!$B:$B,"La Cata DF") | D21: =SUMIFS('Ventas Diarias'!$J:$J,'Ventas Diarias'!$A:$A,">="&46174,'Ventas Diarias'!$A:$A,"<="&46203,'Ventas Diarias'!$B:$B,"La Cata SJM") | E21: =B21+C21+D21 | F21: =IFERROR(B21/E21,0) | G21: =IFERROR(C21/E21,0) | H21: =IFERROR(D21/E21,0) | Q21: Tienda | R21: Efectivo | S21: Tarjeta Neta | T21: Transferencias
A22: Julio 2026 | B22: =SUMIFS('Ventas Diarias'!$J:$J,'Ventas Diarias'!$A:$A,">="&46204,'Ventas Diarias'!$A:$A,"<="&46234,'Ventas Diarias'!$B:$B,"La Cata LMF") | C22: =SUMIFS('Ventas Diarias'!$J:$J,'Ventas Diarias'!$A:$A,">="&46204,'Ventas Diarias'!$A:$A,"<="&46234,'Ventas Diarias'!$B:$B,"La Cata DF") | D22: =SUMIFS('Ventas Diarias'!$J:$J,'Ventas Diarias'!$A:$A,">="&46204,'Ventas Diarias'!$A:$A,"<="&46234,'Ventas Diarias'!$B:$B,"La Cata SJM") | E22: =B22+C22+D22 | F22: =IFERROR(B22/E22,0) | G22: =IFERROR(C22/E22,0) | H22: =IFERROR(D22/E22,0)
A23: Agosto 2026 | B23: =SUMIFS('Ventas Diarias'!$J:$J,'Ventas Diarias'!$A:$A,">="&46235,'Ventas Diarias'!$A:$A,"<="&46265,'Ventas Diarias'!$B:$B,"La Cata LMF") | C23: =SUMIFS('Ventas Diarias'!$J:$J,'Ventas Diarias'!$A:$A,">="&46235,'Ventas Diarias'!$A:$A,"<="&46265,'Ventas Diarias'!$B:$B,"La Cata DF") | D23: =SUMIFS('Ventas Diarias'!$J:$J,'Ventas Diarias'!$A:$A,">="&46235,'Ventas Diarias'!$A:$A,"<="&46265,'Ventas Diarias'!$B:$B,"La Cata SJM") | E23: =B23+C23+D23 | F23: =IFERROR(B23/E23,0) | G23: =IFERROR(C23/E23,0) | H23: =IFERROR(D23/E23,0)
A24: Septiembre 2026 | B24: =SUMIFS('Ventas Diarias'!$J:$J,'Ventas Diarias'!$A:$A,">="&46266,'Ventas Diarias'!$A:$A,"<="&46295,'Ventas Diarias'!$B:$B,"La Cata LMF") | C24: =SUMIFS('Ventas Diarias'!$J:$J,'Ventas Diarias'!$A:$A,">="&46266,'Ventas Diarias'!$A:$A,"<="&46295,'Ventas Diarias'!$B:$B,"La Cata DF") | D24: =SUMIFS('Ventas Diarias'!$J:$J,'Ventas Diarias'!$A:$A,">="&46266,'Ventas Diarias'!$A:$A,"<="&46295,'Ventas Diarias'!$B:$B,"La Cata SJM") | E24: =B24+C24+D24 | F24: =IFERROR(B24/E24,0) | G24: =IFERROR(C24/E24,0) | H24: =IFERROR(D24/E24,0)
A25: Octubre 2026 | B25: =SUMIFS('Ventas Diarias'!$J:$J,'Ventas Diarias'!$A:$A,">="&46296,'Ventas Diarias'!$A:$A,"<="&46326,'Ventas Diarias'!$B:$B,"La Cata LMF") | C25: =SUMIFS('Ventas Diarias'!$J:$J,'Ventas Diarias'!$A:$A,">="&46296,'Ventas Diarias'!$A:$A,"<="&46326,'Ventas Diarias'!$B:$B,"La Cata DF") | D25: =SUMIFS('Ventas Diarias'!$J:$J,'Ventas Diarias'!$A:$A,">="&46296,'Ventas Diarias'!$A:$A,"<="&46326,'Ventas Diarias'!$B:$B,"La Cata SJM") | E25: =B25+C25+D25 | F25: =IFERROR(B25/E25,0) | G25: =IFERROR(C25/E25,0) | H25: =IFERROR(D25/E25,0)
A26: Noviembre 2026 | B26: =SUMIFS('Ventas Diarias'!$J:$J,'Ventas Diarias'!$A:$A,">="&46327,'Ventas Diarias'!$A:$A,"<="&46356,'Ventas Diarias'!$B:$B,"La Cata LMF") | C26: =SUMIFS('Ventas Diarias'!$J:$J,'Ventas Diarias'!$A:$A,">="&46327,'Ventas Diarias'!$A:$A,"<="&46356,'Ventas Diarias'!$B:$B,"La Cata DF") | D26: =SUMIFS('Ventas Diarias'!$J:$J,'Ventas Diarias'!$A:$A,">="&46327,'Ventas Diarias'!$A:$A,"<="&46356,'Ventas Diarias'!$B:$B,"La Cata SJM") | E26: =B26+C26+D26 | F26: =IFERROR(B26/E26,0) | G26: =IFERROR(C26/E26,0) | H26: =IFERROR(D26/E26,0)
A27: Diciembre 2026 | B27: =SUMIFS('Ventas Diarias'!$J:$J,'Ventas Diarias'!$A:$A,">="&46357,'Ventas Diarias'!$A:$A,"<="&46387,'Ventas Diarias'!$B:$B,"La Cata LMF") | C27: =SUMIFS('Ventas Diarias'!$J:$J,'Ventas Diarias'!$A:$A,">="&46357,'Ventas Diarias'!$A:$A,"<="&46387,'Ventas Diarias'!$B:$B,"La Cata DF") | D27: =SUMIFS('Ventas Diarias'!$J:$J,'Ventas Diarias'!$A:$A,">="&46357,'Ventas Diarias'!$A:$A,"<="&46387,'Ventas Diarias'!$B:$B,"La Cata SJM") | E27: =B27+C27+D27 | F27: =IFERROR(B27/E27,0) | G27: =IFERROR(C27/E27,0) | H27: =IFERROR(D27/E27,0)
A28: TOTAL 2026 | B28: =SUM(B16:B27) | C28: =SUM(C16:C27) | D28: =SUM(D16:D27) | E28: =SUM(E16:E27) | F28: =IFERROR(B28/E28,0) | G28: =IFERROR(C28/E28,0) | H28: =IFERROR(D28/E28,0) | Q28: LMF | R28: =B47 | S28: =C47-D47 | T28: =E47
A29: Crecimiento Mensual | B29: =IFERROR((B21-B20)/B20,"N/A") | C29: =IFERROR((C21-C20)/C20,"N/A") | D29: =IFERROR((D21-D20)/D20,"N/A") | E29: =IFERROR((E21-E20)/E20,"N/A") | F29: =IFERROR(B29/E29,0) | G29: =IFERROR(C29/E29,0) | H29: =IFERROR(D29/E29,0) | Q29: DF | R29: =B48 | S29: =C48-D48 | T29: =E48
A30: 📈 INDICADORES CLAVE (KPIs) | Q30: SJM | R30: =B49 | S30: =C49-D49 | T30: =E49
A31: Promedio Diario LMF: | B31: =AVERAGEIF('Ventas Diarias'!$B:$B,"La Cata LMF",'Ventas Diarias'!$J:$J) | C31: Promedio Diario DF: | D31: =AVERAGEIF('Ventas Diarias'!$B:$B,"La Cata DF",'Ventas Diarias'!$J:$J) | E31: Promedio Diario SJM: | F31: =AVERAGEIF('Ventas Diarias'!$B:$B,"La Cata SJM",'Ventas Diarias'!$J:$J)
A32: Mejor Día LMF: | B32: =_xlfn.MAXIFS('Ventas Diarias'!$J:$J,'Ventas Diarias'!$B:$B,"La Cata LMF") | C32: Mejor Día DF: | D32: =_xlfn.MAXIFS('Ventas Diarias'!$J:$J,'Ventas Diarias'!$B:$B,"La Cata DF") | E32: Mejor Día SJM: | F32: =_xlfn.MAXIFS('Ventas Diarias'!$J:$J,'Ventas Diarias'!$B:$B,"La Cata SJM")
L33: 💵 CONTROL DE DEPÓSITOS VS EFECTIVO VENDIDO
A34: 📊 VENTAS PROMEDIO POR DÍA DE LA SEMANA | L34: Ciclo: Domingo a Sábado | Depósito: Lunes siguiente | Tolerancia: ±RD$500
A35: Día | B35: La Cata LMF | C35: La Cata DF | D35: La Cata SJM | E35: Promedio Total
A36: Lunes | B36: {=IFERROR(SUMPRODUCT(('Ventas Diarias'!$B$2:$B$500="La Cata LMF")*(WEEKDAY('Ventas Diarias'!$A$2:$A$500,2)=1)*('Ventas Diarias'!$J$2:$J$500))/SUMPRODUCT(('Ventas Diarias'!$B$2:$B$500="La Cata LMF")*(WEEKDAY('Ventas Diarias'!$A$2:$A$500,2)=1)*('Ventas Diarias'!$J$2:$J$500<>0)),0)} | C36: {=IFERROR(SUMPRODUCT(('Ventas Diarias'!$B$2:$B$500="La Cata DF")*(WEEKDAY('Ventas Diarias'!$A$2:$A$500,2)=1)*('Ventas Diarias'!$J$2:$J$500))/SUMPRODUCT(('Ventas Diarias'!$B$2:$B$500="La Cata DF")*(WEEKDAY('Ventas Diarias'!$A$2:$A$500,2)=1)*('Ventas Diarias'!$J$2:$J$500<>0)),0)} | D36: {=IFERROR(SUMPRODUCT(('Ventas Diarias'!$B$2:$B$500="La Cata SJM")*(WEEKDAY('Ventas Diarias'!$A$2:$A$500,2)=1)*('Ventas Diarias'!$J$2:$J$500))/SUMPRODUCT(('Ventas Diarias'!$B$2:$B$500="La Cata SJM")*(WEEKDAY('Ventas Diarias'!$A$2:$A$500,2)=1)*('Ventas Diarias'!$J$2:$J$500<>0)),0)} | E36: =IFERROR(AVERAGE(B36:D36),0) | L36: 🏪 LA CATA LMF
A37: Martes | B37: {=IFERROR(SUMPRODUCT(('Ventas Diarias'!$B$2:$B$500="La Cata LMF")*(WEEKDAY('Ventas Diarias'!$A$2:$A$500,2)=2)*('Ventas Diarias'!$J$2:$J$500))/SUMPRODUCT(('Ventas Diarias'!$B$2:$B$500="La Cata LMF")*(WEEKDAY('Ventas Diarias'!$A$2:$A$500,2)=2)*('Ventas Diarias'!$J$2:$J$500<>0)),0)} | C37: {=IFERROR(SUMPRODUCT(('Ventas Diarias'!$B$2:$B$500="La Cata DF")*(WEEKDAY('Ventas Diarias'!$A$2:$A$500,2)=2)*('Ventas Diarias'!$J$2:$J$500))/SUMPRODUCT(('Ventas Diarias'!$B$2:$B$500="La Cata DF")*(WEEKDAY('Ventas Diarias'!$A$2:$A$500,2)=2)*('Ventas Diarias'!$J$2:$J$500<>0)),0)} | D37: {=IFERROR(SUMPRODUCT(('Ventas Diarias'!$B$2:$B$500="La Cata SJM")*(WEEKDAY('Ventas Diarias'!$A$2:$A$500,2)=2)*('Ventas Diarias'!$J$2:$J$500))/SUMPRODUCT(('Ventas Diarias'!$B$2:$B$500="La Cata SJM")*(WEEKDAY('Ventas Diarias'!$A$2:$A$500,2)=2)*('Ventas Diarias'!$J$2:$J$500<>0)),0)} | E37: =IFERROR(AVERAGE(B37:D37),0) | L37: Semana | M37: Inicio | N37: Fin | O37: Efectivo Vendido | P37: Depósito | Q37: Diferencia | R37: % Var | S37: Estado
A38: Miércoles | B38: {=IFERROR(SUMPRODUCT(('Ventas Diarias'!$B$2:$B$500="La Cata LMF")*(WEEKDAY('Ventas Diarias'!$A$2:$A$500,2)=3)*('Ventas Diarias'!$J$2:$J$500))/SUMPRODUCT(('Ventas Diarias'!$B$2:$B$500="La Cata LMF")*(WEEKDAY('Ventas Diarias'!$A$2:$A$500,2)=3)*('Ventas Diarias'!$J$2:$J$500<>0)),0)} | C38: {=IFERROR(SUMPRODUCT(('Ventas Diarias'!$B$2:$B$500="La Cata DF")*(WEEKDAY('Ventas Diarias'!$A$2:$A$500,2)=3)*('Ventas Diarias'!$J$2:$J$500))/SUMPRODUCT(('Ventas Diarias'!$B$2:$B$500="La Cata DF")*(WEEKDAY('Ventas Diarias'!$A$2:$A$500,2)=3)*('Ventas Diarias'!$J$2:$J$500<>0)),0)} | D38: {=IFERROR(SUMPRODUCT(('Ventas Diarias'!$B$2:$B$500="La Cata SJM")*(WEEKDAY('Ventas Diarias'!$A$2:$A$500,2)=3)*('Ventas Diarias'!$J$2:$J$500))/SUMPRODUCT(('Ventas Diarias'!$B$2:$B$500="La Cata SJM")*(WEEKDAY('Ventas Diarias'!$A$2:$A$500,2)=3)*('Ventas Diarias'!$J$2:$J$500<>0)),0)} | E38: =IFERROR(AVERAGE(B38:D38),0) | L38: 1 | M38: =TODAY()-WEEKDAY(TODAY())-6 | N38: =M38+6 | O38: =SUMIFS('Ventas Diarias'!$C:$C,'Ventas Diarias'!$A:$A,">="&M38,'Ventas Diarias'!$A:$A,"<="&N38,'Ventas Diarias'!$B:$B,"La Cata LMF") | P38: =SUMIFS('Ventas Diarias'!$N:$N,'Ventas Diarias'!$A:$A,">="&M38,'Ventas Diarias'!$A:$A,"<="&N38+2,'Ventas Diarias'!$B:$B,"La Cata LMF") | Q38: =P38-O38 | R38: =IFERROR(Q38/O38,0) | S38: =IF(ABS(Q38)<=500,"✅ OK",IF(Q38<-500,"🔴 Faltante",IF(Q38>500,"🟢 Sobrante","")))
A39: Jueves | B39: {=IFERROR(SUMPRODUCT(('Ventas Diarias'!$B$2:$B$500="La Cata LMF")*(WEEKDAY('Ventas Diarias'!$A$2:$A$500,2)=4)*('Ventas Diarias'!$J$2:$J$500))/SUMPRODUCT(('Ventas Diarias'!$B$2:$B$500="La Cata LMF")*(WEEKDAY('Ventas Diarias'!$A$2:$A$500,2)=4)*('Ventas Diarias'!$J$2:$J$500<>0)),0)} | C39: {=IFERROR(SUMPRODUCT(('Ventas Diarias'!$B$2:$B$500="La Cata DF")*(WEEKDAY('Ventas Diarias'!$A$2:$A$500,2)=4)*('Ventas Diarias'!$J$2:$J$500))/SUMPRODUCT(('Ventas Diarias'!$B$2:$B$500="La Cata DF")*(WEEKDAY('Ventas Diarias'!$A$2:$A$500,2)=4)*('Ventas Diarias'!$J$2:$J$500<>0)),0)} | D39: {=IFERROR(SUMPRODUCT(('Ventas Diarias'!$B$2:$B$500="La Cata SJM")*(WEEKDAY('Ventas Diarias'!$A$2:$A$500,2)=4)*('Ventas Diarias'!$J$2:$J$500))/SUMPRODUCT(('Ventas Diarias'!$B$2:$B$500="La Cata SJM")*(WEEKDAY('Ventas Diarias'!$A$2:$A$500,2)=4)*('Ventas Diarias'!$J$2:$J$500<>0)),0)} | E39: =IFERROR(AVERAGE(B39:D39),0) | L39: 2 | M39: =M38-7 | N39: =M39+6 | O39: =SUMIFS('Ventas Diarias'!$C:$C,'Ventas Diarias'!$A:$A,">="&M39,'Ventas Diarias'!$A:$A,"<="&N39,'Ventas Diarias'!$B:$B,"La Cata LMF") | P39: =SUMIFS('Ventas Diarias'!$N:$N,'Ventas Diarias'!$A:$A,">="&M39,'Ventas Diarias'!$A:$A,"<="&N39+2,'Ventas Diarias'!$B:$B,"La Cata LMF") | Q39: =P39-O39 | R39: =IFERROR(Q39/O39,0) | S39: =IF(ABS(Q39)<=500,"✅ OK",IF(Q39<-500,"🔴 Faltante",IF(Q39>500,"🟢 Sobrante","")))
A40: Viernes | B40: {=IFERROR(SUMPRODUCT(('Ventas Diarias'!$B$2:$B$500="La Cata LMF")*(WEEKDAY('Ventas Diarias'!$A$2:$A$500,2)=5)*('Ventas Diarias'!$J$2:$J$500))/SUMPRODUCT(('Ventas Diarias'!$B$2:$B$500="La Cata LMF")*(WEEKDAY('Ventas Diarias'!$A$2:$A$500,2)=5)*('Ventas Diarias'!$J$2:$J$500<>0)),0)} | C40: {=IFERROR(SUMPRODUCT(('Ventas Diarias'!$B$2:$B$500="La Cata DF")*(WEEKDAY('Ventas Diarias'!$A$2:$A$500,2)=5)*('Ventas Diarias'!$J$2:$J$500))/SUMPRODUCT(('Ventas Diarias'!$B$2:$B$500="La Cata DF")*(WEEKDAY('Ventas Diarias'!$A$2:$A$500,2)=5)*('Ventas Diarias'!$J$2:$J$500<>0)),0)} | D40: {=IFERROR(SUMPRODUCT(('Ventas Diarias'!$B$2:$B$500="La Cata SJM")*(WEEKDAY('Ventas Diarias'!$A$2:$A$500,2)=5)*('Ventas Diarias'!$J$2:$J$500))/SUMPRODUCT(('Ventas Diarias'!$B$2:$B$500="La Cata SJM")*(WEEKDAY('Ventas Diarias'!$A$2:$A$500,2)=5)*('Ventas Diarias'!$J$2:$J$500<>0)),0)} | E40: =IFERROR(AVERAGE(B40:D40),0) | L40: 3 | M40: =M39-7 | N40: =M40+6 | O40: =SUMIFS('Ventas Diarias'!$C:$C,'Ventas Diarias'!$A:$A,">="&M40,'Ventas Diarias'!$A:$A,"<="&N40,'Ventas Diarias'!$B:$B,"La Cata LMF") | P40: =SUMIFS('Ventas Diarias'!$N:$N,'Ventas Diarias'!$A:$A,">="&M40,'Ventas Diarias'!$A:$A,"<="&N40+2,'Ventas Diarias'!$B:$B,"La Cata LMF") | Q40: =P40-O40 | R40: =IFERROR(Q40/O40,0) | S40: =IF(ABS(Q40)<=500,"✅ OK",IF(Q40<-500,"🔴 Faltante",IF(Q40>500,"🟢 Sobrante","")))
A41: Sábado | B41: {=IFERROR(SUMPRODUCT(('Ventas Diarias'!$B$2:$B$500="La Cata LMF")*(WEEKDAY('Ventas Diarias'!$A$2:$A$500,2)=6)*('Ventas Diarias'!$J$2:$J$500))/SUMPRODUCT(('Ventas Diarias'!$B$2:$B$500="La Cata LMF")*(WEEKDAY('Ventas Diarias'!$A$2:$A$500,2)=6)*('Ventas Diarias'!$J$2:$J$500<>0)),0)} | C41: {=IFERROR(SUMPRODUCT(('Ventas Diarias'!$B$2:$B$500="La Cata DF")*(WEEKDAY('Ventas Diarias'!$A$2:$A$500,2)=6)*('Ventas Diarias'!$J$2:$J$500))/SUMPRODUCT(('Ventas Diarias'!$B$2:$B$500="La Cata DF")*(WEEKDAY('Ventas Diarias'!$A$2:$A$500,2)=6)*('Ventas Diarias'!$J$2:$J$500<>0)),0)} | D41: {=IFERROR(SUMPRODUCT(('Ventas Diarias'!$B$2:$B$500="La Cata SJM")*(WEEKDAY('Ventas Diarias'!$A$2:$A$500,2)=6)*('Ventas Diarias'!$J$2:$J$500))/SUMPRODUCT(('Ventas Diarias'!$B$2:$B$500="La Cata SJM")*(WEEKDAY('Ventas Diarias'!$A$2:$A$500,2)=6)*('Ventas Diarias'!$J$2:$J$500<>0)),0)} | E41: =IFERROR(AVERAGE(B41:D41),0) | L41: 4 | M41: =M40-7 | N41: =M41+6 | O41: =SUMIFS('Ventas Diarias'!$C:$C,'Ventas Diarias'!$A:$A,">="&M41,'Ventas Diarias'!$A:$A,"<="&N41,'Ventas Diarias'!$B:$B,"La Cata LMF") | P41: =SUMIFS('Ventas Diarias'!$N:$N,'Ventas Diarias'!$A:$A,">="&M41,'Ventas Diarias'!$A:$A,"<="&N41+2,'Ventas Diarias'!$B:$B,"La Cata LMF") | Q41: =P41-O41 | R41: =IFERROR(Q41/O41,0) | S41: =IF(ABS(Q41)<=500,"✅ OK",IF(Q41<-500,"🔴 Faltante",IF(Q41>500,"🟢 Sobrante","")))
A42: Domingo | B42: {=IFERROR(SUMPRODUCT(('Ventas Diarias'!$B$2:$B$500="La Cata LMF")*(WEEKDAY('Ventas Diarias'!$A$2:$A$500,2)=7)*('Ventas Diarias'!$J$2:$J$500))/SUMPRODUCT(('Ventas Diarias'!$B$2:$B$500="La Cata LMF")*(WEEKDAY('Ventas Diarias'!$A$2:$A$500,2)=7)*('Ventas Diarias'!$J$2:$J$500<>0)),0)} | C42: {=IFERROR(SUMPRODUCT(('Ventas Diarias'!$B$2:$B$500="La Cata DF")*(WEEKDAY('Ventas Diarias'!$A$2:$A$500,2)=7)*('Ventas Diarias'!$J$2:$J$500))/SUMPRODUCT(('Ventas Diarias'!$B$2:$B$500="La Cata DF")*(WEEKDAY('Ventas Diarias'!$A$2:$A$500,2)=7)*('Ventas Diarias'!$J$2:$J$500<>0)),0)} | D42: {=IFERROR(SUMPRODUCT(('Ventas Diarias'!$B$2:$B$500="La Cata SJM")*(WEEKDAY('Ventas Diarias'!$A$2:$A$500,2)=7)*('Ventas Diarias'!$J$2:$J$500))/SUMPRODUCT(('Ventas Diarias'!$B$2:$B$500="La Cata SJM")*(WEEKDAY('Ventas Diarias'!$A$2:$A$500,2)=7)*('Ventas Diarias'!$J$2:$J$500<>0)),0)} | E42: =IFERROR(AVERAGE(B42:D42),0) | L42: 5 | M42: =M41-7 | N42: =M42+6 | O42: =SUMIFS('Ventas Diarias'!$C:$C,'Ventas Diarias'!$A:$A,">="&M42,'Ventas Diarias'!$A:$A,"<="&N42,'Ventas Diarias'!$B:$B,"La Cata LMF") | P42: =SUMIFS('Ventas Diarias'!$N:$N,'Ventas Diarias'!$A:$A,">="&M42,'Ventas Diarias'!$A:$A,"<="&N42+2,'Ventas Diarias'!$B:$B,"La Cata LMF") | Q42: =P42-O42 | R42: =IFERROR(Q42/O42,0) | S42: =IF(ABS(Q42)<=500,"✅ OK",IF(Q42<-500,"🔴 Faltante",IF(Q42>500,"🟢 Sobrante","")))
L43: 6 | M43: =M42-7 | N43: =M43+6 | O43: =SUMIFS('Ventas Diarias'!$C:$C,'Ventas Diarias'!$A:$A,">="&M43,'Ventas Diarias'!$A:$A,"<="&N43,'Ventas Diarias'!$B:$B,"La Cata LMF") | P43: =SUMIFS('Ventas Diarias'!$N:$N,'Ventas Diarias'!$A:$A,">="&M43,'Ventas Diarias'!$A:$A,"<="&N43+2,'Ventas Diarias'!$B:$B,"La Cata LMF") | Q43: =P43-O43 | R43: =IFERROR(Q43/O43,0) | S43: =IF(ABS(Q43)<=500,"✅ OK",IF(Q43<-500,"🔴 Faltante",IF(Q43>500,"🟢 Sobrante","")))
L44: 7 | M44: =M43-7 | N44: =M44+6 | O44: =SUMIFS('Ventas Diarias'!$C:$C,'Ventas Diarias'!$A:$A,">="&M44,'Ventas Diarias'!$A:$A,"<="&N44,'Ventas Diarias'!$B:$B,"La Cata LMF") | P44: =SUMIFS('Ventas Diarias'!$N:$N,'Ventas Diarias'!$A:$A,">="&M44,'Ventas Diarias'!$A:$A,"<="&N44+2,'Ventas Diarias'!$B:$B,"La Cata LMF") | Q44: =P44-O44 | R44: =IFERROR(Q44/O44,0) | S44: =IF(ABS(Q44)<=500,"✅ OK",IF(Q44<-500,"🔴 Faltante",IF(Q44>500,"🟢 Sobrante","")))
A45: 💳 ANÁLISIS DE MÉTODOS DE PAGO | L45: 8 | M45: =M44-7 | N45: =M45+6 | O45: =SUMIFS('Ventas Diarias'!$C:$C,'Ventas Diarias'!$A:$A,">="&M45,'Ventas Diarias'!$A:$A,"<="&N45,'Ventas Diarias'!$B:$B,"La Cata LMF") | P45: =SUMIFS('Ventas Diarias'!$N:$N,'Ventas Diarias'!$A:$A,">="&M45,'Ventas Diarias'!$A:$A,"<="&N45+2,'Ventas Diarias'!$B:$B,"La Cata LMF") | Q45: =P45-O45 | R45: =IFERROR(Q45/O45,0) | S45: =IF(ABS(Q45)<=500,"✅ OK",IF(Q45<-500,"🔴 Faltante",IF(Q45>500,"🟢 Sobrante","")))
A46: Tienda | B46: Efectivo | C46: Tarjeta Bruta | D46: Fee Tarjeta | E46: Transferencias | F46: Total
A47: La Cata LMF | B47: 13471413 | C47: 5379032 | D47: 185576.6 | E47: 811608.57 | F47: 19476477 | L47: 🏪 LA CATA DF
A48: La Cata DF | B48: 1526379.5 | C48: 730942.6 | D48: 25217.52 | E48: 34545 | F48: 2266649.6 | L48: Semana | M48: Inicio | N48: Fin | O48: Efectivo Vendido | P48: Depósito | Q48: Diferencia | R48: % Var | S48: Estado
A49: La Cata SJM | B49: 0 | C49: 0 | D49: 0 | E49: 0 | F49: 0 | L49: 1 | M49: =M38 | N49: =N38 | O49: =SUMIFS('Ventas Diarias'!$C:$C,'Ventas Diarias'!$A:$A,">="&M49,'Ventas Diarias'!$A:$A,"<="&N49,'Ventas Diarias'!$B:$B,"La Cata DF") | P49: =SUMIFS('Ventas Diarias'!$N:$N,'Ventas Diarias'!$A:$A,">="&M49,'Ventas Diarias'!$A:$A,"<="&N49+2,'Ventas Diarias'!$B:$B,"La Cata DF") | Q49: =P49-O49 | R49: =IFERROR(Q49/O49,0) | S49: =IF(ABS(Q49)<=500,"✅ OK",IF(Q49<-500,"🔴 Faltante",IF(Q49>500,"🟢 Sobrante","")))
A50: TOTAL | B50: 14997793 | C50: 6109974.6 | D50: 210794.12 | E50: 846153.57 | F50: 21743127 | L50: 2 | M50: =M39 | N50: =N39 | O50: =SUMIFS('Ventas Diarias'!$C:$C,'Ventas Diarias'!$A:$A,">="&M50,'Ventas Diarias'!$A:$A,"<="&N50,'Ventas Diarias'!$B:$B,"La Cata DF") | P50: =SUMIFS('Ventas Diarias'!$N:$N,'Ventas Diarias'!$A:$A,">="&M50,'Ventas Diarias'!$A:$A,"<="&N50+2,'Ventas Diarias'!$B:$B,"La Cata DF") | Q50: =P50-O50 | R50: =IFERROR(Q50/O50,0) | S50: =IF(ABS(Q50)<=500,"✅ OK",IF(Q50<-500,"🔴 Faltante",IF(Q50>500,"🟢 Sobrante","")))
L51: 3 | M51: =M40 | N51: =N40 | O51: =SUMIFS('Ventas Diarias'!$C:$C,'Ventas Diarias'!$A:$A,">="&M51,'Ventas Diarias'!$A:$A,"<="&N51,'Ventas Diarias'!$B:$B,"La Cata DF") | P51: =SUMIFS('Ventas Diarias'!$N:$N,'Ventas Diarias'!$A:$A,">="&M51,'Ventas Diarias'!$A:$A,"<="&N51+2,'Ventas Diarias'!$B:$B,"La Cata DF") | Q51: =P51-O51 | R51: =IFERROR(Q51/O51,0) | S51: =IF(ABS(Q51)<=500,"✅ OK",IF(Q51<-500,"🔴 Faltante",IF(Q51>500,"🟢 Sobrante","")))
A52: % Distribución | B52: % Efectivo | C52: % Tarjeta | D52: Fee Perdido | E52: % Transfer | L52: 4 | M52: =M41 | N52: =N41 | O52: =SUMIFS('Ventas Diarias'!$C:$C,'Ventas Diarias'!$A:$A,">="&M52,'Ventas Diarias'!$A:$A,"<="&N52,'Ventas Diarias'!$B:$B,"La Cata DF") | P52: =SUMIFS('Ventas Diarias'!$N:$N,'Ventas Diarias'!$A:$A,">="&M52,'Ventas Diarias'!$A:$A,"<="&N52+2,'Ventas Diarias'!$B:$B,"La Cata DF") | Q52: =P52-O52 | R52: =IFERROR(Q52/O52,0) | S52: =IF(ABS(Q52)<=500,"✅ OK",IF(Q52<-500,"🔴 Faltante",IF(Q52>500,"🟢 Sobrante","")))
A53: La Cata LMF | B53: 0.69167607 | C53: 0.26665271 | D53: 185576.6 | E53: 0.04167122 | L53: 5 | M53: =M42 | N53: =N42 | O53: =SUMIFS('Ventas Diarias'!$C:$C,'Ventas Diarias'!$A:$A,">="&M53,'Ventas Diarias'!$A:$A,"<="&N53,'Ventas Diarias'!$B:$B,"La Cata DF") | P53: =SUMIFS('Ventas Diarias'!$N:$N,'Ventas Diarias'!$A:$A,">="&M53,'Ventas Diarias'!$A:$A,"<="&N53+2,'Ventas Diarias'!$B:$B,"La Cata DF") | Q53: =P53-O53 | R53: =IFERROR(Q53/O53,0) | S53: =IF(ABS(Q53)<=500,"✅ OK",IF(Q53<-500,"🔴 Faltante",IF(Q53>500,"🟢 Sobrante","")))
A54: La Cata DF | B54: 0.67340779 | C54: 0.31135165 | D54: 25217.52 | E54: 0.015240556 | L54: 6 | M54: =M43 | N54: =N43 | O54: =SUMIFS('Ventas Diarias'!$C:$C,'Ventas Diarias'!$A:$A,">="&M54,'Ventas Diarias'!$A:$A,"<="&N54,'Ventas Diarias'!$B:$B,"La Cata DF") | P54: =SUMIFS('Ventas Diarias'!$N:$N,'Ventas Diarias'!$A:$A,">="&M54,'Ventas Diarias'!$A:$A,"<="&N54+2,'Ventas Diarias'!$B:$B,"La Cata DF") | Q54: =P54-O54 | R54: =IFERROR(Q54/O54,0) | S54: =IF(ABS(Q54)<=500,"✅ OK",IF(Q54<-500,"🔴 Faltante",IF(Q54>500,"🟢 Sobrante","")))
A55: La Cata SJM | B55: 0 | C55: 0 | D55: 0 | E55: 0 | L55: 7 | M55: =M44 | N55: =N44 | O55: =SUMIFS('Ventas Diarias'!$C:$C,'Ventas Diarias'!$A:$A,">="&M55,'Ventas Diarias'!$A:$A,"<="&N55,'Ventas Diarias'!$B:$B,"La Cata DF") | P55: =SUMIFS('Ventas Diarias'!$N:$N,'Ventas Diarias'!$A:$A,">="&M55,'Ventas Diarias'!$A:$A,"<="&N55+2,'Ventas Diarias'!$B:$B,"La Cata DF") | Q55: =P55-O55 | R55: =IFERROR(Q55/O55,0) | S55: =IF(ABS(Q55)<=500,"✅ OK",IF(Q55<-500,"🔴 Faltante",IF(Q55>500,"🟢 Sobrante","")))
L56: 8 | M56: =M45 | N56: =N45 | O56: =SUMIFS('Ventas Diarias'!$C:$C,'Ventas Diarias'!$A:$A,">="&M56,'Ventas Diarias'!$A:$A,"<="&N56,'Ventas Diarias'!$B:$B,"La Cata DF") | P56: =SUMIFS('Ventas Diarias'!$N:$N,'Ventas Diarias'!$A:$A,">="&M56,'Ventas Diarias'!$A:$A,"<="&N56+2,'Ventas Diarias'!$B:$B,"La Cata DF") | Q56: =P56-O56 | R56: =IFERROR(Q56/O56,0) | S56: =IF(ABS(Q56)<=500,"✅ OK",IF(Q56<-500,"🔴 Faltante",IF(Q56>500,"🟢 Sobrante","")))
A58: 📌 NOTA: Los datos de La Cata SJM comenzarán a partir de Junio 2026. La semana actual mostrará 0 si no hay datos ingresados para esas fechas. | L58: 📊 RESUMEN ÚLTIMAS 8 SEMANAS
L59: Tienda | M59: Total Efectivo | N59: Total Depósitos | O59: Diferencia Neta | P59: % Variación | Q59: Estado
A60: 💰 RESUMEN FINANCIERO MENSUAL | L60: La Cata LMF | M60: =SUM(O38:O45) | N60: =SUM(P38:P45) | O60: =N60-M60 | P60: =IFERROR(O60/M60,0) | Q60: =IF(ABS(O60)<=4000,"✅ OK",IF(O60<-4000,"🔴 Faltante","🟢 Sobrante"))
A61: Mes | B61: Ubicación | C61: Ventas | D61: Gastos | E61: Utilidad Neta | F61: Margen % | G61: CXP Pagadas | H61: Cash Neto | L61: La Cata DF | M61: =SUM(O49:O56) | N61: =SUM(P49:P56) | O61: =N61-M61 | P61: =IFERROR(O61/M61,0) | Q61: =IF(ABS(O61)<=4000,"✅ OK",IF(O61<-4000,"🔴 Faltante","🟢 Sobrante"))
A62: Enero 2026 | B62: La Cata LMF | C62: =IFERROR(SUMIFS('Ventas Diarias'!$M:$M,'Ventas Diarias'!$B:$B,B62,'Ventas Diarias'!$A:$A,">="&DATE(2026,1,1),'Ventas Diarias'!$A:$A,"<"&EOMONTH(DATE(2026,1,1),0)+1)/1.18,0) | D62: =IFERROR(SUMIFS(Gastos!$E:$E,Gastos!$B:$B,B62,Gastos!$A:$A,">="&DATE(2026,1,1),Gastos!$A:$A,"<"&EOMONTH(DATE(2026,1,1),0)+1),0) | E62: =IFERROR(SUMIFS('Ventas Diarias'!$C:$C,'Ventas Diarias'!$B:$B,B62,'Ventas Diarias'!$A:$A,">="&DATE(2026,1,1),'Ventas Diarias'!$A:$A,"<"&EOMONTH(DATE(2026,1,1),0)+1)+SUMIFS('Ventas Diarias'!$F:$F,'Ventas Diarias'!$B:$B,B62,'Ventas Diarias'!$A:$A,">="&DATE(2026,1,1),'Ventas Diarias'!$A:$A,"<"&EOMONTH(DATE(2026,1,1),0)+1)+SUMIFS('Ventas Diarias'!$G:$G,'Ventas Diarias'!$B:$B,B62,'Ventas Diarias'!$A:$A,">="&DATE(2026,1,1),'Ventas Diarias'!$A:$A,"<"&EOMONTH(DATE(2026,1,1),0)+1)-SUMIFS('Ventas Diarias'!$I:$I,'Ventas Diarias'!$B:$B,B62,'Ventas Diarias'!$A:$A,">="&DATE(2026,1,1),'Ventas Diarias'!$A:$A,"<"&EOMONTH(DATE(2026,1,1),0)+1)-D62,0) | F62: =IFERROR(E62/C62,"") | G62: =IFERROR(SUMIFS(CXP!$M:$M,CXP!$N:$N,"Sí",CXP!$B:$B,B62,CXP!$J:$J,">="&DATE(2026,1,1),CXP!$J:$J,"<"&EOMONTH(DATE(2026,1,1),0)+1),0) | H62: =IF(E62=0,"",E62-G62) | L62: TOTAL | M62: =M60+M61 | N62: =N60+N61 | O62: =O60+O61 | P62: =IFERROR(O62/M62,0) | Q62: =IF(ABS(O62)<=8000,"✅ OK",IF(O62<-8000,"🔴 Faltante","🟢 Sobrante"))
A63: Enero 2026 | B63: La Cata DF | C63: =IFERROR(SUMIFS('Ventas Diarias'!$M:$M,'Ventas Diarias'!$B:$B,B63,'Ventas Diarias'!$A:$A,">="&DATE(2026,1,1),'Ventas Diarias'!$A:$A,"<"&EOMONTH(DATE(2026,1,1),0)+1)/1.18,0) | D63: =IFERROR(SUMIFS(Gastos!$E:$E,Gastos!$B:$B,B63,Gastos!$A:$A,">="&DATE(2026,1,1),Gastos!$A:$A,"<"&EOMONTH(DATE(2026,1,1),0)+1),0) | E63: =IFERROR(SUMIFS('Ventas Diarias'!$C:$C,'Ventas Diarias'!$B:$B,B63,'Ventas Diarias'!$A:$A,">="&DATE(2026,1,1),'Ventas Diarias'!$A:$A,"<"&EOMONTH(DATE(2026,1,1),0)+1)+SUMIFS('Ventas Diarias'!$F:$F,'Ventas Diarias'!$B:$B,B63,'Ventas Diarias'!$A:$A,">="&DATE(2026,1,1),'Ventas Diarias'!$A:$A,"<"&EOMONTH(DATE(2026,1,1),0)+1)+SUMIFS('Ventas Diarias'!$G:$G,'Ventas Diarias'!$B:$B,B63,'Ventas Diarias'!$A:$A,">="&DATE(2026,1,1),'Ventas Diarias'!$A:$A,"<"&EOMONTH(DATE(2026,1,1),0)+1)-SUMIFS('Ventas Diarias'!$I:$I,'Ventas Diarias'!$B:$B,B63,'Ventas Diarias'!$A:$A,">="&DATE(2026,1,1),'Ventas Diarias'!$A:$A,"<"&EOMONTH(DATE(2026,1,1),0)+1)-D63,0) | F63: =IFERROR(E63/C63,"") | G63: =IFERROR(SUMIFS(CXP!$M:$M,CXP!$N:$N,"Sí",CXP!$B:$B,B63,CXP!$J:$J,">="&DATE(2026,1,1),CXP!$J:$J,"<"&EOMONTH(DATE(2026,1,1),0)+1),0) | H63: =IF(E63=0,"",E63-G63)
A64: Enero 2026 | B64: La Cata SJM | C64: =IFERROR(SUMIFS('Ventas Diarias'!$M:$M,'Ventas Diarias'!$B:$B,B64,'Ventas Diarias'!$A:$A,">="&DATE(2026,1,1),'Ventas Diarias'!$A:$A,"<"&EOMONTH(DATE(2026,1,1),0)+1)/1.18,0) | D64: =IFERROR(SUMIFS(Gastos!$E:$E,Gastos!$B:$B,B64,Gastos!$A:$A,">="&DATE(2026,1,1),Gastos!$A:$A,"<"&EOMONTH(DATE(2026,1,1),0)+1),0) | E64: =IFERROR(SUMIFS('Ventas Diarias'!$C:$C,'Ventas Diarias'!$B:$B,B64,'Ventas Diarias'!$A:$A,">="&DATE(2026,1,1),'Ventas Diarias'!$A:$A,"<"&EOMONTH(DATE(2026,1,1),0)+1)+SUMIFS('Ventas Diarias'!$F:$F,'Ventas Diarias'!$B:$B,B64,'Ventas Diarias'!$A:$A,">="&DATE(2026,1,1),'Ventas Diarias'!$A:$A,"<"&EOMONTH(DATE(2026,1,1),0)+1)+SUMIFS('Ventas Diarias'!$G:$G,'Ventas Diarias'!$B:$B,B64,'Ventas Diarias'!$A:$A,">="&DATE(2026,1,1),'Ventas Diarias'!$A:$A,"<"&EOMONTH(DATE(2026,1,1),0)+1)-SUMIFS('Ventas Diarias'!$I:$I,'Ventas Diarias'!$B:$B,B64,'Ventas Diarias'!$A:$A,">="&DATE(2026,1,1),'Ventas Diarias'!$A:$A,"<"&EOMONTH(DATE(2026,1,1),0)+1)-D64,0) | F64: =IFERROR(E64/C64,"") | G64: =IFERROR(SUMIFS(CXP!$M:$M,CXP!$N:$N,"Sí",CXP!$B:$B,B64,CXP!$J:$J,">="&DATE(2026,1,1),CXP!$J:$J,"<"&EOMONTH(DATE(2026,1,1),0)+1),0) | H64: =IF(E64=0,"",E64-G64)
A65: Febrero 2026 | B65: La Cata LMF | C65: =IFERROR(SUMIFS('Ventas Diarias'!$M:$M,'Ventas Diarias'!$B:$B,B65,'Ventas Diarias'!$A:$A,">="&DATE(2026,2,1),'Ventas Diarias'!$A:$A,"<"&EOMONTH(DATE(2026,2,1),0)+1)/1.18,0) | D65: =IFERROR(SUMIFS(Gastos!$E:$E,Gastos!$B:$B,B65,Gastos!$A:$A,">="&DATE(2026,2,1),Gastos!$A:$A,"<"&EOMONTH(DATE(2026,2,1),0)+1),0) | E65: =IFERROR(SUMIFS('Ventas Diarias'!$C:$C,'Ventas Diarias'!$B:$B,B65,'Ventas Diarias'!$A:$A,">="&DATE(2026,2,1),'Ventas Diarias'!$A:$A,"<"&EOMONTH(DATE(2026,2,1),0)+1)+SUMIFS('Ventas Diarias'!$F:$F,'Ventas Diarias'!$B:$B,B65,'Ventas Diarias'!$A:$A,">="&DATE(2026,2,1),'Ventas Diarias'!$A:$A,"<"&EOMONTH(DATE(2026,2,1),0)+1)+SUMIFS('Ventas Diarias'!$G:$G,'Ventas Diarias'!$B:$B,B65,'Ventas Diarias'!$A:$A,">="&DATE(2026,2,1),'Ventas Diarias'!$A:$A,"<"&EOMONTH(DATE(2026,2,1),0)+1)-SUMIFS('Ventas Diarias'!$I:$I,'Ventas Diarias'!$B:$B,B65,'Ventas Diarias'!$A:$A,">="&DATE(2026,2,1),'Ventas Diarias'!$A:$A,"<"&EOMONTH(DATE(2026,2,1),0)+1)-D65,0) | F65: =IFERROR(E65/C65,"") | G65: =IFERROR(SUMIFS(CXP!$M:$M,CXP!$N:$N,"Sí",CXP!$B:$B,B65,CXP!$J:$J,">="&DATE(2026,2,1),CXP!$J:$J,"<"&EOMONTH(DATE(2026,2,1),0)+1),0) | H65: =IF(E65=0,"",E65-G65)
A66: Febrero 2026 | B66: La Cata DF | C66: =IFERROR(SUMIFS('Ventas Diarias'!$M:$M,'Ventas Diarias'!$B:$B,B66,'Ventas Diarias'!$A:$A,">="&DATE(2026,2,1),'Ventas Diarias'!$A:$A,"<"&EOMONTH(DATE(2026,2,1),0)+1)/1.18,0) | D66: =IFERROR(SUMIFS(Gastos!$E:$E,Gastos!$B:$B,B66,Gastos!$A:$A,">="&DATE(2026,2,1),Gastos!$A:$A,"<"&EOMONTH(DATE(2026,2,1),0)+1),0) | E66: =IFERROR(SUMIFS('Ventas Diarias'!$C:$C,'Ventas Diarias'!$B:$B,B66,'Ventas Diarias'!$A:$A,">="&DATE(2026,2,1),'Ventas Diarias'!$A:$A,"<"&EOMONTH(DATE(2026,2,1),0)+1)+SUMIFS('Ventas Diarias'!$F:$F,'Ventas Diarias'!$B:$B,B66,'Ventas Diarias'!$A:$A,">="&DATE(2026,2,1),'Ventas Diarias'!$A:$A,"<"&EOMONTH(DATE(2026,2,1),0)+1)+SUMIFS('Ventas Diarias'!$G:$G,'Ventas Diarias'!$B:$B,B66,'Ventas Diarias'!$A:$A,">="&DATE(2026,2,1),'Ventas Diarias'!$A:$A,"<"&EOMONTH(DATE(2026,2,1),0)+1)-SUMIFS('Ventas Diarias'!$I:$I,'Ventas Diarias'!$B:$B,B66,'Ventas Diarias'!$A:$A,">="&DATE(2026,2,1),'Ventas Diarias'!$A:$A,"<"&EOMONTH(DATE(2026,2,1),0)+1)-D66,0) | F66: =IFERROR(E66/C66,"") | G66: =IFERROR(SUMIFS(CXP!$M:$M,CXP!$N:$N,"Sí",CXP!$B:$B,B66,CXP!$J:$J,">="&DATE(2026,2,1),CXP!$J:$J,"<"&EOMONTH(DATE(2026,2,1),0)+1),0) | H66: =IF(E66=0,"",E66-G66)
A67: Febrero 2026 | B67: La Cata SJM | C67: =IFERROR(SUMIFS('Ventas Diarias'!$M:$M,'Ventas Diarias'!$B:$B,B67,'Ventas Diarias'!$A:$A,">="&DATE(2026,2,1),'Ventas Diarias'!$A:$A,"<"&EOMONTH(DATE(2026,2,1),0)+1)/1.18,0) | D67: =IFERROR(SUMIFS(Gastos!$E:$E,Gastos!$B:$B,B67,Gastos!$A:$A,">="&DATE(2026,2,1),Gastos!$A:$A,"<"&EOMONTH(DATE(2026,2,1),0)+1),0) | E67: =IFERROR(SUMIFS('Ventas Diarias'!$C:$C,'Ventas Diarias'!$B:$B,B67,'Ventas Diarias'!$A:$A,">="&DATE(2026,2,1),'Ventas Diarias'!$A:$A,"<"&EOMONTH(DATE(2026,2,1),0)+1)+SUMIFS('Ventas Diarias'!$F:$F,'Ventas Diarias'!$B:$B,B67,'Ventas Diarias'!$A:$A,">="&DATE(2026,2,1),'Ventas Diarias'!$A:$A,"<"&EOMONTH(DATE(2026,2,1),0)+1)+SUMIFS('Ventas Diarias'!$G:$G,'Ventas Diarias'!$B:$B,B67,'Ventas Diarias'!$A:$A,">="&DATE(2026,2,1),'Ventas Diarias'!$A:$A,"<"&EOMONTH(DATE(2026,2,1),0)+1)-SUMIFS('Ventas Diarias'!$I:$I,'Ventas Diarias'!$B:$B,B67,'Ventas Diarias'!$A:$A,">="&DATE(2026,2,1),'Ventas Diarias'!$A:$A,"<"&EOMONTH(DATE(2026,2,1),0)+1)-D67,0) | F67: =IFERROR(E67/C67,"") | G67: =IFERROR(SUMIFS(CXP!$M:$M,CXP!$N:$N,"Sí",CXP!$B:$B,B67,CXP!$J:$J,">="&DATE(2026,2,1),CXP!$J:$J,"<"&EOMONTH(DATE(2026,2,1),0)+1),0) | H67: =IF(E67=0,"",E67-G67)
A68: Marzo 2026 | B68: La Cata LMF | C68: =IFERROR(SUMIFS('Ventas Diarias'!$M:$M,'Ventas Diarias'!$B:$B,B68,'Ventas Diarias'!$A:$A,">="&DATE(2026,3,1),'Ventas Diarias'!$A:$A,"<"&EOMONTH(DATE(2026,3,1),0)+1)/1.18,0) | D68: =IFERROR(SUMIFS(Gastos!$E:$E,Gastos!$B:$B,B68,Gastos!$A:$A,">="&DATE(2026,3,1),Gastos!$A:$A,"<"&EOMONTH(DATE(2026,3,1),0)+1),0) | E68: =IFERROR(SUMIFS('Ventas Diarias'!$C:$C,'Ventas Diarias'!$B:$B,B68,'Ventas Diarias'!$A:$A,">="&DATE(2026,3,1),'Ventas Diarias'!$A:$A,"<"&EOMONTH(DATE(2026,3,1),0)+1)+SUMIFS('Ventas Diarias'!$F:$F,'Ventas Diarias'!$B:$B,B68,'Ventas Diarias'!$A:$A,">="&DATE(2026,3,1),'Ventas Diarias'!$A:$A,"<"&EOMONTH(DATE(2026,3,1),0)+1)+SUMIFS('Ventas Diarias'!$G:$G,'Ventas Diarias'!$B:$B,B68,'Ventas Diarias'!$A:$A,">="&DATE(2026,3,1),'Ventas Diarias'!$A:$A,"<"&EOMONTH(DATE(2026,3,1),0)+1)-SUMIFS('Ventas Diarias'!$I:$I,'Ventas Diarias'!$B:$B,B68,'Ventas Diarias'!$A:$A,">="&DATE(2026,3,1),'Ventas Diarias'!$A:$A,"<"&EOMONTH(DATE(2026,3,1),0)+1)-D68,0) | F68: =IFERROR(E68/C68,"") | G68: =IFERROR(SUMIFS(CXP!$M:$M,CXP!$N:$N,"Sí",CXP!$B:$B,B68,CXP!$J:$J,">="&DATE(2026,3,1),CXP!$J:$J,"<"&EOMONTH(DATE(2026,3,1),0)+1),0) | H68: =IF(E68=0,"",E68-G68)
A69: Marzo 2026 | B69: La Cata DF | C69: =IFERROR(SUMIFS('Ventas Diarias'!$M:$M,'Ventas Diarias'!$B:$B,B69,'Ventas Diarias'!$A:$A,">="&DATE(2026,3,1),'Ventas Diarias'!$A:$A,"<"&EOMONTH(DATE(2026,3,1),0)+1)/1.18,0) | D69: =IFERROR(SUMIFS(Gastos!$E:$E,Gastos!$B:$B,B69,Gastos!$A:$A,">="&DATE(2026,3,1),Gastos!$A:$A,"<"&EOMONTH(DATE(2026,3,1),0)+1),0) | E69: =IFERROR(SUMIFS('Ventas Diarias'!$C:$C,'Ventas Diarias'!$B:$B,B69,'Ventas Diarias'!$A:$A,">="&DATE(2026,3,1),'Ventas Diarias'!$A:$A,"<"&EOMONTH(DATE(2026,3,1),0)+1)+SUMIFS('Ventas Diarias'!$F:$F,'Ventas Diarias'!$B:$B,B69,'Ventas Diarias'!$A:$A,">="&DATE(2026,3,1),'Ventas Diarias'!$A:$A,"<"&EOMONTH(DATE(2026,3,1),0)+1)+SUMIFS('Ventas Diarias'!$G:$G,'Ventas Diarias'!$B:$B,B69,'Ventas Diarias'!$A:$A,">="&DATE(2026,3,1),'Ventas Diarias'!$A:$A,"<"&EOMONTH(DATE(2026,3,1),0)+1)-SUMIFS('Ventas Diarias'!$I:$I,'Ventas Diarias'!$B:$B,B69,'Ventas Diarias'!$A:$A,">="&DATE(2026,3,1),'Ventas Diarias'!$A:$A,"<"&EOMONTH(DATE(2026,3,1),0)+1)-D69,0) | F69: =IFERROR(E69/C69,"") | G69: =IFERROR(SUMIFS(CXP!$M:$M,CXP!$N:$N,"Sí",CXP!$B:$B,B69,CXP!$J:$J,">="&DATE(2026,3,1),CXP!$J:$J,"<"&EOMONTH(DATE(2026,3,1),0)+1),0) | H69: =IF(E69=0,"",E69-G69)
A70: Marzo 2026 | B70: La Cata SJM | C70: =IFERROR(SUMIFS('Ventas Diarias'!$M:$M,'Ventas Diarias'!$B:$B,B70,'Ventas Diarias'!$A:$A,">="&DATE(2026,3,1),'Ventas Diarias'!$A:$A,"<"&EOMONTH(DATE(2026,3,1),0)+1)/1.18,0) | D70: =IFERROR(SUMIFS(Gastos!$E:$E,Gastos!$B:$B,B70,Gastos!$A:$A,">="&DATE(2026,3,1),Gastos!$A:$A,"<"&EOMONTH(DATE(2026,3,1),0)+1),0) | E70: =IFERROR(SUMIFS('Ventas Diarias'!$C:$C,'Ventas Diarias'!$B:$B,B70,'Ventas Diarias'!$A:$A,">="&DATE(2026,3,1),'Ventas Diarias'!$A:$A,"<"&EOMONTH(DATE(2026,3,1),0)+1)+SUMIFS('Ventas Diarias'!$F:$F,'Ventas Diarias'!$B:$B,B70,'Ventas Diarias'!$A:$A,">="&DATE(2026,3,1),'Ventas Diarias'!$A:$A,"<"&EOMONTH(DATE(2026,3,1),0)+1)+SUMIFS('Ventas Diarias'!$G:$G,'Ventas Diarias'!$B:$B,B70,'Ventas Diarias'!$A:$A,">="&DATE(2026,3,1),'Ventas Diarias'!$A:$A,"<"&EOMONTH(DATE(2026,3,1),0)+1)-SUMIFS('Ventas Diarias'!$I:$I,'Ventas Diarias'!$B:$B,B70,'Ventas Diarias'!$A:$A,">="&DATE(2026,3,1),'Ventas Diarias'!$A:$A,"<"&EOMONTH(DATE(2026,3,1),0)+1)-D70,0) | F70: =IFERROR(E70/C70,"") | G70: =IFERROR(SUMIFS(CXP!$M:$M,CXP!$N:$N,"Sí",CXP!$B:$B,B70,CXP!$J:$J,">="&DATE(2026,3,1),CXP!$J:$J,"<"&EOMONTH(DATE(2026,3,1),0)+1),0) | H70: =IF(E70=0,"",E70-G70)
A71: Abril 2026 | B71: La Cata LMF | C71: =IFERROR(SUMIFS('Ventas Diarias'!$M:$M,'Ventas Diarias'!$B:$B,B71,'Ventas Diarias'!$A:$A,">="&DATE(2026,4,1),'Ventas Diarias'!$A:$A,"<"&EOMONTH(DATE(2026,4,1),0)+1)/1.18,0) | D71: =IFERROR(SUMIFS(Gastos!$E:$E,Gastos!$B:$B,B71,Gastos!$A:$A,">="&DATE(2026,4,1),Gastos!$A:$A,"<"&EOMONTH(DATE(2026,4,1),0)+1),0) | E71: =IFERROR(SUMIFS('Ventas Diarias'!$C:$C,'Ventas Diarias'!$B:$B,B71,'Ventas Diarias'!$A:$A,">="&DATE(2026,4,1),'Ventas Diarias'!$A:$A,"<"&EOMONTH(DATE(2026,4,1),0)+1)+SUMIFS('Ventas Diarias'!$F:$F,'Ventas Diarias'!$B:$B,B71,'Ventas Diarias'!$A:$A,">="&DATE(2026,4,1),'Ventas Diarias'!$A:$A,"<"&EOMONTH(DATE(2026,4,1),0)+1)+SUMIFS('Ventas Diarias'!$G:$G,'Ventas Diarias'!$B:$B,B71,'Ventas Diarias'!$A:$A,">="&DATE(2026,4,1),'Ventas Diarias'!$A:$A,"<"&EOMONTH(DATE(2026,4,1),0)+1)-SUMIFS('Ventas Diarias'!$I:$I,'Ventas Diarias'!$B:$B,B71,'Ventas Diarias'!$A:$A,">="&DATE(2026,4,1),'Ventas Diarias'!$A:$A,"<"&EOMONTH(DATE(2026,4,1),0)+1)-D71,0) | F71: =IFERROR(E71/C71,"") | G71: =IFERROR(SUMIFS(CXP!$M:$M,CXP!$N:$N,"Sí",CXP!$B:$B,B71,CXP!$J:$J,">="&DATE(2026,4,1),CXP!$J:$J,"<"&EOMONTH(DATE(2026,4,1),0)+1),0) | H71: =IF(E71=0,"",E71-G71)
A72: Abril 2026 | B72: La Cata DF | C72: =IFERROR(SUMIFS('Ventas Diarias'!$M:$M,'Ventas Diarias'!$B:$B,B72,'Ventas Diarias'!$A:$A,">="&DATE(2026,4,1),'Ventas Diarias'!$A:$A,"<"&EOMONTH(DATE(2026,4,1),0)+1)/1.18,0) | D72: =IFERROR(SUMIFS(Gastos!$E:$E,Gastos!$B:$B,B72,Gastos!$A:$A,">="&DATE(2026,4,1),Gastos!$A:$A,"<"&EOMONTH(DATE(2026,4,1),0)+1),0) | E72: =IFERROR(SUMIFS('Ventas Diarias'!$C:$C,'Ventas Diarias'!$B:$B,B72,'Ventas Diarias'!$A:$A,">="&DATE(2026,4,1),'Ventas Diarias'!$A:$A,"<"&EOMONTH(DATE(2026,4,1),0)+1)+SUMIFS('Ventas Diarias'!$F:$F,'Ventas Diarias'!$B:$B,B72,'Ventas Diarias'!$A:$A,">="&DATE(2026,4,1),'Ventas Diarias'!$A:$A,"<"&EOMONTH(DATE(2026,4,1),0)+1)+SUMIFS('Ventas Diarias'!$G:$G,'Ventas Diarias'!$B:$B,B72,'Ventas Diarias'!$A:$A,">="&DATE(2026,4,1),'Ventas Diarias'!$A:$A,"<"&EOMONTH(DATE(2026,4,1),0)+1)-SUMIFS('Ventas Diarias'!$I:$I,'Ventas Diarias'!$B:$B,B72,'Ventas Diarias'!$A:$A,">="&DATE(2026,4,1),'Ventas Diarias'!$A:$A,"<"&EOMONTH(DATE(2026,4,1),0)+1)-D72,0) | F72: =IFERROR(E72/C72,"") | G72: =IFERROR(SUMIFS(CXP!$M:$M,CXP!$N:$N,"Sí",CXP!$B:$B,B72,CXP!$J:$J,">="&DATE(2026,4,1),CXP!$J:$J,"<"&EOMONTH(DATE(2026,4,1),0)+1),0) | H72: =IF(E72=0,"",E72-G72)
A73: Abril 2026 | B73: La Cata SJM | C73: =IFERROR(SUMIFS('Ventas Diarias'!$M:$M,'Ventas Diarias'!$B:$B,B73,'Ventas Diarias'!$A:$A,">="&DATE(2026,4,1),'Ventas Diarias'!$A:$A,"<"&EOMONTH(DATE(2026,4,1),0)+1)/1.18,0) | D73: =IFERROR(SUMIFS(Gastos!$E:$E,Gastos!$B:$B,B73,Gastos!$A:$A,">="&DATE(2026,4,1),Gastos!$A:$A,"<"&EOMONTH(DATE(2026,4,1),0)+1),0) | E73: =IFERROR(SUMIFS('Ventas Diarias'!$C:$C,'Ventas Diarias'!$B:$B,B73,'Ventas Diarias'!$A:$A,">="&DATE(2026,4,1),'Ventas Diarias'!$A:$A,"<"&EOMONTH(DATE(2026,4,1),0)+1)+SUMIFS('Ventas Diarias'!$F:$F,'Ventas Diarias'!$B:$B,B73,'Ventas Diarias'!$A:$A,">="&DATE(2026,4,1),'Ventas Diarias'!$A:$A,"<"&EOMONTH(DATE(2026,4,1),0)+1)+SUMIFS('Ventas Diarias'!$G:$G,'Ventas Diarias'!$B:$B,B73,'Ventas Diarias'!$A:$A,">="&DATE(2026,4,1),'Ventas Diarias'!$A:$A,"<"&EOMONTH(DATE(2026,4,1),0)+1)-SUMIFS('Ventas Diarias'!$I:$I,'Ventas Diarias'!$B:$B,B73,'Ventas Diarias'!$A:$A,">="&DATE(2026,4,1),'Ventas Diarias'!$A:$A,"<"&EOMONTH(DATE(2026,4,1),0)+1)-D73,0) | F73: =IFERROR(E73/C73,"") | G73: =IFERROR(SUMIFS(CXP!$M:$M,CXP!$N:$N,"Sí",CXP!$B:$B,B73,CXP!$J:$J,">="&DATE(2026,4,1),CXP!$J:$J,"<"&EOMONTH(DATE(2026,4,1),0)+1),0) | H73: =IF(E73=0,"",E73-G73)
A74: Mayo 2026 | B74: La Cata LMF | C74: =IFERROR(SUMIFS('Ventas Diarias'!$M:$M,'Ventas Diarias'!$B:$B,B74,'Ventas Diarias'!$A:$A,">="&DATE(2026,5,1),'Ventas Diarias'!$A:$A,"<"&EOMONTH(DATE(2026,5,1),0)+1)/1.18,0) | D74: =IFERROR(SUMIFS(Gastos!$E:$E,Gastos!$B:$B,B74,Gastos!$A:$A,">="&DATE(2026,5,1),Gastos!$A:$A,"<"&EOMONTH(DATE(2026,5,1),0)+1),0) | E74: =IFERROR(SUMIFS('Ventas Diarias'!$C:$C,'Ventas Diarias'!$B:$B,B74,'Ventas Diarias'!$A:$A,">="&DATE(2026,5,1),'Ventas Diarias'!$A:$A,"<"&EOMONTH(DATE(2026,5,1),0)+1)+SUMIFS('Ventas Diarias'!$F:$F,'Ventas Diarias'!$B:$B,B74,'Ventas Diarias'!$A:$A,">="&DATE(2026,5,1),'Ventas Diarias'!$A:$A,"<"&EOMONTH(DATE(2026,5,1),0)+1)+SUMIFS('Ventas Diarias'!$G:$G,'Ventas Diarias'!$B:$B,B74,'Ventas Diarias'!$A:$A,">="&DATE(2026,5,1),'Ventas Diarias'!$A:$A,"<"&EOMONTH(DATE(2026,5,1),0)+1)-SUMIFS('Ventas Diarias'!$I:$I,'Ventas Diarias'!$B:$B,B74,'Ventas Diarias'!$A:$A,">="&DATE(2026,5,1),'Ventas Diarias'!$A:$A,"<"&EOMONTH(DATE(2026,5,1),0)+1)-D74,0) | F74: =IFERROR(E74/C74,"") | G74: =IFERROR(SUMIFS(CXP!$M:$M,CXP!$N:$N,"Sí",CXP!$B:$B,B74,CXP!$J:$J,">="&DATE(2026,5,1),CXP!$J:$J,"<"&EOMONTH(DATE(2026,5,1),0)+1),0) | H74: =IF(E74=0,"",E74-G74)
A75: Mayo 2026 | B75: La Cata DF | C75: =IFERROR(SUMIFS('Ventas Diarias'!$M:$M,'Ventas Diarias'!$B:$B,B75,'Ventas Diarias'!$A:$A,">="&DATE(2026,5,1),'Ventas Diarias'!$A:$A,"<"&EOMONTH(DATE(2026,5,1),0)+1)/1.18,0) | D75: =IFERROR(SUMIFS(Gastos!$E:$E,Gastos!$B:$B,B75,Gastos!$A:$A,">="&DATE(2026,5,1),Gastos!$A:$A,"<"&EOMONTH(DATE(2026,5,1),0)+1),0) | E75: =IFERROR(SUMIFS('Ventas Diarias'!$C:$C,'Ventas Diarias'!$B:$B,B75,'Ventas Diarias'!$A:$A,">="&DATE(2026,5,1),'Ventas Diarias'!$A:$A,"<"&EOMONTH(DATE(2026,5,1),0)+1)+SUMIFS('Ventas Diarias'!$F:$F,'Ventas Diarias'!$B:$B,B75,'Ventas Diarias'!$A:$A,">="&DATE(2026,5,1),'Ventas Diarias'!$A:$A,"<"&EOMONTH(DATE(2026,5,1),0)+1)+SUMIFS('Ventas Diarias'!$G:$G,'Ventas Diarias'!$B:$B,B75,'Ventas Diarias'!$A:$A,">="&DATE(2026,5,1),'Ventas Diarias'!$A:$A,"<"&EOMONTH(DATE(2026,5,1),0)+1)-SUMIFS('Ventas Diarias'!$I:$I,'Ventas Diarias'!$B:$B,B75,'Ventas Diarias'!$A:$A,">="&DATE(2026,5,1),'Ventas Diarias'!$A:$A,"<"&EOMONTH(DATE(2026,5,1),0)+1)-D75,0) | F75: =IFERROR(E75/C75,"") | G75: =IFERROR(SUMIFS(CXP!$M:$M,CXP!$N:$N,"Sí",CXP!$B:$B,B75,CXP!$J:$J,">="&DATE(2026,5,1),CXP!$J:$J,"<"&EOMONTH(DATE(2026,5,1),0)+1),0) | H75: =IF(E75=0,"",E75-G75)
A76: Mayo 2026 | B76: La Cata SJM | C76: =IFERROR(SUMIFS('Ventas Diarias'!$M:$M,'Ventas Diarias'!$B:$B,B76,'Ventas Diarias'!$A:$A,">="&DATE(2026,5,1),'Ventas Diarias'!$A:$A,"<"&EOMONTH(DATE(2026,5,1),0)+1)/1.18,0) | D76: =IFERROR(SUMIFS(Gastos!$E:$E,Gastos!$B:$B,B76,Gastos!$A:$A,">="&DATE(2026,5,1),Gastos!$A:$A,"<"&EOMONTH(DATE(2026,5,1),0)+1),0) | E76: =IFERROR(SUMIFS('Ventas Diarias'!$C:$C,'Ventas Diarias'!$B:$B,B76,'Ventas Diarias'!$A:$A,">="&DATE(2026,5,1),'Ventas Diarias'!$A:$A,"<"&EOMONTH(DATE(2026,5,1),0)+1)+SUMIFS('Ventas Diarias'!$F:$F,'Ventas Diarias'!$B:$B,B76,'Ventas Diarias'!$A:$A,">="&DATE(2026,5,1),'Ventas Diarias'!$A:$A,"<"&EOMONTH(DATE(2026,5,1),0)+1)+SUMIFS('Ventas Diarias'!$G:$G,'Ventas Diarias'!$B:$B,B76,'Ventas Diarias'!$A:$A,">="&DATE(2026,5,1),'Ventas Diarias'!$A:$A,"<"&EOMONTH(DATE(2026,5,1),0)+1)-SUMIFS('Ventas Diarias'!$I:$I,'Ventas Diarias'!$B:$B,B76,'Ventas Diarias'!$A:$A,">="&DATE(2026,5,1),'Ventas Diarias'!$A:$A,"<"&EOMONTH(DATE(2026,5,1),0)+1)-D76,0) | F76: =IFERROR(E76/C76,"") | G76: =IFERROR(SUMIFS(CXP!$M:$M,CXP!$N:$N,"Sí",CXP!$B:$B,B76,CXP!$J:$J,">="&DATE(2026,5,1),CXP!$J:$J,"<"&EOMONTH(DATE(2026,5,1),0)+1),0) | H76: =IF(E76=0,"",E76-G76)
A77: Junio 2026 | B77: La Cata LMF | C77: =IFERROR(SUMIFS('Ventas Diarias'!$M:$M,'Ventas Diarias'!$B:$B,B77,'Ventas Diarias'!$A:$A,">="&DATE(2026,6,1),'Ventas Diarias'!$A:$A,"<"&EOMONTH(DATE(2026,6,1),0)+1)/1.18,0) | D77: =IFERROR(SUMIFS(Gastos!$E:$E,Gastos!$B:$B,B77,Gastos!$A:$A,">="&DATE(2026,6,1),Gastos!$A:$A,"<"&EOMONTH(DATE(2026,6,1),0)+1),0) | E77: =IFERROR(SUMIFS('Ventas Diarias'!$C:$C,'Ventas Diarias'!$B:$B,B77,'Ventas Diarias'!$A:$A,">="&DATE(2026,6,1),'Ventas Diarias'!$A:$A,"<"&EOMONTH(DATE(2026,6,1),0)+1)+SUMIFS('Ventas Diarias'!$F:$F,'Ventas Diarias'!$B:$B,B77,'Ventas Diarias'!$A:$A,">="&DATE(2026,6,1),'Ventas Diarias'!$A:$A,"<"&EOMONTH(DATE(2026,6,1),0)+1)+SUMIFS('Ventas Diarias'!$G:$G,'Ventas Diarias'!$B:$B,B77,'Ventas Diarias'!$A:$A,">="&DATE(2026,6,1),'Ventas Diarias'!$A:$A,"<"&EOMONTH(DATE(2026,6,1),0)+1)-SUMIFS('Ventas Diarias'!$I:$I,'Ventas Diarias'!$B:$B,B77,'Ventas Diarias'!$A:$A,">="&DATE(2026,6,1),'Ventas Diarias'!$A:$A,"<"&EOMONTH(DATE(2026,6,1),0)+1)-D77,0) | F77: =IFERROR(E77/C77,"") | G77: =IFERROR(SUMIFS(CXP!$M:$M,CXP!$N:$N,"Sí",CXP!$B:$B,B77,CXP!$J:$J,">="&DATE(2026,6,1),CXP!$J:$J,"<"&EOMONTH(DATE(2026,6,1),0)+1),0) | H77: =IF(E77=0,"",E77-G77)
A78: Junio 2026 | B78: La Cata DF | C78: =IFERROR(SUMIFS('Ventas Diarias'!$M:$M,'Ventas Diarias'!$B:$B,B78,'Ventas Diarias'!$A:$A,">="&DATE(2026,6,1),'Ventas Diarias'!$A:$A,"<"&EOMONTH(DATE(2026,6,1),0)+1)/1.18,0) | D78: =IFERROR(SUMIFS(Gastos!$E:$E,Gastos!$B:$B,B78,Gastos!$A:$A,">="&DATE(2026,6,1),Gastos!$A:$A,"<"&EOMONTH(DATE(2026,6,1),0)+1),0) | E78: =IFERROR(SUMIFS('Ventas Diarias'!$C:$C,'Ventas Diarias'!$B:$B,B78,'Ventas Diarias'!$A:$A,">="&DATE(2026,6,1),'Ventas Diarias'!$A:$A,"<"&EOMONTH(DATE(2026,6,1),0)+1)+SUMIFS('Ventas Diarias'!$F:$F,'Ventas Diarias'!$B:$B,B78,'Ventas Diarias'!$A:$A,">="&DATE(2026,6,1),'Ventas Diarias'!$A:$A,"<"&EOMONTH(DATE(2026,6,1),0)+1)+SUMIFS('Ventas Diarias'!$G:$G,'Ventas Diarias'!$B:$B,B78,'Ventas Diarias'!$A:$A,">="&DATE(2026,6,1),'Ventas Diarias'!$A:$A,"<"&EOMONTH(DATE(2026,6,1),0)+1)-SUMIFS('Ventas Diarias'!$I:$I,'Ventas Diarias'!$B:$B,B78,'Ventas Diarias'!$A:$A,">="&DATE(2026,6,1),'Ventas Diarias'!$A:$A,"<"&EOMONTH(DATE(2026,6,1),0)+1)-D78,0) | F78: =IFERROR(E78/C78,"") | G78: =IFERROR(SUMIFS(CXP!$M:$M,CXP!$N:$N,"Sí",CXP!$B:$B,B78,CXP!$J:$J,">="&DATE(2026,6,1),CXP!$J:$J,"<"&EOMONTH(DATE(2026,6,1),0)+1),0) | H78: =IF(E78=0,"",E78-G78)
A79: Junio 2026 | B79: La Cata SJM | C79: =IFERROR(SUMIFS('Ventas Diarias'!$M:$M,'Ventas Diarias'!$B:$B,B79,'Ventas Diarias'!$A:$A,">="&DATE(2026,6,1),'Ventas Diarias'!$A:$A,"<"&EOMONTH(DATE(2026,6,1),0)+1)/1.18,0) | D79: =IFERROR(SUMIFS(Gastos!$E:$E,Gastos!$B:$B,B79,Gastos!$A:$A,">="&DATE(2026,6,1),Gastos!$A:$A,"<"&EOMONTH(DATE(2026,6,1),0)+1),0) | E79: =IFERROR(SUMIFS('Ventas Diarias'!$C:$C,'Ventas Diarias'!$B:$B,B79,'Ventas Diarias'!$A:$A,">="&DATE(2026,6,1),'Ventas Diarias'!$A:$A,"<"&EOMONTH(DATE(2026,6,1),0)+1)+SUMIFS('Ventas Diarias'!$F:$F,'Ventas Diarias'!$B:$B,B79,'Ventas Diarias'!$A:$A,">="&DATE(2026,6,1),'Ventas Diarias'!$A:$A,"<"&EOMONTH(DATE(2026,6,1),0)+1)+SUMIFS('Ventas Diarias'!$G:$G,'Ventas Diarias'!$B:$B,B79,'Ventas Diarias'!$A:$A,">="&DATE(2026,6,1),'Ventas Diarias'!$A:$A,"<"&EOMONTH(DATE(2026,6,1),0)+1)-SUMIFS('Ventas Diarias'!$I:$I,'Ventas Diarias'!$B:$B,B79,'Ventas Diarias'!$A:$A,">="&DATE(2026,6,1),'Ventas Diarias'!$A:$A,"<"&EOMONTH(DATE(2026,6,1),0)+1)-D79,0) | F79: =IFERROR(E79/C79,"") | G79: =IFERROR(SUMIFS(CXP!$M:$M,CXP!$N:$N,"Sí",CXP!$B:$B,B79,CXP!$J:$J,">="&DATE(2026,6,1),CXP!$J:$J,"<"&EOMONTH(DATE(2026,6,1),0)+1),0) | H79: =IF(E79=0,"",E79-G79)
A80: Julio 2026 | B80: La Cata LMF | C80: =IFERROR(SUMIFS('Ventas Diarias'!$M:$M,'Ventas Diarias'!$B:$B,B80,'Ventas Diarias'!$A:$A,">="&DATE(2026,7,1),'Ventas Diarias'!$A:$A,"<"&EOMONTH(DATE(2026,7,1),0)+1)/1.18,0) | D80: =IFERROR(SUMIFS(Gastos!$E:$E,Gastos!$B:$B,B80,Gastos!$A:$A,">="&DATE(2026,7,1),Gastos!$A:$A,"<"&EOMONTH(DATE(2026,7,1),0)+1),0) | E80: =IFERROR(SUMIFS('Ventas Diarias'!$C:$C,'Ventas Diarias'!$B:$B,B80,'Ventas Diarias'!$A:$A,">="&DATE(2026,7,1),'Ventas Diarias'!$A:$A,"<"&EOMONTH(DATE(2026,7,1),0)+1)+SUMIFS('Ventas Diarias'!$F:$F,'Ventas Diarias'!$B:$B,B80,'Ventas Diarias'!$A:$A,">="&DATE(2026,7,1),'Ventas Diarias'!$A:$A,"<"&EOMONTH(DATE(2026,7,1),0)+1)+SUMIFS('Ventas Diarias'!$G:$G,'Ventas Diarias'!$B:$B,B80,'Ventas Diarias'!$A:$A,">="&DATE(2026,7,1),'Ventas Diarias'!$A:$A,"<"&EOMONTH(DATE(2026,7,1),0)+1)-SUMIFS('Ventas Diarias'!$I:$I,'Ventas Diarias'!$B:$B,B80,'Ventas Diarias'!$A:$A,">="&DATE(2026,7,1),'Ventas Diarias'!$A:$A,"<"&EOMONTH(DATE(2026,7,1),0)+1)-D80,0) | F80: =IFERROR(E80/C80,"") | G80: =IFERROR(SUMIFS(CXP!$M:$M,CXP!$N:$N,"Sí",CXP!$B:$B,B80,CXP!$J:$J,">="&DATE(2026,7,1),CXP!$J:$J,"<"&EOMONTH(DATE(2026,7,1),0)+1),0) | H80: =IF(E80=0,"",E80-G80)
A81: Julio 2026 | B81: La Cata DF | C81: =IFERROR(SUMIFS('Ventas Diarias'!$M:$M,'Ventas Diarias'!$B:$B,B81,'Ventas Diarias'!$A:$A,">="&DATE(2026,7,1),'Ventas Diarias'!$A:$A,"<"&EOMONTH(DATE(2026,7,1),0)+1)/1.18,0) | D81: =IFERROR(SUMIFS(Gastos!$E:$E,Gastos!$B:$B,B81,Gastos!$A:$A,">="&DATE(2026,7,1),Gastos!$A:$A,"<"&EOMONTH(DATE(2026,7,1),0)+1),0) | E81: =IFERROR(SUMIFS('Ventas Diarias'!$C:$C,'Ventas Diarias'!$B:$B,B81,'Ventas Diarias'!$A:$A,">="&DATE(2026,7,1),'Ventas Diarias'!$A:$A,"<"&EOMONTH(DATE(2026,7,1),0)+1)+SUMIFS('Ventas Diarias'!$F:$F,'Ventas Diarias'!$B:$B,B81,'Ventas Diarias'!$A:$A,">="&DATE(2026,7,1),'Ventas Diarias'!$A:$A,"<"&EOMONTH(DATE(2026,7,1),0)+1)+SUMIFS('Ventas Diarias'!$G:$G,'Ventas Diarias'!$B:$B,B81,'Ventas Diarias'!$A:$A,">="&DATE(2026,7,1),'Ventas Diarias'!$A:$A,"<"&EOMONTH(DATE(2026,7,1),0)+1)-SUMIFS('Ventas Diarias'!$I:$I,'Ventas Diarias'!$B:$B,B81,'Ventas Diarias'!$A:$A,">="&DATE(2026,7,1),'Ventas Diarias'!$A:$A,"<"&EOMONTH(DATE(2026,7,1),0)+1)-D81,0) | F81: =IFERROR(E81/C81,"") | G81: =IFERROR(SUMIFS(CXP!$M:$M,CXP!$N:$N,"Sí",CXP!$B:$B,B81,CXP!$J:$J,">="&DATE(2026,7,1),CXP!$J:$J,"<"&EOMONTH(DATE(2026,7,1),0)+1),0) | H81: =IF(E81=0,"",E81-G81)
A82: Julio 2026 | B82: La Cata SJM | C82: =IFERROR(SUMIFS('Ventas Diarias'!$M:$M,'Ventas Diarias'!$B:$B,B82,'Ventas Diarias'!$A:$A,">="&DATE(2026,7,1),'Ventas Diarias'!$A:$A,"<"&EOMONTH(DATE(2026,7,1),0)+1)/1.18,0) | D82: =IFERROR(SUMIFS(Gastos!$E:$E,Gastos!$B:$B,B82,Gastos!$A:$A,">="&DATE(2026,7,1),Gastos!$A:$A,"<"&EOMONTH(DATE(2026,7,1),0)+1),0) | E82: =IFERROR(SUMIFS('Ventas Diarias'!$C:$C,'Ventas Diarias'!$B:$B,B82,'Ventas Diarias'!$A:$A,">="&DATE(2026,7,1),'Ventas Diarias'!$A:$A,"<"&EOMONTH(DATE(2026,7,1),0)+1)+SUMIFS('Ventas Diarias'!$F:$F,'Ventas Diarias'!$B:$B,B82,'Ventas Diarias'!$A:$A,">="&DATE(2026,7,1),'Ventas Diarias'!$A:$A,"<"&EOMONTH(DATE(2026,7,1),0)+1)+SUMIFS('Ventas Diarias'!$G:$G,'Ventas Diarias'!$B:$B,B82,'Ventas Diarias'!$A:$A,">="&DATE(2026,7,1),'Ventas Diarias'!$A:$A,"<"&EOMONTH(DATE(2026,7,1),0)+1)-SUMIFS('Ventas Diarias'!$I:$I,'Ventas Diarias'!$B:$B,B82,'Ventas Diarias'!$A:$A,">="&DATE(2026,7,1),'Ventas Diarias'!$A:$A,"<"&EOMONTH(DATE(2026,7,1),0)+1)-D82,0) | F82: =IFERROR(E82/C82,"") | G82: =IFERROR(SUMIFS(CXP!$M:$M,CXP!$N:$N,"Sí",CXP!$B:$B,B82,CXP!$J:$J,">="&DATE(2026,7,1),CXP!$J:$J,"<"&EOMONTH(DATE(2026,7,1),0)+1),0) | H82: =IF(E82=0,"",E82-G82)
A83: Agosto 2026 | B83: La Cata LMF | C83: =IFERROR(SUMIFS('Ventas Diarias'!$M:$M,'Ventas Diarias'!$B:$B,B83,'Ventas Diarias'!$A:$A,">="&DATE(2026,8,1),'Ventas Diarias'!$A:$A,"<"&EOMONTH(DATE(2026,8,1),0)+1)/1.18,0) | D83: =IFERROR(SUMIFS(Gastos!$E:$E,Gastos!$B:$B,B83,Gastos!$A:$A,">="&DATE(2026,8,1),Gastos!$A:$A,"<"&EOMONTH(DATE(2026,8,1),0)+1),0) | E83: =IFERROR(SUMIFS('Ventas Diarias'!$C:$C,'Ventas Diarias'!$B:$B,B83,'Ventas Diarias'!$A:$A,">="&DATE(2026,8,1),'Ventas Diarias'!$A:$A,"<"&EOMONTH(DATE(2026,8,1),0)+1)+SUMIFS('Ventas Diarias'!$F:$F,'Ventas Diarias'!$B:$B,B83,'Ventas Diarias'!$A:$A,">="&DATE(2026,8,1),'Ventas Diarias'!$A:$A,"<"&EOMONTH(DATE(2026,8,1),0)+1)+SUMIFS('Ventas Diarias'!$G:$G,'Ventas Diarias'!$B:$B,B83,'Ventas Diarias'!$A:$A,">="&DATE(2026,8,1),'Ventas Diarias'!$A:$A,"<"&EOMONTH(DATE(2026,8,1),0)+1)-SUMIFS('Ventas Diarias'!$I:$I,'Ventas Diarias'!$B:$B,B83,'Ventas Diarias'!$A:$A,">="&DATE(2026,8,1),'Ventas Diarias'!$A:$A,"<"&EOMONTH(DATE(2026,8,1),0)+1)-D83,0) | F83: =IFERROR(E83/C83,"") | G83: =IFERROR(SUMIFS(CXP!$M:$M,CXP!$N:$N,"Sí",CXP!$B:$B,B83,CXP!$J:$J,">="&DATE(2026,8,1),CXP!$J:$J,"<"&EOMONTH(DATE(2026,8,1),0)+1),0) | H83: =IF(E83=0,"",E83-G83)
A84: Agosto 2026 | B84: La Cata DF | C84: =IFERROR(SUMIFS('Ventas Diarias'!$M:$M,'Ventas Diarias'!$B:$B,B84,'Ventas Diarias'!$A:$A,">="&DATE(2026,8,1),'Ventas Diarias'!$A:$A,"<"&EOMONTH(DATE(2026,8,1),0)+1)/1.18,0) | D84: =IFERROR(SUMIFS(Gastos!$E:$E,Gastos!$B:$B,B84,Gastos!$A:$A,">="&DATE(2026,8,1),Gastos!$A:$A,"<"&EOMONTH(DATE(2026,8,1),0)+1),0) | E84: =IFERROR(SUMIFS('Ventas Diarias'!$C:$C,'Ventas Diarias'!$B:$B,B84,'Ventas Diarias'!$A:$A,">="&DATE(2026,8,1),'Ventas Diarias'!$A:$A,"<"&EOMONTH(DATE(2026,8,1),0)+1)+SUMIFS('Ventas Diarias'!$F:$F,'Ventas Diarias'!$B:$B,B84,'Ventas Diarias'!$A:$A,">="&DATE(2026,8,1),'Ventas Diarias'!$A:$A,"<"&EOMONTH(DATE(2026,8,1),0)+1)+SUMIFS('Ventas Diarias'!$G:$G,'Ventas Diarias'!$B:$B,B84,'Ventas Diarias'!$A:$A,">="&DATE(2026,8,1),'Ventas Diarias'!$A:$A,"<"&EOMONTH(DATE(2026,8,1),0)+1)-SUMIFS('Ventas Diarias'!$I:$I,'Ventas Diarias'!$B:$B,B84,'Ventas Diarias'!$A:$A,">="&DATE(2026,8,1),'Ventas Diarias'!$A:$A,"<"&EOMONTH(DATE(2026,8,1),0)+1)-D84,0) | F84: =IFERROR(E84/C84,"") | G84: =IFERROR(SUMIFS(CXP!$M:$M,CXP!$N:$N,"Sí",CXP!$B:$B,B84,CXP!$J:$J,">="&DATE(2026,8,1),CXP!$J:$J,"<"&EOMONTH(DATE(2026,8,1),0)+1),0) | H84: =IF(E84=0,"",E84-G84)
A85: Agosto 2026 | B85: La Cata SJM | C85: =IFERROR(SUMIFS('Ventas Diarias'!$M:$M,'Ventas Diarias'!$B:$B,B85,'Ventas Diarias'!$A:$A,">="&DATE(2026,8,1),'Ventas Diarias'!$A:$A,"<"&EOMONTH(DATE(2026,8,1),0)+1)/1.18,0) | D85: =IFERROR(SUMIFS(Gastos!$E:$E,Gastos!$B:$B,B85,Gastos!$A:$A,">="&DATE(2026,8,1),Gastos!$A:$A,"<"&EOMONTH(DATE(2026,8,1),0)+1),0) | E85: =IFERROR(SUMIFS('Ventas Diarias'!$C:$C,'Ventas Diarias'!$B:$B,B85,'Ventas Diarias'!$A:$A,">="&DATE(2026,8,1),'Ventas Diarias'!$A:$A,"<"&EOMONTH(DATE(2026,8,1),0)+1)+SUMIFS('Ventas Diarias'!$F:$F,'Ventas Diarias'!$B:$B,B85,'Ventas Diarias'!$A:$A,">="&DATE(2026,8,1),'Ventas Diarias'!$A:$A,"<"&EOMONTH(DATE(2026,8,1),0)+1)+SUMIFS('Ventas Diarias'!$G:$G,'Ventas Diarias'!$B:$B,B85,'Ventas Diarias'!$A:$A,">="&DATE(2026,8,1),'Ventas Diarias'!$A:$A,"<"&EOMONTH(DATE(2026,8,1),0)+1)-SUMIFS('Ventas Diarias'!$I:$I,'Ventas Diarias'!$B:$B,B85,'Ventas Diarias'!$A:$A,">="&DATE(2026,8,1),'Ventas Diarias'!$A:$A,"<"&EOMONTH(DATE(2026,8,1),0)+1)-D85,0) | F85: =IFERROR(E85/C85,"") | G85: =IFERROR(SUMIFS(CXP!$M:$M,CXP!$N:$N,"Sí",CXP!$B:$B,B85,CXP!$J:$J,">="&DATE(2026,8,1),CXP!$J:$J,"<"&EOMONTH(DATE(2026,8,1),0)+1),0) | H85: =IF(E85=0,"",E85-G85)
A86: Septiembre 2026 | B86: La Cata LMF | C86: =IFERROR(SUMIFS('Ventas Diarias'!$M:$M,'Ventas Diarias'!$B:$B,B86,'Ventas Diarias'!$A:$A,">="&DATE(2026,9,1),'Ventas Diarias'!$A:$A,"<"&EOMONTH(DATE(2026,9,1),0)+1)/1.18,0) | D86: =IFERROR(SUMIFS(Gastos!$E:$E,Gastos!$B:$B,B86,Gastos!$A:$A,">="&DATE(2026,9,1),Gastos!$A:$A,"<"&EOMONTH(DATE(2026,9,1),0)+1),0) | E86: =IFERROR(SUMIFS('Ventas Diarias'!$C:$C,'Ventas Diarias'!$B:$B,B86,'Ventas Diarias'!$A:$A,">="&DATE(2026,9,1),'Ventas Diarias'!$A:$A,"<"&EOMONTH(DATE(2026,9,1),0)+1)+SUMIFS('Ventas Diarias'!$F:$F,'Ventas Diarias'!$B:$B,B86,'Ventas Diarias'!$A:$A,">="&DATE(2026,9,1),'Ventas Diarias'!$A:$A,"<"&EOMONTH(DATE(2026,9,1),0)+1)+SUMIFS('Ventas Diarias'!$G:$G,'Ventas Diarias'!$B:$B,B86,'Ventas Diarias'!$A:$A,">="&DATE(2026,9,1),'Ventas Diarias'!$A:$A,"<"&EOMONTH(DATE(2026,9,1),0)+1)-SUMIFS('Ventas Diarias'!$I:$I,'Ventas Diarias'!$B:$B,B86,'Ventas Diarias'!$A:$A,">="&DATE(2026,9,1),'Ventas Diarias'!$A:$A,"<"&EOMONTH(DATE(2026,9,1),0)+1)-D86,0) | F86: =IFERROR(E86/C86,"") | G86: =IFERROR(SUMIFS(CXP!$M:$M,CXP!$N:$N,"Sí",CXP!$B:$B,B86,CXP!$J:$J,">="&DATE(2026,9,1),CXP!$J:$J,"<"&EOMONTH(DATE(2026,9,1),0)+1),0) | H86: =IF(E86=0,"",E86-G86)
A87: Septiembre 2026 | B87: La Cata DF | C87: =IFERROR(SUMIFS('Ventas Diarias'!$M:$M,'Ventas Diarias'!$B:$B,B87,'Ventas Diarias'!$A:$A,">="&DATE(2026,9,1),'Ventas Diarias'!$A:$A,"<"&EOMONTH(DATE(2026,9,1),0)+1)/1.18,0) | D87: =IFERROR(SUMIFS(Gastos!$E:$E,Gastos!$B:$B,B87,Gastos!$A:$A,">="&DATE(2026,9,1),Gastos!$A:$A,"<"&EOMONTH(DATE(2026,9,1),0)+1),0) | E87: =IFERROR(SUMIFS('Ventas Diarias'!$C:$C,'Ventas Diarias'!$B:$B,B87,'Ventas Diarias'!$A:$A,">="&DATE(2026,9,1),'Ventas Diarias'!$A:$A,"<"&EOMONTH(DATE(2026,9,1),0)+1)+SUMIFS('Ventas Diarias'!$F:$F,'Ventas Diarias'!$B:$B,B87,'Ventas Diarias'!$A:$A,">="&DATE(2026,9,1),'Ventas Diarias'!$A:$A,"<"&EOMONTH(DATE(2026,9,1),0)+1)+SUMIFS('Ventas Diarias'!$G:$G,'Ventas Diarias'!$B:$B,B87,'Ventas Diarias'!$A:$A,">="&DATE(2026,9,1),'Ventas Diarias'!$A:$A,"<"&EOMONTH(DATE(2026,9,1),0)+1)-SUMIFS('Ventas Diarias'!$I:$I,'Ventas Diarias'!$B:$B,B87,'Ventas Diarias'!$A:$A,">="&DATE(2026,9,1),'Ventas Diarias'!$A:$A,"<"&EOMONTH(DATE(2026,9,1),0)+1)-D87,0) | F87: =IFERROR(E87/C87,"") | G87: =IFERROR(SUMIFS(CXP!$M:$M,CXP!$N:$N,"Sí",CXP!$B:$B,B87,CXP!$J:$J,">="&DATE(2026,9,1),CXP!$J:$J,"<"&EOMONTH(DATE(2026,9,1),0)+1),0) | H87: =IF(E87=0,"",E87-G87)
A88: Septiembre 2026 | B88: La Cata SJM | C88: =IFERROR(SUMIFS('Ventas Diarias'!$M:$M,'Ventas Diarias'!$B:$B,B88,'Ventas Diarias'!$A:$A,">="&DATE(2026,9,1),'Ventas Diarias'!$A:$A,"<"&EOMONTH(DATE(2026,9,1),0)+1)/1.18,0) | D88: =IFERROR(SUMIFS(Gastos!$E:$E,Gastos!$B:$B,B88,Gastos!$A:$A,">="&DATE(2026,9,1),Gastos!$A:$A,"<"&EOMONTH(DATE(2026,9,1),0)+1),0) | E88: =IFERROR(SUMIFS('Ventas Diarias'!$C:$C,'Ventas Diarias'!$B:$B,B88,'Ventas Diarias'!$A:$A,">="&DATE(2026,9,1),'Ventas Diarias'!$A:$A,"<"&EOMONTH(DATE(2026,9,1),0)+1)+SUMIFS('Ventas Diarias'!$F:$F,'Ventas Diarias'!$B:$B,B88,'Ventas Diarias'!$A:$A,">="&DATE(2026,9,1),'Ventas Diarias'!$A:$A,"<"&EOMONTH(DATE(2026,9,1),0)+1)+SUMIFS('Ventas Diarias'!$G:$G,'Ventas Diarias'!$B:$B,B88,'Ventas Diarias'!$A:$A,">="&DATE(2026,9,1),'Ventas Diarias'!$A:$A,"<"&EOMONTH(DATE(2026,9,1),0)+1)-SUMIFS('Ventas Diarias'!$I:$I,'Ventas Diarias'!$B:$B,B88,'Ventas Diarias'!$A:$A,">="&DATE(2026,9,1),'Ventas Diarias'!$A:$A,"<"&EOMONTH(DATE(2026,9,1),0)+1)-D88,0) | F88: =IFERROR(E88/C88,"") | G88: =IFERROR(SUMIFS(CXP!$M:$M,CXP!$N:$N,"Sí",CXP!$B:$B,B88,CXP!$J:$J,">="&DATE(2026,9,1),CXP!$J:$J,"<"&EOMONTH(DATE(2026,9,1),0)+1),0) | H88: =IF(E88=0,"",E88-G88)
A89: Octubre 2026 | B89: La Cata LMF | C89: =IFERROR(SUMIFS('Ventas Diarias'!$M:$M,'Ventas Diarias'!$B:$B,B89,'Ventas Diarias'!$A:$A,">="&DATE(2026,10,1),'Ventas Diarias'!$A:$A,"<"&EOMONTH(DATE(2026,10,1),0)+1)/1.18,0) | D89: =IFERROR(SUMIFS(Gastos!$E:$E,Gastos!$B:$B,B89,Gastos!$A:$A,">="&DATE(2026,10,1),Gastos!$A:$A,"<"&EOMONTH(DATE(2026,10,1),0)+1),0) | E89: =IFERROR(SUMIFS('Ventas Diarias'!$C:$C,'Ventas Diarias'!$B:$B,B89,'Ventas Diarias'!$A:$A,">="&DATE(2026,10,1),'Ventas Diarias'!$A:$A,"<"&EOMONTH(DATE(2026,10,1),0)+1)+SUMIFS('Ventas Diarias'!$F:$F,'Ventas Diarias'!$B:$B,B89,'Ventas Diarias'!$A:$A,">="&DATE(2026,10,1),'Ventas Diarias'!$A:$A,"<"&EOMONTH(DATE(2026,10,1),0)+1)+SUMIFS('Ventas Diarias'!$G:$G,'Ventas Diarias'!$B:$B,B89,'Ventas Diarias'!$A:$A,">="&DATE(2026,10,1),'Ventas Diarias'!$A:$A,"<"&EOMONTH(DATE(2026,10,1),0)+1)-SUMIFS('Ventas Diarias'!$I:$I,'Ventas Diarias'!$B:$B,B89,'Ventas Diarias'!$A:$A,">="&DATE(2026,10,1),'Ventas Diarias'!$A:$A,"<"&EOMONTH(DATE(2026,10,1),0)+1)-D89,0) | F89: =IFERROR(E89/C89,"") | G89: =IFERROR(SUMIFS(CXP!$M:$M,CXP!$N:$N,"Sí",CXP!$B:$B,B89,CXP!$J:$J,">="&DATE(2026,10,1),CXP!$J:$J,"<"&EOMONTH(DATE(2026,10,1),0)+1),0) | H89: =IF(E89=0,"",E89-G89)
A90: Octubre 2026 | B90: La Cata DF | C90: =IFERROR(SUMIFS('Ventas Diarias'!$M:$M,'Ventas Diarias'!$B:$B,B90,'Ventas Diarias'!$A:$A,">="&DATE(2026,10,1),'Ventas Diarias'!$A:$A,"<"&EOMONTH(DATE(2026,10,1),0)+1)/1.18,0) | D90: =IFERROR(SUMIFS(Gastos!$E:$E,Gastos!$B:$B,B90,Gastos!$A:$A,">="&DATE(2026,10,1),Gastos!$A:$A,"<"&EOMONTH(DATE(2026,10,1),0)+1),0) | E90: =IFERROR(SUMIFS('Ventas Diarias'!$C:$C,'Ventas Diarias'!$B:$B,B90,'Ventas Diarias'!$A:$A,">="&DATE(2026,10,1),'Ventas Diarias'!$A:$A,"<"&EOMONTH(DATE(2026,10,1),0)+1)+SUMIFS('Ventas Diarias'!$F:$F,'Ventas Diarias'!$B:$B,B90,'Ventas Diarias'!$A:$A,">="&DATE(2026,10,1),'Ventas Diarias'!$A:$A,"<"&EOMONTH(DATE(2026,10,1),0)+1)+SUMIFS('Ventas Diarias'!$G:$G,'Ventas Diarias'!$B:$B,B90,'Ventas Diarias'!$A:$A,">="&DATE(2026,10,1),'Ventas Diarias'!$A:$A,"<"&EOMONTH(DATE(2026,10,1),0)+1)-SUMIFS('Ventas Diarias'!$I:$I,'Ventas Diarias'!$B:$B,B90,'Ventas Diarias'!$A:$A,">="&DATE(2026,10,1),'Ventas Diarias'!$A:$A,"<"&EOMONTH(DATE(2026,10,1),0)+1)-D90,0) | F90: =IFERROR(E90/C90,"") | G90: =IFERROR(SUMIFS(CXP!$M:$M,CXP!$N:$N,"Sí",CXP!$B:$B,B90,CXP!$J:$J,">="&DATE(2026,10,1),CXP!$J:$J,"<"&EOMONTH(DATE(2026,10,1),0)+1),0) | H90: =IF(E90=0,"",E90-G90)
A91: Octubre 2026 | B91: La Cata SJM | C91: =IFERROR(SUMIFS('Ventas Diarias'!$M:$M,'Ventas Diarias'!$B:$B,B91,'Ventas Diarias'!$A:$A,">="&DATE(2026,10,1),'Ventas Diarias'!$A:$A,"<"&EOMONTH(DATE(2026,10,1),0)+1)/1.18,0) | D91: =IFERROR(SUMIFS(Gastos!$E:$E,Gastos!$B:$B,B91,Gastos!$A:$A,">="&DATE(2026,10,1),Gastos!$A:$A,"<"&EOMONTH(DATE(2026,10,1),0)+1),0) | E91: =IFERROR(SUMIFS('Ventas Diarias'!$C:$C,'Ventas Diarias'!$B:$B,B91,'Ventas Diarias'!$A:$A,">="&DATE(2026,10,1),'Ventas Diarias'!$A:$A,"<"&EOMONTH(DATE(2026,10,1),0)+1)+SUMIFS('Ventas Diarias'!$F:$F,'Ventas Diarias'!$B:$B,B91,'Ventas Diarias'!$A:$A,">="&DATE(2026,10,1),'Ventas Diarias'!$A:$A,"<"&EOMONTH(DATE(2026,10,1),0)+1)+SUMIFS('Ventas Diarias'!$G:$G,'Ventas Diarias'!$B:$B,B91,'Ventas Diarias'!$A:$A,">="&DATE(2026,10,1),'Ventas Diarias'!$A:$A,"<"&EOMONTH(DATE(2026,10,1),0)+1)-SUMIFS('Ventas Diarias'!$I:$I,'Ventas Diarias'!$B:$B,B91,'Ventas Diarias'!$A:$A,">="&DATE(2026,10,1),'Ventas Diarias'!$A:$A,"<"&EOMONTH(DATE(2026,10,1),0)+1)-D91,0) | F91: =IFERROR(E91/C91,"") | G91: =IFERROR(SUMIFS(CXP!$M:$M,CXP!$N:$N,"Sí",CXP!$B:$B,B91,CXP!$J:$J,">="&DATE(2026,10,1),CXP!$J:$J,"<"&EOMONTH(DATE(2026,10,1),0)+1),0) | H91: =IF(E91=0,"",E91-G91)
A92: Noviembre 2026 | B92: La Cata LMF | C92: =IFERROR(SUMIFS('Ventas Diarias'!$M:$M,'Ventas Diarias'!$B:$B,B92,'Ventas Diarias'!$A:$A,">="&DATE(2026,11,1),'Ventas Diarias'!$A:$A,"<"&EOMONTH(DATE(2026,11,1),0)+1)/1.18,0) | D92: =IFERROR(SUMIFS(Gastos!$E:$E,Gastos!$B:$B,B92,Gastos!$A:$A,">="&DATE(2026,11,1),Gastos!$A:$A,"<"&EOMONTH(DATE(2026,11,1),0)+1),0) | E92: =IFERROR(SUMIFS('Ventas Diarias'!$C:$C,'Ventas Diarias'!$B:$B,B92,'Ventas Diarias'!$A:$A,">="&DATE(2026,11,1),'Ventas Diarias'!$A:$A,"<"&EOMONTH(DATE(2026,11,1),0)+1)+SUMIFS('Ventas Diarias'!$F:$F,'Ventas Diarias'!$B:$B,B92,'Ventas Diarias'!$A:$A,">="&DATE(2026,11,1),'Ventas Diarias'!$A:$A,"<"&EOMONTH(DATE(2026,11,1),0)+1)+SUMIFS('Ventas Diarias'!$G:$G,'Ventas Diarias'!$B:$B,B92,'Ventas Diarias'!$A:$A,">="&DATE(2026,11,1),'Ventas Diarias'!$A:$A,"<"&EOMONTH(DATE(2026,11,1),0)+1)-SUMIFS('Ventas Diarias'!$I:$I,'Ventas Diarias'!$B:$B,B92,'Ventas Diarias'!$A:$A,">="&DATE(2026,11,1),'Ventas Diarias'!$A:$A,"<"&EOMONTH(DATE(2026,11,1),0)+1)-D92,0) | F92: =IFERROR(E92/C92,"") | G92: =IFERROR(SUMIFS(CXP!$M:$M,CXP!$N:$N,"Sí",CXP!$B:$B,B92,CXP!$J:$J,">="&DATE(2026,11,1),CXP!$J:$J,"<"&EOMONTH(DATE(2026,11,1),0)+1),0) | H92: =IF(E92=0,"",E92-G92)
A93: Noviembre 2026 | B93: La Cata DF | C93: =IFERROR(SUMIFS('Ventas Diarias'!$M:$M,'Ventas Diarias'!$B:$B,B93,'Ventas Diarias'!$A:$A,">="&DATE(2026,11,1),'Ventas Diarias'!$A:$A,"<"&EOMONTH(DATE(2026,11,1),0)+1)/1.18,0) | D93: =IFERROR(SUMIFS(Gastos!$E:$E,Gastos!$B:$B,B93,Gastos!$A:$A,">="&DATE(2026,11,1),Gastos!$A:$A,"<"&EOMONTH(DATE(2026,11,1),0)+1),0) | E93: =IFERROR(SUMIFS('Ventas Diarias'!$C:$C,'Ventas Diarias'!$B:$B,B93,'Ventas Diarias'!$A:$A,">="&DATE(2026,11,1),'Ventas Diarias'!$A:$A,"<"&EOMONTH(DATE(2026,11,1),0)+1)+SUMIFS('Ventas Diarias'!$F:$F,'Ventas Diarias'!$B:$B,B93,'Ventas Diarias'!$A:$A,">="&DATE(2026,11,1),'Ventas Diarias'!$A:$A,"<"&EOMONTH(DATE(2026,11,1),0)+1)+SUMIFS('Ventas Diarias'!$G:$G,'Ventas Diarias'!$B:$B,B93,'Ventas Diarias'!$A:$A,">="&DATE(2026,11,1),'Ventas Diarias'!$A:$A,"<"&EOMONTH(DATE(2026,11,1),0)+1)-SUMIFS('Ventas Diarias'!$I:$I,'Ventas Diarias'!$B:$B,B93,'Ventas Diarias'!$A:$A,">="&DATE(2026,11,1),'Ventas Diarias'!$A:$A,"<"&EOMONTH(DATE(2026,11,1),0)+1)-D93,0) | F93: =IFERROR(E93/C93,"") | G93: =IFERROR(SUMIFS(CXP!$M:$M,CXP!$N:$N,"Sí",CXP!$B:$B,B93,CXP!$J:$J,">="&DATE(2026,11,1),CXP!$J:$J,"<"&EOMONTH(DATE(2026,11,1),0)+1),0) | H93: =IF(E93=0,"",E93-G93)
A94: Noviembre 2026 | B94: La Cata SJM | C94: =IFERROR(SUMIFS('Ventas Diarias'!$M:$M,'Ventas Diarias'!$B:$B,B94,'Ventas Diarias'!$A:$A,">="&DATE(2026,11,1),'Ventas Diarias'!$A:$A,"<"&EOMONTH(DATE(2026,11,1),0)+1)/1.18,0) | D94: =IFERROR(SUMIFS(Gastos!$E:$E,Gastos!$B:$B,B94,Gastos!$A:$A,">="&DATE(2026,11,1),Gastos!$A:$A,"<"&EOMONTH(DATE(2026,11,1),0)+1),0) | E94: =IFERROR(SUMIFS('Ventas Diarias'!$C:$C,'Ventas Diarias'!$B:$B,B94,'Ventas Diarias'!$A:$A,">="&DATE(2026,11,1),'Ventas Diarias'!$A:$A,"<"&EOMONTH(DATE(2026,11,1),0)+1)+SUMIFS('Ventas Diarias'!$F:$F,'Ventas Diarias'!$B:$B,B94,'Ventas Diarias'!$A:$A,">="&DATE(2026,11,1),'Ventas Diarias'!$A:$A,"<"&EOMONTH(DATE(2026,11,1),0)+1)+SUMIFS('Ventas Diarias'!$G:$G,'Ventas Diarias'!$B:$B,B94,'Ventas Diarias'!$A:$A,">="&DATE(2026,11,1),'Ventas Diarias'!$A:$A,"<"&EOMONTH(DATE(2026,11,1),0)+1)-SUMIFS('Ventas Diarias'!$I:$I,'Ventas Diarias'!$B:$B,B94,'Ventas Diarias'!$A:$A,">="&DATE(2026,11,1),'Ventas Diarias'!$A:$A,"<"&EOMONTH(DATE(2026,11,1),0)+1)-D94,0) | F94: =IFERROR(E94/C94,"") | G94: =IFERROR(SUMIFS(CXP!$M:$M,CXP!$N:$N,"Sí",CXP!$B:$B,B94,CXP!$J:$J,">="&DATE(2026,11,1),CXP!$J:$J,"<"&EOMONTH(DATE(2026,11,1),0)+1),0) | H94: =IF(E94=0,"",E94-G94)
A95: Diciembre 2026 | B95: La Cata LMF | C95: =IFERROR(SUMIFS('Ventas Diarias'!$M:$M,'Ventas Diarias'!$B:$B,B95,'Ventas Diarias'!$A:$A,">="&DATE(2026,12,1),'Ventas Diarias'!$A:$A,"<"&EOMONTH(DATE(2026,12,1),0)+1)/1.18,0) | D95: =IFERROR(SUMIFS(Gastos!$E:$E,Gastos!$B:$B,B95,Gastos!$A:$A,">="&DATE(2026,12,1),Gastos!$A:$A,"<"&EOMONTH(DATE(2026,12,1),0)+1),0) | E95: =IFERROR(SUMIFS('Ventas Diarias'!$C:$C,'Ventas Diarias'!$B:$B,B95,'Ventas Diarias'!$A:$A,">="&DATE(2026,12,1),'Ventas Diarias'!$A:$A,"<"&EOMONTH(DATE(2026,12,1),0)+1)+SUMIFS('Ventas Diarias'!$F:$F,'Ventas Diarias'!$B:$B,B95,'Ventas Diarias'!$A:$A,">="&DATE(2026,12,1),'Ventas Diarias'!$A:$A,"<"&EOMONTH(DATE(2026,12,1),0)+1)+SUMIFS('Ventas Diarias'!$G:$G,'Ventas Diarias'!$B:$B,B95,'Ventas Diarias'!$A:$A,">="&DATE(2026,12,1),'Ventas Diarias'!$A:$A,"<"&EOMONTH(DATE(2026,12,1),0)+1)-SUMIFS('Ventas Diarias'!$I:$I,'Ventas Diarias'!$B:$B,B95,'Ventas Diarias'!$A:$A,">="&DATE(2026,12,1),'Ventas Diarias'!$A:$A,"<"&EOMONTH(DATE(2026,12,1),0)+1)-D95,0) | F95: =IFERROR(E95/C95,"") | G95: =IFERROR(SUMIFS(CXP!$M:$M,CXP!$N:$N,"Sí",CXP!$B:$B,B95,CXP!$J:$J,">="&DATE(2026,12,1),CXP!$J:$J,"<"&EOMONTH(DATE(2026,12,1),0)+1),0) | H95: =IF(E95=0,"",E95-G95)
A96: Diciembre 2026 | B96: La Cata DF | C96: =IFERROR(SUMIFS('Ventas Diarias'!$M:$M,'Ventas Diarias'!$B:$B,B96,'Ventas Diarias'!$A:$A,">="&DATE(2026,12,1),'Ventas Diarias'!$A:$A,"<"&EOMONTH(DATE(2026,12,1),0)+1)/1.18,0) | D96: =IFERROR(SUMIFS(Gastos!$E:$E,Gastos!$B:$B,B96,Gastos!$A:$A,">="&DATE(2026,12,1),Gastos!$A:$A,"<"&EOMONTH(DATE(2026,12,1),0)+1),0) | E96: =IFERROR(SUMIFS('Ventas Diarias'!$C:$C,'Ventas Diarias'!$B:$B,B96,'Ventas Diarias'!$A:$A,">="&DATE(2026,12,1),'Ventas Diarias'!$A:$A,"<"&EOMONTH(DATE(2026,12,1),0)+1)+SUMIFS('Ventas Diarias'!$F:$F,'Ventas Diarias'!$B:$B,B96,'Ventas Diarias'!$A:$A,">="&DATE(2026,12,1),'Ventas Diarias'!$A:$A,"<"&EOMONTH(DATE(2026,12,1),0)+1)+SUMIFS('Ventas Diarias'!$G:$G,'Ventas Diarias'!$B:$B,B96,'Ventas Diarias'!$A:$A,">="&DATE(2026,12,1),'Ventas Diarias'!$A:$A,"<"&EOMONTH(DATE(2026,12,1),0)+1)-SUMIFS('Ventas Diarias'!$I:$I,'Ventas Diarias'!$B:$B,B96,'Ventas Diarias'!$A:$A,">="&DATE(2026,12,1),'Ventas Diarias'!$A:$A,"<"&EOMONTH(DATE(2026,12,1),0)+1)-D96,0) | F96: =IFERROR(E96/C96,"") | G96: =IFERROR(SUMIFS(CXP!$M:$M,CXP!$N:$N,"Sí",CXP!$B:$B,B96,CXP!$J:$J,">="&DATE(2026,12,1),CXP!$J:$J,"<"&EOMONTH(DATE(2026,12,1),0)+1),0) | H96: =IF(E96=0,"",E96-G96)
A97: Diciembre 2026 | B97: La Cata SJM | C97: =IFERROR(SUMIFS('Ventas Diarias'!$M:$M,'Ventas Diarias'!$B:$B,B97,'Ventas Diarias'!$A:$A,">="&DATE(2026,12,1),'Ventas Diarias'!$A:$A,"<"&EOMONTH(DATE(2026,12,1),0)+1)/1.18,0) | D97: =IFERROR(SUMIFS(Gastos!$E:$E,Gastos!$B:$B,B97,Gastos!$A:$A,">="&DATE(2026,12,1),Gastos!$A:$A,"<"&EOMONTH(DATE(2026,12,1),0)+1),0) | E97: =IFERROR(SUMIFS('Ventas Diarias'!$C:$C,'Ventas Diarias'!$B:$B,B97,'Ventas Diarias'!$A:$A,">="&DATE(2026,12,1),'Ventas Diarias'!$A:$A,"<"&EOMONTH(DATE(2026,12,1),0)+1)+SUMIFS('Ventas Diarias'!$F:$F,'Ventas Diarias'!$B:$B,B97,'Ventas Diarias'!$A:$A,">="&DATE(2026,12,1),'Ventas Diarias'!$A:$A,"<"&EOMONTH(DATE(2026,12,1),0)+1)+SUMIFS('Ventas Diarias'!$G:$G,'Ventas Diarias'!$B:$B,B97,'Ventas Diarias'!$A:$A,">="&DATE(2026,12,1),'Ventas Diarias'!$A:$A,"<"&EOMONTH(DATE(2026,12,1),0)+1)-SUMIFS('Ventas Diarias'!$I:$I,'Ventas Diarias'!$B:$B,B97,'Ventas Diarias'!$A:$A,">="&DATE(2026,12,1),'Ventas Diarias'!$A:$A,"<"&EOMONTH(DATE(2026,12,1),0)+1)-D97,0) | F97: =IFERROR(E97/C97,"") | G97: =IFERROR(SUMIFS(CXP!$M:$M,CXP!$N:$N,"Sí",CXP!$B:$B,B97,CXP!$J:$J,">="&DATE(2026,12,1),CXP!$J:$J,"<"&EOMONTH(DATE(2026,12,1),0)+1),0) | H97: =IF(E97=0,"",E97-G97)
A98: TOTAL 2026 | C98: =SUM(C62:C97) | D98: =SUM(D62:D97) | E98: =SUM(E62:E97) | F98: =IFERROR(E98/C98,"") | G98: =SUM(G62:G97) | H98: =SUM(H62:H97)
A100: 📊 KPIs FINANCIEROS 2026
A101: Ventas Totales: | B101: =C98 | D101: Mejor Mes (Ventas): | E101: =INDEX(A62:A97,MATCH(MAX(C62:C97),C62:C97,0))
A102: Gastos Totales: | B102: =D98 | D102: Peor Mes (Ventas): | E102: =INDEX(A62:A97,MATCH(_xlfn.MINIFS(C62:C97,C62:C97,">0"),C62:C97,0))
A103: Utilidad Neta Total: | B103: =E98 | D103: Mejor Margen: | E103: =MAX(F62:F97)
A104: Margen Promedio: | B104: =F98 | D104: Tienda Más Rentable: | E104: =INDEX(B62:B97,MATCH(MAX(E62:E97),E62:E97,0))
...

Sheet Ventas Diarias (Backup)
A1: FECHA | B1: UBICACION | C1: EFECTIVO | D1: TARJETA (BRUTA) | E1: FEE TARJETA (3.45%) | F1: TARJETA NETA | G1: TRANSFERENCIAS | H1: PEDIDOS YA | I1: NOTAS DE CREDITO (-) | J1: TOTAL COBRADO CON ITBS | K1: VENTAS GRABADAS (BASE SIN ITBS) | L1: ITBS COBRADO | M1: VENTAS SIN ITBIS (para utilidad) | N1: DEPOSITO EFECTIVO (SEMANAL) | O1: NOTAS
A2: 46174 | B2: La Cata LMF | C2: 20725 | D2: 5905 | E2: =D2*Setup!$B$5 | F2: =D2-E2 | G2: 2365 | I2: 0 | J2: =C2+F2+G2-I2 | L2: =K2*Setup!$B$6 | M2: =J2-L2
A3: 46175 | B3: La Cata LMF | C3: 39077 | D3: 12420 | E3: =D3*Setup!$B$5 | F3: =D3-E3 | G3: 0 | I3: 0 | J3: =C3+F3+G3-I3 | L3: =K3*Setup!$B$6 | M3: =J3-L3
A4: 46176 | B4: La Cata LMF | C4: 54488 | D4: 13620 | E4: =D4*Setup!$B$5 | F4: =D4-E4 | G4: 1866 | I4: 0 | J4: =C4+F4+G4-I4 | L4: =K4*Setup!$B$6 | M4: =J4-L4
A5: 46177 | B5: La Cata LMF | C5: 104926 | D5: 46270 | E5: =D5*Setup!$B$5 | F5: =D5-E5 | G5: 3255 | I5: 0 | J5: =C5+F5+G5-I5 | L5: =K5*Setup!$B$6 | M5: =J5-L5
A6: 46178 | B6: La Cata LMF | C6: 0 | D6: 0 | E6: =D6*Setup!$B$5 | F6: =D6-E6 | G6: 0 | I6: 0 | J6: =C6+F6+G6-I6 | L6: =K6*Setup!$B$6 | M6: =J6-L6
A7: 46179 | B7: La Cata LMF | C7: 135910 | D7: 38305 | E7: =D7*Setup!$B$5 | F7: =D7-E7 | G7: 6875 | I7: 0 | J7: =C7+F7+G7-I7 | L7: =K7*Setup!$B$6 | M7: =J7-L7
A8: 46180 | B8: La Cata LMF | C8: 168335 | D8: 53835 | E8: =D8*Setup!$B$5 | F8: =D8-E8 | G8: 0 | I8: 0 | J8: =C8+F8+G8-I8 | L8: =K8*Setup!$B$6 | M8: =J8-L8
A9: 46181 | B9: La Cata LMF | C9: 20725 | D9: 5905 | E9: =D9*Setup!$B$5 | F9: =D9-E9 | G9: 2365 | I9: 0 | J9: =C9+F9+G9-I9 | L9: =K9*Setup!$B$6 | M9: =J9-L9 | N9: 623815
A10: 46182 | B10: La Cata LMF | C10: 33510 | D10: 11355 | E10: =D10*Setup!$B$5 | F10: =D10-E10 | G10: 0 | I10: 0 | J10: =C10+F10+G10-I10 | L10: =K10*Setup!$B$6 | M10: =J10-L10
A11: 46183 | B11: La Cata LMF | C11: 19035 | D11: 4460 | E11: =D11*Setup!$B$5 | F11: =D11-E11 | G11: 0 | I11: 0 | J11: =C11+F11+G11-I11 | L11: =K11*Setup!$B$6 | M11: =J11-L11
A12: 46184 | B12: La Cata LMF | C12: 14400 | D12: 9505 | E12: =D12*Setup!$B$5 | F12: =D12-E12 | G12: 0 | I12: 0 | J12: =C12+F12+G12-I12 | L12: =K12*Setup!$B$6 | M12: =J12-L12
A13: 46185 | B13: La Cata LMF | C13: 47335 | D13: 14035 | E13: =D13*Setup!$B$5 | F13: =D13-E13 | G13: 1290 | I13: 160 | J13: =C13+F13+G13-I13 | L13: =K13*Setup!$B$6 | M13: =J13-L13
A14: 46186 | B14: La Cata LMF | C14: 114934 | D14: 40440 | E14: =D14*Setup!$B$5 | F14: =D14-E14 | G14: 16775 | I14: 0 | J14: =C14+F14+G14-I14 | L14: =K14*Setup!$B$6 | M14: =J14-L14
A15: 46187 | B15: La Cata LMF | C15: 183535 | D15: 53845 | E15: =D15*Setup!$B$5 | F15: =D15-E15 | G15: 1740 | I15: 0 | J15: =C15+F15+G15-I15 | L15: =K15*Setup!$B$6 | M15: =J15-L15
A16: 46188 | B16: La Cata LMF | C16: 29567 | D16: 9435 | E16: =D16*Setup!$B$5 | F16: =D16-E16 | G16: 2765 | I16: 0 | J16: =C16+F16+G16-I16 | L16: =K16*Setup!$B$6 | M16: =J16-L16 | N16: 434840
A17: 46189 | B17: La Cata LMF | C17: 30559 | D17: 10346 | E17: =D17*Setup!$B$5 | F17: =D17-E17 | G17: 0 | I17: 0 | J17: =C17+F17+G17-I17 | L17: =K17*Setup!$B$6 | M17: =J17-L17
A18: 46190 | B18: La Cata LMF | C18: 37857 | D18: 27615 | E18: =D18*Setup!$B$5 | F18: =D18-E18 | G18: 0 | I18: 0 | J18: =C18+F18+G18-I18 | L18: =K18*Setup!$B$6 | M18: =J18-L18
A19: 46191 | B19: La Cata LMF | C19: 29700 | D19: 24095 | E19: =D19*Setup!$B$5 | F19: =D19-E19 | G19: 0 | I19: 0 | J19: =C19+F19+G19-I19 | L19: =K19*Setup!$B$6 | M19: =J19-L19
A20: 46192 | B20: La Cata LMF | C20: 65320 | D20: 37590 | E20: =D20*Setup!$B$5 | F20: =D20-E20 | G20: 420 | I20: 0 | J20: =C20+F20+G20-I20 | L20: =K20*Setup!$B$6 | M20: =J20-L20
A21: 46193 | B21: La Cata LMF | C21: 137440 | D21: 80635 | E21: =D21*Setup!$B$5 | F21: =D21-E21 | G21: 760 | I21: 0 | J21: =C21+F21+G21-I21 | L21: =K21*Setup!$B$6 | M21: =J21-L21
A22: 46194 | B22: La Cata LMF | C22: 151265 | D22: 65345 | E22: =D22*Setup!$B$5 | F22: =D22-E22 | G22: 3155 | I22: 0 | J22: =C22+F22+G22-I22 | L22: =K22*Setup!$B$6 | M22: =J22-L22
A23: 46195 | B23: La Cata LMF | C23: 24815 | D23: 16840 | E23: =D23*Setup!$B$5 | F23: =D23-E23 | G23: 600 | I23: 0 | J23: =C23+F23+G23-I23 | L23: =K23*Setup!$B$6 | M23: =J23-L23
A24: 46196 | B24: La Cata LMF | C24: 55010 | D24: 15505 | E24: =D24*Setup!$B$5 | F24: =D24-E24 | G24: 2660 | I24: 0 | J24: =C24+F24+G24-I24 | L24: =K24*Setup!$B$6 | M24: =J24-L24
A25: 46197 | B25: La Cata LMF | C25: 59190 | D25: 25428 | E25: =D25*Setup!$B$5 | F25: =D25-E25 | G25: 80 | I25: 0 | J25: =C25+F25+G25-I25 | L25: =K25*Setup!$B$6 | M25: =J25-L25
A26: 46198 | B26: La Cata LMF | C26: 54185 | D26: 25635 | E26: =D26*Setup!$B$5 | F26: =D26-E26 | G26: 1925 | I26: 0 | J26: =C26+F26+G26-I26 | L26: =K26*Setup!$B$6 | M26: =J26-L26
A27: 46199 | B27: La Cata LMF | C27: 46815 | D27: 32320 | E27: =D27*Setup!$B$5 | F27: =D27-E27 | G27: 375 | I27: 0 | J27: =C27+F27+G27-I27 | L27: =K27*Setup!$B$6 | M27: =J27-L27
A28: 46200 | B28: La Cata LMF | C28: 160930 | D28: 69930 | E28: =D28*Setup!$B$5 | F28: =D28-E28 | G28: 3160 | I28: 4585 | J28: =C28+F28+G28-I28 | L28: =K28*Setup!$B$6 | M28: =J28-L28
... A32: 46174 | B32: La Cata DF | C32: 4460 | D32: 3305 | E32: =D32*Setup!$B$5 | F32: =D32-E32 | G32: 0 | I32: 0 | J32: =C32+F32+G32-I32 | L32: =K32*Setup!$B$6 | M32: =J32-L32
A33: 46175 | B33: La Cata DF | E33: =D33*Setup!$B$5 | F33: =D33-E33 | G33: 0 | I33: 0 | J33: =C33+F33+G33-I33 | L33: =K33*Setup!$B$6 | M33: =J33-L33
A34: 46176 | B34: La Cata DF | E34: =D34*Setup!$B$5 | F34: =D34-E34 | G34: 0 | I34: 0 | J34: =C34+F34+G34-I34 | L34: =K34*Setup!$B$6 | M34: =J34-L34
A35: 46177 | B35: La Cata DF | E35: =D35*Setup!$B$5 | F35: =D35-E35 | G35: 0 | I35: 0 | J35: =C35+F35+G35-I35 | L35: =K35*Setup!$B$6 | M35: =J35-L35
A36: 46178 | B36: La Cata DF | E36: =D36*Setup!$B$5 | F36: =D36-E36 | G36: 0 | I36: 0 | J36: =C36+F36+G36-I36 | L36: =K36*Setup!$B$6 | M36: =J36-L36
A37: 46179 | B37: La Cata DF | E37: =D37*Setup!$B$5 | F37: =D37-E37 | G37: 0 | I37: 0 | J37: =C37+F37+G37-I37 | L37: =K37*Setup!$B$6 | M37: =J37-L37
A38: 46180 | B38: La Cata DF | E38: =D38*Setup!$B$5 | F38: =D38-E38 | G38: 0 | I38: 0 | J38: =C38+F38+G38-I38 | L38: =K38*Setup!$B$6 | M38: =J38-L38
A39: 46181 | B39: La Cata DF | E39: =D39*Setup!$B$5 | F39: =D39-E39 | G39: 0 | I39: 0 | J39: =C39+F39+G39-I39 | L39: =K39*Setup!$B$6 | M39: =J39-L39
A40: 46182 | B40: La Cata DF | E40: =D40*Setup!$B$5 | F40: =D40-E40 | G40: 0 | I40: 0 | J40: =C40+F40+G40-I40 | L40: =K40*Setup!$B$6 | M40: =J40-L40 | N40: 181328
A41: 46183 | B41: La Cata DF | E41: =D41*Setup!$B$5 | F41: =D41-E41 | G41: 0 | I41: 0 | J41: =C41+F41+G41-I41 | L41: =K41*Setup!$B$6 | M41: =J41-L41
A42: 46184 | B42: La Cata DF | E42: =D42*Setup!$B$5 | F42: =D42-E42 | G42: 0 | I42: 0 | J42: =C42+F42+G42-I42 | L42: =K42*Setup!$B$6 | M42: =J42-L42
A43: 46185 | B43: La Cata DF | E43: =D43*Setup!$B$5 | F43: =D43-E43 | G43: 0 | I43: 0 | J43: =C43+F43+G43-I43 | L43: =K43*Setup!$B$6 | M43: =J43-L43
A44: 46186 | B44: La Cata DF | E44: =D44*Setup!$B$5 | F44: =D44-E44 | G44: 0 | I44: 0 | J44: =C44+F44+G44-I44 | L44: =K44*Setup!$B$6 | M44: =J44-L44
A45: 46187 | B45: La Cata DF | E45: =D45*Setup!$B$5 | F45: =D45-E45 | G45: 0 | I45: 0 | J45: =C45+F45+G45-I45 | L45: =K45*Setup!$B$6 | M45: =J45-L45
A46: 46188 | B46: La Cata DF | E46: =D46*Setup!$B$5 | F46: =D46-E46 | G46: 0 | I46: 0 | J46: =C46+F46+G46-I46 | L46: =K46*Setup!$B$6 | M46: =J46-L46
A47: 46189 | B47: La Cata DF | E47: =D47*Setup!$B$5 | F47: =D47-E47 | G47: 0 | I47: 0 | J47: =C47+F47+G47-I47 | L47: =K47*Setup!$B$6 | M47: =J47-L47
A48: 46190 | B48: La Cata DF | E48: =D48*Setup!$B$5 | F48: =D48-E48 | G48: 0 | I48: 0 | J48: =C48+F48+G48-I48 | L48: =K48*Setup!$B$6 | M48: =J48-L48
A49: 46191 | B49: La Cata DF | E49: =D49*Setup!$B$5 | F49: =D49-E49 | G49: 0 | I49: 0 | J49: =C49+F49+G49-I49 | L49: =K49*Setup!$B$6 | M49: =J49-L49
A50: 46192 | B50: La Cata DF | E50: =D50*Setup!$B$5 | F50: =D50-E50 | G50: 0 | I50: 0 | J50: =C50+F50+G50-I50 | L50: =K50*Setup!$B$6 | M50: =J50-L50
A51: 46193 | B51: La Cata DF | E51: =D51*Setup!$B$5 | F51: =D51-E51 | G51: 0 | I51: 0 | J51: =C51+F51+G51-I51 | L51: =K51*Setup!$B$6 | M51: =J51-L51
A52: 46194 | B52: La Cata DF | E52: =D52*Setup!$B$5 | F52: =D52-E52 | G52: 0 | I52: 0 | J52: =C52+F52+G52-I52 | L52: =K52*Setup!$B$6 | M52: =J52-L52
... A61: 46203 | B61: La Cata DF | E61: =D61*Setup!$B$5 | F61: =D61-E61 | G61: 0 | I61: 0 | J61: =C61+F61+G61-I61 | L61: =K61*Setup!$B$6 | M61: =J61-L61
A63: 46143 | B63: La Cata LMF | C63: 78835 | D63: 13840 | E63: =D63*Setup!$B$5 | F63: =D63-E63 | G63: 320 | I63: 0 | J63: =C63+F63+G63-I63 | L63: =K63*Setup!$B$6 | M63: =J63-L63
A64: 46144 | B64: La Cata LMF | C64: 169855 | D64: 73995 | E64: =D64*Setup!$B$5 | F64: =D64-E64 | G64: 4420 | I64: 0 | J64: =C64+F64+G64-I64 | L64: =K64*Setup!$B$6 | M64: =J64-L64
A65: 46145 | B65: La Cata LMF | C65: 214184 | D65: 103654 | E65: =D65*Setup!$B$5 | F65: =D65-E65 | G65: 10870 | I65: 0 | J65: =C65+F65+G65-I65 | L65: =K65*Setup!$B$6 | M65: =J65-L65
A66: 46146 | B66: La Cata LMF | C66: 87074 | D66: 43820 | E66: =D66*Setup!$B$5 | F66: =D66-E66 | G66: 0 | I66: 0 | J66: =C66+F66+G66-I66 | L66: =K66*Setup!$B$6 | M66: =J66-L66 | N66: 511600
A67: 46147 | B67: La Cata LMF | C67: 28710 | D67: 5825 | E67: =D67*Setup!$B$5 | F67: =D67-E67 | G67: 705 | I67: 0 | J67: =C67+F67+G67-I67 | L67: =K67*Setup!$B$6 | M67: =J67-L67
A68: 46148 | B68: La Cata LMF | C68: 30240 | D68: 13490 | E68: =D68*Setup!$B$5 | F68: =D68-E68 | G68: 0 | I68: 0 | J68: =C68+F68+G68-I68 | L68: =K68*Setup!$B$6 | M68: =J68-L68
A69: 46149 | B69: La Cata LMF | C69: 31975 | D69: 15745 | E69: =D69*Setup!$B$5 | F69: =D69-E69 | G69: 0 | I69: 0 | J69: =C69+F69+G69-I69 | L69: =K69*Setup!$B$6 | M69: =J69-L69
A70: 46150 | B70: La Cata LMF | C70: 70085 | D70: 19935 | E70: =D70*Setup!$B$5 | F70: =D70-E70 | G70: 4050 | I70: 0 | J70: =C70+F70+G70-I70 | L70: =K70*Setup!$B$6 | M70: =J70-L70
A71: 46151 | B71: La Cata LMF | C71: 89085 | D71: 63415 | E71: =D71*Setup!$B$5 | F71: =D71-E71 | G71: 100 | I71: 0 | J71: =C71+F71+G71-I71 | L71: =K71*Setup!$B$6 | M71: =J71-L71
A72: 46152 | B72: La Cata LMF | C72: 148285 | D72: 54435 | E72: =D72*Setup!$B$5 | F72: =D72-E72 | G72: 5490 | I72: 0 | J72: =C72+F72+G72-I72 | L72: =K72*Setup!$B$6 | M72: =J72-L72
A73: 46153 | B73: La Cata LMF | C73: 25440 | D73: 2290 | E73: =D73*Setup!$B$5 | F73: =D73-E73 | G73: 0 | I73: 0 | J73: =C73+F73+G73-I73 | L73: =K73*Setup!$B$6 | M73: =J73-L73 | N73: 563100
A74: 46154 | B74: La Cata LMF | C74: 21960 | D74: 16180 | E74: =D74*Setup!$B$5 | F74: =D74-E74 | G74: 0 | I74: 0 | J74: =C74+F74+G74-I74 | L74: =K74*Setup!$B$6 | M74: =J74-L74
A75: 46155 | B75: La Cata LMF | C75: 36225 | D75: 7880 | E75: =D75*Setup!$B$5 | F75: =D75-E75 | G75: 3095 | I75: 0 | J75: =C75+F75+G75-I75 | L75: =K75*Setup!$B$6 | M75: =J75-L75
A76: 46156 | B76: La Cata LMF | C76: 23200 | D76: 6950 | E76: =D76*Setup!$B$5 | F76: =D76-E76 | G76: 0 | I76: 0 | J76: =C76+F76+G76-I76 | L76: =K76*Setup!$B$6 | M76: =J76-L76
A77: 46157 | B77: La Cata LMF | C77: 47765 | D77: 7255 | E77: =D77*Setup!$B$5 | F77: =D77-E77 | G77: 12820 | I77: 0 | J77: =C77+F77+G77-I77 | L77: =K77*Setup!$B$6 | M77: =J77-L77
A78: 46158 | B78: La Cata LMF | C78: 144732 | D78: 80333 | E78: =D78*Setup!$B$5 | F78: =D78-E78 | G78: 5885 | I78: 330 | J78: =C78+F78+G78-I78 | L78: =K78*Setup!$B$6 | M78: =J78-L78
A79: 46159 | B79: La Cata LMF | C79: 176873 | D79: 59965 | E79: =D79*Setup!$B$5 | F79: =D79-E79 | G79: 2980 | I79: 435 | J79: =C79+F79+G79-I79 | L79: =K79*Setup!$B$6 | M79: =J79-L79
A80: 46160 | B80: La Cata LMF | C80: 26545 | D80: 12780 | E80: =D80*Setup!$B$5 | F80: =D80-E80 | G80: 0 | I80: 0 | J80: =C80+F80+G80-I80 | L80: =K80*Setup!$B$6 | M80: =J80-L80 | N80: 478610
A81: 46161 | B81: La Cata LMF | C81: 27905 | D81: 6260 | E81: =D81*Setup!$B$5 | F81: =D81-E81 | G81: 600 | I81: 0 | J81: =C81+F81+G81-I81 | L81: =K81*Setup!$B$6 | M81: =J81-L81
A82: 46162 | B82: La Cata LMF | C82: 38255 | D82: 36870 | E82: =D82*Setup!$B$5 | F82: =D82-E82 | G82: 0 | I82: 0 | J82: =C82+F82+G82-I82 | L82: =K82*Setup!$B$6 | M82: =J82-L82
A83: 46163 | B83: La Cata LMF | C83: 34940 | D83: 15880 | E83: =D83*Setup!$B$5 | F83: =D83-E83 | G83: 2820 | I83: 0 | J83: =C83+F83+G83-I83 | L83: =K83*Setup!$B$6 | M83: =J83-L83
A84: 46164 | B84: La Cata LMF | C84: 70590 | D84: 37595 | E84: =D84*Setup!$B$5 | F84: =D84-E84 | G84: 1390 | I84: 0 | J84: =C84+F84+G84-I84 | L84: =K84*Setup!$B$6 | M84: =J84-L84
A85: 46165 | B85: La Cata LMF | C85: 112970 | D85: 53170 | E85: =D85*Setup!$B$5 | F85: =D85-E85 | G85: 0 | I85: 0 | J85: =C85+F85+G85-I85 | L85: =K85*Setup!$B$6 | M85: =J85-L85
A86: 46166 | B86: La Cata LMF | C86: 146790 | D86: 37750 | E86: =D86*Setup!$B$5 | F86: =D86-E86 | G86: 3810 | I86: 0 | J86: =C86+F86+G86-I86 | L86: =K86*Setup!$B$6 | M86: =J86-L86
A87: 46167 | B87: La Cata LMF | C87: 31965 | D87: 15365 | E87: =D87*Setup!$B$5 | F87: =D87-E87 | G87: 0 | I87: 0 | J87: =C87+F87+G87-I87 | L87: =K87*Setup!$B$6 | M87: =J87-L87 | N87: 461001
A88: 46168 | B88: La Cata LMF | C88: 30080 | D88: 16760 | E88: =D88*Setup!$B$5 | F88: =D88-E88 | G88: 0 | I88: 0 | J88: =C88+F88+G88-I88 | L88: =K88*Setup!$B$6 | M88: =J88-L88
A89: 46169 | B89: La Cata LMF | C89: 45115 | D89: 3325 | E89: =D89*Setup!$B$5 | F89: =D89-E89 | G89: 9840 | I89: 0 | J89: =C89+F89+G89-I89 | L89: =K89*Setup!$B$6 | M89: =J89-L89
A90: 46170 | B90: La Cata LMF | C90: 38977 | D90: 21462 | E90: =D90*Setup!$B$5 | F90: =D90-E90 | G90: 3155 | I90: 0 | J90: =C90+F90+G90-I90 | L90: =K90*Setup!$B$6 | M90: =J90-L90
A91: 46171 | B91: La Cata LMF | C91: 78460 | D91: 35475 | E91: =D91*Setup!$B$5 | F91: =D91-E91 | G91: 4750 | I91: 0 | J91: =C91+F91+G91-I91 | L91: =K91*Setup!$B$6 | M91: =J91-L91
A92: 46172 | B92: La Cata LMF | C92: 168585 | D92: 107360 | E92: =D92*Setup!$B$5 | F92: =D92-E92 | G92: 3010 | I92: 0 | J92: =C92+F92+G92-I92 | L92: =K92*Setup!$B$6 | M92: =J92-L92
A93: 46173 | B93: La Cata LMF | C93: 345921 | D93: 100290 | E93: =D93*Setup!$B$5 | F93: =D93-E93 | G93: 8335 | I93: 0 | J93: =C93+F93+G93-I93 | L93: =K93*Setup!$B$6 | M93: =J93-L93
A95: 46143 | B95: La Cata DF | C95: 19450 | D95: 4475 | E95: =D95*Setup!$B$5 | F95: =D95-E95 | G95: 0 | H95: 8145 | I95: 0 | J95: =C95+F95+G95-I95 | L95: =K95*Setup!$B$6 | M95: =J95-L95
A96: 46144 | B96: La Cata DF | C96: 20050 | D96: 14660 | E96: =D96*Setup!$B$5 | F96: =D96-E96 | G96: 0 | H96: 5033.75 | I96: 0 | J96: =C96+F96+G96-I96 | L96: =K96*Setup!$B$6 | M96: =J96-L96
A97: 46145 | B97: La Cata DF | C97: 14465 | D97: 4265 | E97: =D97*Setup!$B$5 | F97: =D97-E97 | G97: 0 | H97: 6060 | I97: 0 | J97: =C97+F97+G97-I97 | L97: =K97*Setup!$B$6 | M97: =J97-L97 | N97: 75670
A98: 46146 | B98: La Cata DF | C98: 11835 | D98: 11880 | E98: =D98*Setup!$B$5 | F98: =D98-E98 | G98: 0 | H98: 5185 | I98: 0 | J98: =C98+F98+G98-I98 | L98: =K98*Setup!$B$6 | M98: =J98-L98
A99: 46147 | B99: La Cata DF | C99: 3290 | D99: 2195 | E99: =D99*Setup!$B$5 | F99: =D99-E99 | G99: 0 | H99: 2795 | I99: 0 | J99: =C99+F99+G99-I99 | L99: =K99*Setup!$B$6 | M99: =J99-L99
A100: 46148 | B100: La Cata DF | C100: 3820 | D100: 3385 | E100: =D100*Setup!$B$5 | F100: =D100-E100 | G100: 1015 | H100: 590 | I100: 0 | J100: =C100+F100+G100-I100 | L100: =K100*Setup!$B$6 | M100: =J100-L100
A101: 46149 | B101: La Cata DF | C101: 8785 | D101: 1895 | E101: =D101*Setup!$B$5 | F101: 825 | G101: 0 | I101: 0 | J101: =C101+F101+G101-I101 | L101: =K101*Setup!$B$6 | M101: =J101-L101
A102: 46150 | B102: La Cata DF | C102: 21495 | D102: 5090 | E102: =D102*Setup!$B$5 | F102: =D102-E102 | G102: 2465 | I102: 0 | J102: =C102+F102+G102-I102 | L102: =K102*Setup!$B$6 | M102: =J102-L102
A103: 46151 | B103: La Cata DF | C103: 25390 | D103: 21460 | E103: =D103*Setup!$B$5 | F103: =D103-E103 | G103: 0 | H103: 7780 | I103: 0 | J103: =C103+F103+G103-I103 | L103: =K103*Setup!$B$6 | M103: =J103-L103
A104: 46152 | B104: La Cata DF | C104: 23405 | D104: 6490 | E104: =D104*Setup!$B$5 | F104: =D104-E104 | G104: 0 | H104: 5532.75 | I104: 0 | J104: =C104+F104+G104-I104 | L104: =K104*Setup!$B$6 | M104: =J104-L104
A105: 46153 | B105: La Cata DF | C105: 2045 | D105: 1515 | E105: =D105*Setup!$B$5 | F105: =D105-E105 | G105: 0 | H105: 1475 | I105: 0 | J105: =C105+F105+G105-I105 | L105: =K105*Setup!$B$6 | M105: =J105-L105
A106: 46154 | B106: La Cata DF | C106: 2885 | D106: 0 | E106: =D106*Setup!$B$5 | F106: 645 | G106: 0 | H106: 785 | I106: 0 | J106: =C106+F106+G106-I106 | L106: =K106*Setup!$B$6 | M106: =J106-L106 | N106: 97380
A107: 46155 | B107: La Cata DF | C107: 4225 | D107: 2065 | E107: =D107*Setup!$B$5 | F107: =D107-E107 | G107: 0 | H107: 6535 | I107: 0 | J107: =C107+F107+G107-I107 | L107: =K107*Setup!$B$6 | M107: =J107-L107
A108: 46156 | B108: La Cata DF | C108: 6545 | D108: 4915 | E108: =D108*Setup!$B$5 | F108: =D108-E108 | G108: 0 | H108: 4910 | I108: 0 | J108: =C108+F108+G108-I108 | L108: =K108*Setup!$B$6 | M108: =J108-L108
A109: 46157 | B109: La Cata DF | C109: 25150 | D109: 13270 | E109: =D109*Setup!$B$5 | F109: =D109-E109 | G109: 570 | H109: 7891 | I109: 0 | J109: =C109+F109+G109-I109 | L109: =K109*Setup!$B$6 | M109: =J109-L109
A110: 46158 | B110: La Cata DF | C110: 23455 | D110: 6725 | E110: =D110*Setup!$B$5 | F110: =D110-E110 | G110: 0 | H110: 2850.5 | I110: 0 | J110: =C110+F110+G110-I110 | L110: =K110*Setup!$B$6 | M110: =J110-L110
A111: 46159 | B111: La Cata DF | C111: 22195 | D111: 11150 | E111: =D111*Setup!$B$5 | F111: =D111-E111 | G111: 3350 | H111: 2560 | I111: 0 | J111: =C111+F111+G111-I111 | L111: =K111*Setup!$B$6 | M111: =J111-L111
A112: 46160 | B112: La Cata DF | C112: 9105 | D112: 600 | E112: =D112*Setup!$B$5 | F112: =D112-E112 | G112: 0 | H112: 155 | I112: 0 | J112: =C112+F112+G112-I112 | L112: =K112*Setup!$B$6 | M112: =J112-L112
A113: 46161 | B113: La Cata DF | C113: 1040 | D113: 0 | E113: =D113*Setup!$B$5 | F113: =D113-E113 | G113: 0 | H113: 310 | I113: 0 | J113: =C113+F113+G113-I113 | L113: =K113*Setup!$B$6 | M113: =J113-L113
...
